Workbook
Name FolderPath: #REF!

Sheet Plan Indicativo 2024 - 2027
A1: Meta de resultado | AC1: Programación física del cuatrienio | AG1: PROYECTOS | AM1: EJECUCIÓN 2024 | AP1: EJECUCIÓN 2025 | AS1: EJECUCIÓN 2026 | AV1: EJECUCIÓN ACUMULADA | AY1: 2024 | BJ1: 2025 | BU1: 2026 | CF1: 2027 | CQ1: GRAN TOTAL | CR1: OBSERVACIONES
AH2: PROGRAMADO | AI2: EJECUTADO-EJECUCIÓN | AJ2: PROGRAMADO | AK2: EJECUTADO-EJECUCIÓN
A3: Codigo Meta | B3: Serie Numero | C3: Línea Estratégica | D3: Indicador de resultado | E3: Línea base | F3: Unidad de Medida | G3: Año base | H3: Fuente | I3: Meta cuatrienio | J3: ODS | K3: Sector PDD | L3: Numero Programa PDD | M3: Programa PDD | N3: Sector de inversión | O3: Código del sector | P3: Programa Presupuestal | Q3: Código del programa | R3: Producto | S3: Código del producto | T3: Indicador de producto principal | U3: código de indicador principal | V3: Descripción | W3: Medido a través de | X3: Tiene EDT | Y3: Unidad de medida2 | Z3: Meta de cuatrenio | AA3: Tipo de Acumulación | AB3: Responsable | AC3: Meta Física Esperada 2024 | AD3: Meta Física Esperada 2025 | AE3: Meta Física Esperada 2026 | AF3: Meta Física Esperada 2027 | AG3: PROYECTOS 2024 | AH3: PROYECTOS Y/O GESTIONES PROGRAMADOS 2025 | AI3: PROYECTOS 2025 | AJ3: PROYECTOS/GESTIONES PROGRAMADAS 2026 | AK3: PROYECTOS 2026 | AL3: PROYECTOS 2027 | AM3: EJECUCIÓN 2024 | AN3: PORCENTAJE DE EJECUCIÓN 2024 | AO3: CATEGORÍA DE EJECUCIÓN FÍSICA 2024 | AP3: EJECUCIÓN 2025 | AQ3: PORCENTAJE DE EJECUCIÓN 2025 | AR3: CATEGORÍA DE EJECUCIÓN FÍSICA 2025 | AS3: EJECUCIÓN 2026 | AT3: PORCENTAJE DE EJECUCIÓN 2026 | AU3: CATEGORÍA DE EJECUCIÓN FÍSICA 2026 | AV3: EJECUCIÓN ACUMULADA | AW3: PORCENTAJE DE EJECUCIÓN ACUMULADA | AX3: CATEGORÍA DE EJECUCIÓN ACUMULADA | AY3: Programación Recursos propios ICLD24 | AZ3: Programación Recursos propios ICDE24 | BA3: Programación SGP Educación24 | BB3: Programación SGP Salud24 | BC3: Programación SGP APSB24 | BD3: Programación Cofinanciación Municipio24 | BE3: Programación Cofinanciación Nación24 | BF3: Programación Crédito24 | BG3: Programación Regalías24 | BH3: Programación Otras Fuentes24 | BI3: Programación TOTAL24 | BJ3: Programación Recursos propios ICLD25 | BK3: Programación Recursos propios ICDE25 | BL3: Programación SGP Educación25 | BM3: Programación SGP Salud25 | BN3: Programación SGP APSB25 | BO3: Programación Cofinanciación Municipio25 | BP3: Programación Cofinanciación Nación25 | BQ3: Programación Crédito25 | BR3: Programación Regalías25 | BS3: Programación Otras Fuentes25 | BT3: Programación TOTAL25 | BU3: Programación Recursos propios ICLD26 | BV3: Programación Recursos propios ICDE26 | BW3: Programación SGP Educación26 | BX3: Programación SGP Salud26 | BY3: Programación SGP APSB26 | BZ3: Programación Cofinanciación Municipio26 | CA3: Programación Cofinanciación Nación26 | CB3: Programación Crédito26 | CC3: Programación Regalías26 | CD3: Programación Otras Fuentes26 | CE3: Programación TOTAL26 | CF3: Programación Recursos propios ICLD27 | CG3: Programación Recursos propios ICDE27 | CH3: Programación SGP Educación27 | CI3: Programación SGP Salud27 | CJ3: Programación SGP APSB27 | CK3: Programación Cofinanciación Municipio27 | CL3: Programación Cofinanciación Nación27 | CM3: Programación Crédito27 | CN3: Programación Regalías27 | CO3: Programación Otras Fuentes27 | CP3: Programación TOTAL27 | CQ3: GRAN TOTAL | CR3: OBSERVACIONES SEGUIMIENTO | CS3: OBSERVACIONES
A4: MT001 | B4: 2 | C4: Transformación del Ser Humano | D4: Porcentaje de ejecución de las actividades del plan de acción de la “Política pública diferencial para la primera infancia, la infancia y adolescencia y el fortalecimiento familiar, porque en Sucre, ser niño, niña o adolescente cuenta, 2019-2029” | E4: 0,5 | F4: Porcentaje | G4: 2023 | H4: Informe de avance Politica para la primera infancia, la infancia y adolescencia y el fortalecimiento familiar | I4: 0,75 | J4: 3. Salud y bienestar | K4: Inclusión Social | L4: 1 | M4: Primera infancia, infancia y adolescencia con garantía de derechos y Oportunidades | N4: Inclusión Social y Reconciliación | O4: 41 | P4: Desarrollo integral de la primera infancia a la juventud, y fortalecimiento de las capacidades de las familias de niñas, niños y adolescentes | Q4: 4102 | R4: Servicio de protección integral a niños, niñas, adolescentes y jóvenes | S4: 4102052 | T4: Niños, niñas, adolescentes y jóvenes beneficiados | U4: 410205200 | V4: Servicios enfocados a garantizar los derechos fundamentales , la prevención de amenazas o vulneración y restablecimiento de derechos. | W4: Número de niños, niñas, adolescentes y jóvenes | X4: No | Y4: Número | Z4: 1500 | AA4: Acumulativo | AB4: Secretaria de Inclusión Social, Mujer y Equidad de Genero | AC4: 200 | AD4: 450 | AE4: 450 | AF4: 400 | AG4: APOYO A LA MESA DE PARTICIPACIÓN DE NIÑOS, NIÑAS Y ADOLESCENTES 2024 EN EL DEPATRTAMENTO DE SUCRE (BPIN: Por Gestión) (Meta del Proyecto: 1050) (Ejecución 2024: 1050) | AH4: FOMENTO Y FORTALECIMIENTO DE UNIDADES PRODUCTIVAS A FAMILIAS CON NIÑOS, NIÑAS Y ADOLECENTES TRABAJADORES EN EL DEPARTAMENTYO DE SUCRE (Tipo Banco: Banco de Gestiones) (Meta de la gestión: ) APOYO A LA MESA DE PARTICIPACIÓN DE NIÑOS, NIÑAS Y ADOLESCENTES CAMPAMENTO 2025 EN EL DEPARTAMENTO DE SUCRE (Tipo Banco: Banco de Gestiones) (Meta de la gestión: 26) IMPLEMENTACIÓN DE LA ESTRETEGIA MI TERRITORIO SIN VIOLENCIA (Tipo Banco: Banco de Gestiones) (Meta de la gestión: 574) FORTALECIMIENTO DE LA INICIATIVA PRESENTADA EN LAS MESAS SUBREGIONALES DE PARTICIPACIÓN DE NIÑOS, NIÑAS Y ADOLESCENTES (BPIN: ) (Tipo de Banco: Sin Tipo de Banco) | AI4: APOYO A LA MESA DE PARTICIPACIÓN DE NIÑOS, NIÑAS Y ADOLESCENTES CAMPAMENTO 2025 EN EL DEPARTAMENTO DE SUCRE (Tipo de banco: Banco de Gestiones) (Meta de la gestión: 26) (Ejecutado: 26) IMPLEMENTACIÓN DE LA ESTRETEGIA MI TERRITORIO SIN VIOLENCIA (Tipo de banco: Banco de Gestiones) (Meta de la gestión: 574) (Ejecutado: 643) | AJ4: MESAS REGIONALES DE NIÑOS, NIÑAS Y ADOLESCENTES 2026 Implementación DE ACCIONES DE APOYO PSICOSOCIAL COMO ESTRATEGIA FRENTE A LAS PROBLEMÁTICAS DE SALUD MENTAL EN EL DEPARTAMENTO DE Sucre (BPIN: 202500000050658) (Meta del proyecto: 1040) (Tipo de Banco: Banco Territorial) Desarrollo de talleres para la prevención de la violencia - campaña mi territorio sin violencia. (Meta Programada: 450) (Tipo de Banco: Banco de Gestiones) | AK4: Desarrollo de talleres para la prevención de la violencia - campaña mi territorio sin violencia. (Meta programada: 450) (Ejecución: 246) (Tipo de banco: Banco de Gestiones) | AL4: FORTALECIMIENTO DE LA INICIATIVA PRESENTADA EN LAS MESAS SUBREGIONALES DE PARTICIPACIÓN DE NIÑOS, NIÑAS Y ADOLESCENTES (Bpin: ) | AM4: 1050 | AN4: 1 | AO4: Superior | AP4: 669 | AQ4: 1 | AR4: Superior | AS4: 246 | AT4: 1 | AU4: Superior | AV4: 1965 | AW4: 1 | AX4: Superior | AY4: 60000000 | AZ4: 0 | BA4: 0 | BB4: 0 | BC4: 0 | BD4: 0 | BE4: 0 | BF4: 0 | BG4: 0 | BH4: 0 | BI4: 60000000 | BJ4: 63000000 | BK4: 0 | BL4: 0 | BM4: 0 | BN4: 0 | BO4: 0 | BP4: 0 | BQ4: 0 | BR4: 0 | BS4: 0 | BT4: 63000000 | BU4: 66150000 | BV4: 0 | BW4: 0 | BX4: 0 | BY4: 0 | BZ4: 0 | CA4: 0 | CB4: 0 | CC4: 0 | CD4: 0 | CE4: 66150000 | CF4: 69457500 | CG4: 0 | CH4: 0 | CI4: 0 | CJ4: 0 | CK4: 0 | CL4: 0 | CM4: 0 | CN4: 0 | CO4: 0 | CP4: 69457500 | CQ4: 258607500 | CR4: 03/10/2024: se reviso la meta establecida con la profesional encargada de esta y se determino un error en el establecimiento de esta, solicita bajar de 1500 a 800 como esta la distribución por vigencia, teniendo en cuenta que esta meta ya se encuentra aprobada por asamblea, no puede hacerse una reducción, por lo que se solicita redistribución en vigencias, Actividad realizada por Gestión. | CS4: Campaña para el fomento del acceso de los niños, niñas y adolescentes a las ofertas institucionales y campaña mi territorio sin violencias.
A5: MT002 | B5: 3 | C5: Transformación del Ser Humano | D5: Porcentaje de ejecución de las actividades del plan de acción de la “Política pública diferencial para la primera infancia, la infancia y adolescencia y el fortalecimiento familiar, porque en Sucre, ser niño, niña o adolescente cuenta, 2019-2029” | E5: 0,5 | F5: Porcentaje | G5: 2023 | H5: Informe de avance Politica para la primera infancia, la infancia y adolescencia y el fortalecimiento familiar | I5: 0,75 | J5: 3. Salud y bienestar | K5: Inclusión Social | L5: 1 | M5: Primera infancia, infancia y adolescencia con garantía de derechos y Oportunidades | N5: Gobierno Territorial | O5: 45 | P5: Fortalecimiento del buen gobierno para el respeto y garantía de los derechos humanos | Q5: 4502 | R5: Servicio de educación informal | S5: 4502034 | T5: Personas Capacitadas | U5: 450203400 | V5: Corresponde al diseño y desarrollo de estrategias educativas que tienen como objetivo brindar oportunidades para apropiar, complementar, actualizar, perfeccionar, renovar o profundizar conocimientos, habilidades, técnicas y prácticas, este conocimiento libre y espontáneo adquirido, puede provenir de personas, entidades, medios masivos de comunicación, medios impresos, tradiciones, costumbres, comportamientos sociales y otros no estructurados y su duración es inferior a 160 horas. | W5: Número de personas | X5: No | Y5: Número | Z5: 200 | AA5: Acumulativo | AB5: Secretaria de Inclusión Social, Mujer y Equidad de Genero | AC5: 50 | AD5: 50 | AE5: 50 | AF5: 50 | AG5: CAPACITACION EN DERECHO INTERNACIONAL HUMANITARIO CON ENFASIS EN RECLUTAMIENTO (BPIN: Por Gestión) (Meta del Proyecto: 50) (Ejecución 2024: 50) MESAS DE PARTICIPACION DE NIÑAS, NIÑOS Y ADOLESCENTES (BPIN: Por Gestión) (Meta del Proyecto: 180) (Ejecución 2024: 180) CAPACITACIÓN A NIÑOS, NIÑAS Y ADOLESCENTES COMO DEFENSORES Y DEFENSORITOS (BPIN: Por Gestión) (Meta del Proyecto: 100) (Ejecución 2024: 100) | AJ5: IMPLEMENTACIÓN DE LA ESTRETEGIA MI TERRITORIO SIN VIOLENCIA (BPIN: Por Gestión) CAPACITACIÓN A NIÑOS, NIÑAS Y ADOLESCENTES (BPIN: Por Gestión) Jornada de sencibilización sobre cuidado ambiental en articulación con interaseo (Meta Programada: 50) (Tipo de Banco: Banco de Gestiones) | AK5: Jornada de sencibilización sobre cuidado ambiental en articulación con interaseo (Meta programada: 50) (Ejecución: 53) (Tipo de banco: Banco de Gestiones) | AL5: IMPLEMENTACIÓN DE LA ESTRETEGIA MI TERRITORIO SIN VIOLENCIA (Bpin: Por Gestión) CAPACITACIÓN A NIÑOS, NIÑAS Y ADOLESCENTES (Bpin: Por Gestión) | AM5: 330 | AN5: 1 | AO5: Superior | AP5: 0 | AQ5: 1 | AR5: Superior | AS5: 53 | AT5: 1 | AU5: Superior | AV5: 383 | AW5: 1 | AX5: Superior | AY5: 14000000 | AZ5: 0 | BA5: 0 | BB5: 0 | BC5: 0 | BD5: 0 | BE5: 0 | BF5: 0 | BG5: 0 | BH5: 0 | BI5: 14000000 | BJ5: 14700000 | BK5: 0 | BL5: 0 | BM5: 0 | BN5: 0 | BO5: 0 | BP5: 0 | BQ5: 0 | BR5: 0 | BS5: 0 | BT5: 14700000 | BU5: 15435000 | BV5: 0 | BW5: 0 | BX5: 0 | BY5: 0 | BZ5: 0 | CA5: 0 | CB5: 0 | CC5: 0 | CD5: 0 | CE5: 15435000 | CF5: 16206750 | CG5: 0 | CH5: 0 | CI5: 0 | CJ5: 0 | CK5: 0 | CL5: 0 | CM5: 0 | CN5: 0 | CO5: 0 | CP5: 16206750 | CQ5: 60341750 | CR5: El proyecto de mi territorio sin violencia, está programado para 2025, 2026 y 2027 en cumplimiento de la política pública. Sin embargo, se tiene una estrategia del plan de desarrollo que se gestionaría por valor de $3000 millones, si esta se gestiona, no hay necesidad de hacer cada año los proyectos pequeños 03/10/2024: Se encuentra una discrepancia engtre la meta de cuatrenio que se encuentra en 200 y las metas por vigencias que estan por 100, dando una cantidad de 400, por lo cual se procede de confornidad a lo definido por el profesional a ajustar la meta de cuatrenio a 400. | CS5: Funcionarios capacitados y mujeres capacitadas con formaciònes para el trabajo y su autonomia productiva, Campañas de prevenciòn de la fobia, bifobia y transfobia. Niños, niñas y adolescentes formados y capacitados
A6: MT003 | B6: 3 | C6: Transformación del Ser Humano | D6: Porcentaje de ejecución de las actividades del Plan de Acción de la Política Pública Departamental de Juventudes "Sucre Territorio Joven" | E6: 0,26700000000000002 | F6: Porcentaje | G6: 2023 | H6: Informe Polìtica Pùblica Departamental de Juventudes | I6: 0,5 | J6: 3. Salud y bienestar | K6: Inclusión Social | L6: 2 | M6: Sucre territorio Joven | N6: Trabajo | O6: 36 | P6: Generación y formalización del empleo | Q6: 3602 | R6: Servicio de gestión para el emprendimiento solidario | S6: 3602003 | T6: Emprendimientos solidarios dinamizados | U6: 360200300 | V6: Se trata de la gestión que realiza Organizaciones Solidarias para la conformación de emprendimientos. Esto podrá incluir conformación, fortalecimiento, asesoría, empresas, modelo de evaluación, personas sensibilizadas, entre otros, que oriente la creación y fortalecimiento de dichas organizaciones. | W6: Número de emprendimientos solidarios | X6: No | Y6: Número | Z6: 500 | AA6: Acumulativo | AB6: Secretaria de Inclusión Social, Mujer y Equidad de Genero | AC6: 40 | AD6: 0 | AE6: 310 | AF6: 150 | AG6: APOYO LOGISTICO PARA LA IMPLEMENTACIÓN DEL LABORATORIO DE EMPREDIMIENTO PARA JOVENES VULNERABLES DEL DEPARTAMENTO DE SUCRE (BPIN: Por Gestión) (Meta del Proyecto: 300) (Ejecución 2024: 32) | AH6: APOYO LOGISTICO PARA LA IMPLEMENTACIÓN DEL LABORATORIO DE EMPREDIMIENTO PARA JOVENES VULNERABLES DEL DEPARTAMENTO DE SUCRE (Tipo Banco: Banco de Gestiones) (Meta de la gestión: ) IMPLEMENTACIÓN DE ACCIONES DE APOYO INTEGRAL PARA EL FORTALECIMIENTO ECONÓMICO Y EL CUMPLIMIENTO DE LA POLÍTICA PÚBLICA DEPARTAMENTAL DE JÓVENES EN EL DEPARTAMENTO DE SUCRE (Tipo Banco: Banco de Gestiones) (Meta de la gestión: 1500) | AM6: 32 | AN6: 0.8 | AO6: Alto | AT6: 0 | AU6: Minimo | AV6: 32 | AW6: 0.064 | AX6: Minimo | AY6: 50000000 | AZ6: 0 | BA6: 0 | BB6: 0 | BC6: 0 | BD6: 0 | BE6: 0 | BF6: 0 | BG6: 0 | BH6: 0 | BI6: 50000000 | BJ6: 52500000 | BK6: 0 | BL6: 0 | BM6: 0 | BN6: 0 | BO6: 0 | BP6: 0 | BQ6: 0 | BR6: 0 | BS6: 0 | BT6: 52500000 | BU6: 55125000 | BV6: 0 | BW6: 0 | BX6: 0 | BY6: 0 | BZ6: 0 | CA6: 0 | CB6: 0 | CC6: 0 | CD6: 0 | CE6: 55125000 | CF6: 57881250 | CG6: 0 | CH6: 0 | CI6: 0 | CJ6: 0 | CK6: 0 | CL6: 0 | CM6: 0 | CN6: 0 | CO6: 0 | CP6: 57881250 | CQ6: 215506250 | CR6: Indican que para 1000 jóvenes pero la meta es 500 03/10/2024: Se indica que para el mes de noviembre se realizara un laboratorio de emprendimiento e innovación con el cual se alcanzara la meta de 500 emprendimientos, esto por Gestión. Se tienen programada la realización del evento para el 28 y 29 de Novimebtre. | CS6: Jovenes capacitidos para el fomento del empredimiento
A7: MT004 | B7: 4 | C7: Transformación del Ser Humano | D7: Porcentaje de ejecución de las actividades del Plan de Acción de la Política Pública Departamental de Juventudes "Sucre Territorio Joven" | E7: 0,26700000000000002 | F7: Porcentaje | G7: 2023 | H7: Informe Polìtica Pùblica Departamental de Juventudes | I7: 0,5 | J7: 3. Salud y bienestar | K7: Inclusión Social | L7: 2 | M7: Sucre territorio Joven | N7: Inclusión Social y Reconciliación | O7: 41 | P7: Desarrollo integral de la primera infancia a la juventud, y fortalecimiento de las capacidades de las familias de niñas, niños y adolescentes | Q7: 4102 | R7: Servicio de asistencia técnica en el ciclo de políticas públicas de familia y otras relacionadas | S7: 4102041 | T7: Instituciones y entidades asistidas técnicamente | U7: 410204100 | V7: Comprende la capacitación, asesoría y acompañamiento en el diseño e implementación de programas dirigidos a las familias y a la garantía de sus derechos y los de sus integrantes . | W7: Número de instituciones y organizaciones | X7: No | Y7: Número | Z7: 26 | AA7: No acumulativo | AB7: Secretaria de Inclusión Social, Mujer y Equidad de Genero | AC7: 26 | AD7: 26 | AE7: 26 | AF7: 26 | AG7: FORTALECIMIENTO A LOS SISTEMAS DE PARTICIPACIÓN JUVENIL MUNICIPALES (BPIN: Por Gestión) (Meta del Proyecto: 24) (Ejecución 2024: 24) | AH7: ASISTENCIAS TECNICAS A LOS SUBSISTEMAS DE PARTICIPACIÓN JUVENIL MUNICIPALES. (Tipo Banco: Banco de Gestiones) (Meta de la gestión: 26) | AI7: ASISTENCIAS TECNICAS A LOS SUBSISTEMAS DE PARTICIPACIÓN JUVENIL MUNICIPALES. (Tipo de banco: Banco de Gestiones) (Meta de la gestión: 26) (Ejecutado: 26) | AJ7: FORTALECIMIENTO A LOS SISTEMAS DE PARTICIPACIÓN JUVENIL MUNICIPALES (Por Gestión) (BPIN: Por Gestión) (Tipo de Banco: Sin Tipo de Banco) | AL7: FORTALECIMIENTO A LOS SISTEMAS DE PARTICIPACIÓN JUVENIL MUNICIPALES (Bpin: Por Gestión) | AM7: 24 | AN7: 0.92307692 | AO7: Alto | AP7: 26 | AQ7: 1 | AR7: Superior | AT7: 0 | AU7: Minimo | AV7: 50 | AW7: 1 | AX7: Superior | AY7: 30000000 | AZ7: 0 | BA7: 0 | BB7: 0 | BC7: 0 | BD7: 0 | BE7: 0 | BF7: 0 | BG7: 0 | BH7: 0 | BI7: 30000000 | BJ7: 31500000 | BK7: 0 | BL7: 0 | BM7: 0 | BN7: 0 | BO7: 0 | BP7: 0 | BQ7: 0 | BR7: 0 | BS7: 0 | BT7: 31500000 | BU7: 33075000 | BV7: 0 | BW7: 0 | BX7: 0 | BY7: 0 | BZ7: 0 | CA7: 0 | CB7: 0 | CC7: 0 | CD7: 0 | CE7: 33075000 | CF7: 34728750 | CG7: 0 | CH7: 0 | CI7: 0 | CJ7: 0 | CK7: 0 | CL7: 0 | CM7: 0 | CN7: 0 | CO7: 0 | CP7: 34728750 | CQ7: 129303750 | CR7: 03/10/2024: Se ha brindado asistencia técnica a los sistemas de participación juvenil municipales, Por Gestión, se tenia previsto la formulación de un proyecto pero este no cuenta con financiación. Se brindo asistencia a las dependencias encargadas de juventud de cada municipio -enlaces de juventud o secretarios de gobierno y miembros de consejos y plataformas municipales de juventud, faltando solo los municipios de Sampues y Majagual. | CS7: Fortalecer y hacer seguimiento a la Ruta Integral de Atenciones -RIA del Departamento.y observatorios de familia operando en el departamento de Sucre
A8: MT005 | B8: 2 | C8: Transformación del Ser Humano | D8: Porcentaje de ejecución de las actividades del Plan de acción de la Política Pública para el fortalecimiento integral de las familias de sucre 2023-2037 | E8: 0 | F8: Porcentaje | G8: 2023 | H8: Informe de avance Política Pública para el fortalecimiento integral de las familias | I8: 0,25 | J8: 3. Salud y bienestar 10- Reducción de las desigualdades. | K8: Inclusión Social | L8: 3 | M8: Familias con Oportunidades | N8: Inclusión Social y Reconciliación | O8: 41 | P8: Desarrollo integral de la primera infancia a la juventud, y fortalecimiento de las capacidades de las familias de niñas, niños y adolescentes | Q8: 4102 | R8: Servicio de asistencia técnica en el ciclo de políticas públicas de familia y otras relacionadas | S8: 4102041 | T8: Instituciones y entidades asistidas técnicamente | U8: 410204100 | V8: Comprende la capacitación, asesoría y acompañamiento en el diseño e implementación de programas dirigidos a las familias y a la garantía de sus derechos y los de sus integrantes . | W8: Número de instituciones y organizaciones | X8: No | Y8: Número | Z8: 26 | AA8: No acumulativo | AB8: Secretaria de Inclusión Social, Mujer y Equidad de Genero | AC8: 26 | AD8: 26 | AE8: 26 | AF8: 26 | AG8: ASISTENCIA TÉCNICA A LOS 26 OBSERVATORIOS MUNICIPALES DE SUCRE (BPIN: Por Gestión) (Meta del Proyecto: 26) (Ejecución 2024: 26) | AH8: Realizar asistencias tecnicas a los 26 observatorios creados en los 26 mucipios del departamento de sucre, en el fortalecimiento institucional. (Tipo Banco: Banco de Gestiones) (Meta de la gestión: 26) FORTALECIMIENTO INSTITUCIONAL DE LOS OBSERVATORIOS DE FAMILIA EN EL DEPARTAMENTO DE SUCRE (BPIN: ) (Tipo de Banco: Banco Territorial) | AI8: Realizar asistencias tecnicas a los 26 observatorios creados en los 26 mucipios del departamento de sucre, en el fortalecimiento institucional. (Tipo de banco: Banco de Gestiones) (Meta de la gestión: 26) (Ejecutado: 26) | AJ8: ASISTENCIA TÉCNICA A LOS 26 OBSERVATORIOS MUNICIPALES DE SUCRE (Tipo de Banco: Sin Tipo de Banco) Implementación DE ACCIONES DE APOYO PSICOSOCIAL COMO ESTRATEGIA FRENTE A LAS PROBLEMÁTICAS DE SALUD MENTAL EN EL DEPARTAMENTO DE Sucre (BPIN: 202500000050658) (Meta del proyecto: 26) (Tipo de Banco: Banco Territorial) Asistencia técnica virtual a los observatorios municipales de familia del Departamento de Sucre, en lo relacionado en la implementación de la politica pública de familia y al plan de desarrollo. (Meta Programada: 26) (Tipo de Banco: Banco de Gestiones) | AK8: Asistencia técnica virtual a los observatorios municipales de familia del Departamento de Sucre, en lo relacionado en la implementación de la politica pública de familia y al plan de desarrollo. (Meta programada: 26) (Ejecución: 19) (Tipo de banco: Banco de Gestiones) | AL8: ASISTENCIA TÉCNICA A LOS 26 OBSERVATORIOS MUNICIPALES DE SUCRE (Bpin: ) (Tipo de banco: Sin Tipo de Banco) | AM8: 26 | AN8: 1 | AO8: Superior | AP8: 26 | AQ8: 1 | AR8: Superior | AS8: 19 | AT8: 0.73076923 | AU8: Alto | AV8: 71 | AW8: 1 | AX8: Superior | AY8: 30000000 | AZ8: 0 | BA8: 0 | BB8: 0 | BC8: 0 | BD8: 0 | BE8: 0 | BF8: 0 | BG8: 0 | BH8: 0 | BI8: 30000000 | BJ8: 31500000 | BK8: 0 | BL8: 0 | BM8: 0 | BN8: 0 | BO8: 0 | BP8: 0 | BQ8: 0 | BR8: 0 | BS8: 0 | BT8: 31500000 | BU8: 33075000 | BV8: 0 | BW8: 0 | BX8: 0 | BY8: 0 | BZ8: 0 | CA8: 0 | CB8: 0 | CC8: 0 | CD8: 0 | CE8: 33075000 | CF8: 34728750 | CG8: 0 | CH8: 0 | CI8: 0 | CJ8: 0 | CK8: 0 | CL8: 0 | CM8: 0 | CN8: 0 | CO8: 0 | CP8: 34728750 | CQ8: 129303750 | CR8: El año 2024 se va a hacer por gestión | CS8: Fortalecer y hacer seguimiento a la Ruta Integral de Atenciones -RIA del Departamento.y observatorios de familia operando en el departamento de Sucre
A9: MT006 | B9: 1 | C9: Transformación del Ser Humano | D9: Porcentaje de ejecución de las actividades del plan de acción de la “Política pública diferencial para la primera infancia, la infancia y adolescencia y el fortalecimiento familiar, porque en Sucre, ser niño, niña o adolescente cuenta, 2019-2029” | E9: 0,5 | F9: Porcentaje | G9: 2023 | H9: Informe de avance Politica para la primera infancia, la infancia y adolescencia y el fortalecimiento familiar | I9: 0,75 | J9: 3. Salud y bienestar | K9: Inclusión Social | L9: 1 | M9: Primera infancia, infancia y adolescencia con garantía de derechos y Oportunidades | N9: Inclusión Social y Reconciliación | O9: 41 | P9: Desarrollo integral de la primera infancia a la juventud, y fortalecimiento de las capacidades de las familias de niñas, niños y adolescentes | Q9: 4102 | R9: Servicio de atención integral a la primera infancia | S9: 4102001 | T9: Niños y niñas atendidos en Servicio integrales | U9: 410200100 | V9: Servicio dispuestos para atender a los niños y niñas en primera infancia, con el fin de promover su desarrollo integral a través de la atención en educación inicial, cuidado calificado, salud, nutrición, protección y acompañamiento familiar. | W9: Número de niños y niñas | X9: No | Y9: Número | Z9: 1230 | AA9: No acumulativo | AB9: Secretaria de Inclusión Social, Mujer y Equidad de Genero | AC9: 1230 | AD9: 1230 | AE9: 1230 | AF9: 1230 | AG9: APOYO PARA LA REALIZACIÓN DE ACTIVIDADES CULTURALES Y RECREATIVAS EN EL MARCO DEL MES DE LA NIÑEZ EN EL DEPARTAMENTO DE SUCRE (BPIN: 2024002700041) (Meta del Proyecto: 1769) (Ejecución 2024: 1769) | AH9: APOYO NUTRICIONAL A NIÑAS Y NIÑOS DE LA PRIMERA INFANCIA CON DESNUTRICIÓN Y EN RIESGO DE DESNUTRICIÓN EN EL DEPARTAMENTO DE SUCRE (BPIN: ) (Tipo de Banco: Banco Territorial) APOYO PARA LA REALIZACIÓN DE ACTIVIDADES RECREATIVAS Y LÚDICAS EN EL MARCO DEL MES DE LA NIÑEZ VIGENCIA 2025, EN EL DEPARTAMENTO DE SUCRE (BPIN: 202400000004298) (Tipo de Banco: Banco Territorial) APOYO NUTRICIONAL A FAMILIAS CON NIÑAS Y NIÑOS MENORES DE 5 AÑOS CON DESNUTRICIÓN Y RIESGO DE DESNUTRICIÓN EN EL DEPARTAMENTO DE SUCRE (BPIN: ) (Tipo de Banco: Banco Territorial) APOYO PARA LA ELABORACIÓN E IMPLEMENTACIÓN DEL MAPA DE LA RUTA INTEGRAL DE ATENCIÓN A LA PRIMERA INFANCIA Y ADOLESCENCIA - RIA EN LOS MUNICIPIOS DEL DEPARTAMENTO DE SUCRE (BPIN: 2024002700095) (Tipo de Banco: Banco Territorial) | AI9: Apoyo PARA LA ELABORACIÓN E IMPLEMENTACIÓN DEL MAPA DE LA RUTA INTEGRAL DE ATENCIÓN A LA PRIMERA INFANCIA Y ADOLESCENCIA - RIA EN LOS MUNICIPIOS DEL DEPARTAMENTO DE Sucre (Bpin: 2024002700095) (Tipo de Banco: Banco Territorial) (Meta total del indicador: 70081.0) (Meta total de la vigencia: 70081.0) (Ejecutado: 70081.0) Apoyo para la realización de actividades recreativas y lúdicas en el marco del mes de la niñez Vigencia 2025, en el Departamento de Sucre (Bpin: 202400000004298) (Tipo de Banco: Banco Territorial) (Meta total del indicador: 1320.0) (Meta total de la vigencia: 1320.0) (Ejecutado: 1320.0) | AJ9: Apoyo PARA LA REALIZACIÓN DE ACTIVIDADES RECREATIVAS, DE EMPRENDIMIENTO, JUEGO, CIENCIA Y TECNOLOGIA A NIÑOS Y NIÑAS DEL DEPARTAMENTO DE Sucre (BPIN: 202500000050596) (Meta del proyecto: 1358) (Tipo de Banco: Banco Territorial) (Estado en Portafolio: En Ejecución) APOYO PARA LA REALIZACIÓN DE ACTIVIDADES CULTURALES Y RECREATIVAS EN EL MARCO DEL MES DE LA NIÑEZ EN EL DEPARTAMENTO DE SUCRE (Tipo de Banco: Sin Tipo de Banco) FORTALECIMIENTO NUTRICIONAL A NIÑOS MENORES DE 5 AÑOS EN RIESGO DE DESNUTRICIÓN EN EL DEPARTAMENTO DE SUCRE (Tipo de Banco: Sin Tipo de Banco) | AL9: APOYO PARA LA REALIZACIÓN DE ACTIVIDADES CULTURALES Y RECREATIVAS EN EL MARCO DEL MES DE LA NIÑEZ EN EL DEPARTAMENTO DE SUCRE (Pendiente por formular) (Bpin: ) (Tipo de banco: Sin Tipo de Banco) FORTALECIMIENTO NUTRICIONAL A NIÑOS MENORES DE 5 AÑOS EN RIESGO DE DESNUTRICIÓN EN EL DEPARTAMENTO DE SUCRE (Bpin: ) (Tipo de banco: Sin Tipo de Banco) | AM9: 1769 | AN9: 1 | AO9: Superior | AP9: 71401 | AQ9: 1 | AR9: Superior | AT9: 1 | AU9: Superior | AV9: 73170 | AW9: 1 | AX9: Superior | AY9: 150000000 | AZ9: 0 | BA9: 0 | BB9: 0 | BC9: 0 | BD9: 0 | BE9: 0 | BF9: 0 | BG9: 0 | BH9: 0 | BI9: 150000000 | BJ9: 157500000 | BK9: 0 | BL9: 0 | BM9: 0 | BN9: 0 | BO9: 0 | BP9: 0 | BQ9: 0 | BR9: 0 | BS9: 0 | BT9: 157500000 | BU9: 165375000 | BV9: 0 | BW9: 0 | BX9: 0 | BY9: 0 | BZ9: 0 | CA9: 0 | CB9: 0 | CC9: 0 | CD9: 0 | CE9: 165375000 | CF9: 173643750 | CG9: 0 | CH9: 0 | CI9: 0 | CJ9: 0 | CK9: 0 | CL9: 0 | CM9: 0 | CN9: 0 | CO9: 0 | CP9: 173643750 | CQ9: 646518750 | CR9: Se dio orientación de mantenimiento porque se está programando sobrecumplir la meta con los proyectos que asociaron Se alcanzo el cumplimiento de la meta con la ejecución APOYO PARA LA REALIZACIÓN DE ACTIVIDADES CULTURALES Y RECREATIVAS EN EL MARCO DEL MES DE LA NIÑEZ EN EL DEPARTAMENTO DE SUCRE (2024002700041), en el cual se beneficiaror 1,769 niños y niñas 03/10/2024: se tenia una meta de 1230 por mantenimiento, en conversacion la profesional tresponsable de la meta detecta un error y solicita subir la meta a 1500 para el mes de la niñez. Se elimina la iniciativa IMPLEMEMENTACIÓN DEL PROGRAMA DE PUERICULTURA (Pendiente por formular), y se incluye en la iniciativa IMPLEMENTACIÓN DE LA ESTRETEGIA MI TERRITORIO SIN VIOLENCIA (Pendiente por formular) | CS9: Estrategia "mi territorio sin violencias", redes de instituciones y servicios destinados a la atención de la primera infancia y conmemoraciòn del mes del niño.
A10: MT007 | B10: 1 | C10: Transformación del Ser Humano | D10: Porcentaje de ejecución de las actividades del Plan de Acción de la Política Pública Departamental de Juventudes "Sucre Territorio Joven" | E10: 0,26700000000000002 | F10: Porcentaje | G10: 2023 | H10: Informe Polìtica Pùblica Departamental de Juventudes | I10: 0,5 | J10: 3. Salud y bienestar | K10: Inclusión Social | L10: 2 | M10: Sucre territorio Joven | N10: Gobierno Territorial | O10: 45 | P10: Fortalecimiento del buen gobierno para el respeto y garantía de los derechos humanos | Q10: 4502 | R10: Servicio de promoción a la participación ciudadana | S10: 4502001 | T10: Espacios de participación promovidos | U10: 450200100 | V10: Corresponde al diseño e implementación de acciones y estrategias que promuevan el ejercicio de la participación ciudadana para el respeto y garantía de los derechos humanos | W10: Número de iniciativas | X10: No | Y10: Número | Z10: 108 | AA10: Acumulativo | AB10: Secretaria de Inclusión Social, Mujer y Equidad de Genero | AC10: 16 | AD10: 31 | AE10: 31 | AF10: 30 | AG10: APOYO LOGÍSTICO PARA LA CONMEMORACIÓN DEL MES DE LA JUVENTUD EN EL DEPARTAMENTO DE SUCRE (BPIN: 2024002700096) (Meta del Proyecto: 9) (Ejecución 2024: 9) APOYO A LA PRIMERA CUMBRE REGIONAL DE JOVENES CARIBE 2024 EN EL DEPARTAMENTO DE SUCRE (BPIN: Por Gestión) (Meta del Proyecto: 1) (Ejecución 2024: 1) | AH10: Jornadas de promoción en las instituciones educativas para promover la participación de los jovenes en las elecciones de Consejos de Juventud Municipales. (Tipo Banco: Banco de Gestiones) (Meta de la gestión: 31) Apoyo logístico para la conmemoración del mes de la juventud 2025 en el Departamento de Sucre (BPIN: 202500000028886) (Tipo de Banco: Banco Territorial) APOYO A LA ENTREGA DE ESTÍMULOS DE CARÁCTER EDUCATIVO, CULTURAL Y RECREATIVO PARA LOS CONSEJEROS Y PLATAFORMADOS DEPARTAMENTALES DE JUVENTUD Y SUMINISTRO DE ELEMENTOS DE APOYO AL SISTEMA DE PARTICIPACIÓN JUVENIL DEL DEPARTAMENTO DE SUCRE (BPIN: ) (Tipo de Banco: Banco Territorial) APOYO AL FORTALECIMIENTO DEL SISTEMA DE PARTICIPACIÓN JUVENIL DURANTE LAS VIGENCIAS 2025 - 2026 EN EL DEPARTAMENTO DE SUCRE (BPIN: 202500000028900) (Tipo de Banco: Banco Territorial) APOYO LOGISTICO PARA EL FORTALECIMIENTO DEL SISTEMA DE PARTICIPACIÓN JUVENIL EN EL DEPARTAMENTO DE SUCRE (BPIN: 202400000001355) (Tipo de Banco: Banco Territorial) APOYO PARA EL FORTALECIMIENTO DEL SISTEMA DE PARTICIPACION JUVENIL DURANTE LAS VIGENCIAS 2025 - 2026 EN EL DEPARTAMENTO DE SUCRE (BPIN: ) (Tipo de Banco: Banco Territorial) APOYO LOGISTICO PARA LA CONMEMORACIÓN DEL MES DE LA JUVENTUD 2025 EN EL DEPARTAMENTO DE SUCRE (BPIN: ) (Tipo de Banco: Banco Territorial) | AI10: Apoyo logístico para la conmemoración del mes de la juventud 2025 en el Departamento de Sucre (Bpin: 202500000028886) (Tipo de Banco: Banco Territorial) (Meta total del indicador: 5.0) (Meta total de la vigencia: 5.0) (Ejecutado: 5.0) Jornadas de promoción en las instituciones educativas para promover la participación de los jovenes en las elecciones de Consejos de Juventud Municipales. (Tipo de banco: Banco de Gestiones) (Meta de la gestión: 31) (Ejecutado: 25) APOYO LOGISTICO PARA EL FORTALECIMIENTO DEL SISTEMA DE PARTICIPACIÓN JUVENIL EN EL DEPARTAMENTO DE SUCRE (BPIN: 202400000001355) (Tipo de banco: Banco Territorial) (Meta total del proyecto: 7) (Ejecutado: 7.0) | AJ10: Apoyo para el fomento de las oportunidades de los jovenes mediante la realización de Ferias Universitarias, espacios de emprendimiento y otros escenarios de participación en el departamento de Sucre (BPIN: 202600000005647) (Meta del proyecto: 2) (Tipo de Banco: Banco Territorial) (Estado en Portafolio: En gestión de recursos) Apoyo para el fortalecimiento del sistema de participación juvenil para la vigencia 2026 en el Departamento de Sucre (BPIN: 202600000003201) (Meta del proyecto: 14) (Tipo de Banco: Banco Territorial) (Estado en Portafolio: En gestión de recursos) APOYO AL FORTALECIMIENTO DEL SISTEMA DE PARTICIPACIÓN JUVENIL EN EL DEPARTAMENTO DE SUCRE (Pendiente de subsanaciones) (Tipo de Banco: Sin Tipo de Banco) APOYO LOGÍSTICO PARA LA CONMEMORACIÓN DEL MES DE LA JUVENTUD EN EL DEPARTAMENTO DE SUCRE APOYO A LA ENTREGA DE ESTÍMULOS DE CARÁCTER EDUCATIVO, CULTURAL Y RECREATIVO PARA LOS CONSEJEROS Y PLATAFORMADOS DEPARTAMENTALES DE JUVENTUD Y SUMINISTRO DE ELEMENTOS DE APOYO AL SISTEMA DE PARTICIPACIÓN JUVENIL DEL DEPARTAMENTO DE SUCRE APOYO A LA PRIMERA CUMBRE REGIONAL DE JOVENES CARIBE 2024 EN EL DEPARTAMENTO DE SUCRE Poseción del Consejo Departamental de Juventudes 2026-2027. Elección del Consejo Departamental de Juventudes 2026-2027. Espacio de socialización con la junta directiva y Comite de Concertación y Desición del Consejo Departamentalde Juventudes. (Meta Programada: 3) (Tipo de Banco: Banco de Gestiones) | AK10: Poseción del Consejo Departamental de Juventudes 2026-2027. Elección del Consejo Departamental de Juventudes 2026-2027. Espacio de socialización con la junta directiva y Comite de Concertación y Desición del Consejo Departamentalde Juventudes. (Meta programada: 3) (Ejecución: 3) (Tipo de banco: Banco de Gestiones) | AL10: APOYO A LA PRIMERA CUMBRE REGIONAL DE JOVENES CARIBE 2024 EN EL DEPARTAMENTO DE SUCRE. (Bpin: ) (Tipo de banco: Sin Tipo de Banco) APOYO LOGÍSTICO PARA LA CONMEMORACIÓN DEL MES DE LA JUVENTUD EN EL DEPARTAMENTO DE SUCRE (Bpin: ) APOYO A LA ENTREGA DE ESTÍMULOS DE CARÁCTER EDUCATIVO, CULTURAL Y RECREATIVO PARA LOS CONSEJEROS Y PLATAFORMADOS DEPARTAMENTALES DE JUVENTUD Y SUMINISTRO DE ELEMENTOS DE APOYO AL SISTEMA DE PARTICIPACIÓN JUVENIL DEL DEPARTAMENTO DE SUCRE (Bpin: ) APOYO AL FORTALECIMIENTO DEL SISTEMA DE PARTICIPACIÓN JUVENIL EN EL DEPARTAMENTO DE SUCRE (Bpin: ) | AM10: 10 | AN10: 0.625 | AO10: Alto | AP10: 37 | AQ10: 1 | AR10: Superior | AS10: 3 | AT10: 0.096774194 | AU10: Minimo | AV10: 50 | AW10: 0.46296296 | AX10: Medio | AY10: 166000000 | AZ10: 0 | BA10: 0 | BB10: 0 | BC10: 0 | BD10: 0 | BE10: 0 | BF10: 0 | BG10: 0 | BH10: 0 | BI10: 166000000 | BJ10: 174300000 | BK10: 0 | BL10: 0 | BM10: 0 | BN10: 0 | BO10: 0 | BP10: 0 | BQ10: 0 | BR10: 0 | BS10: 0 | BT10: 174300000 | BU10: 183015000 | BV10: 0 | BW10: 0 | BX10: 0 | BY10: 0 | BZ10: 0 | CA10: 0 | CB10: 0 | CC10: 0 | CD10: 0 | CE10: 183015000 | CF10: 192165750 | CG10: 0 | CH10: 0 | CI10: 0 | CJ10: 0 | CK10: 0 | CL10: 0 | CM10: 0 | CN10: 0 | CO10: 0 | CP10: 192165750 | CQ10: 715480750 | CR10: se adelantará proceso contractual este año y se solicitará vigencias futuras para ejecución 03/10/2024: Se tenia una meta de 108 espacios en el cuatrienio, se establece por incremento, por solicitud del profesional a cargo se redistribuyen las metas por vigencia. | CS10: Sesiones Consejo Departamental de Juventudes y asiistencias tecnicas a las alcaldias municipales para el fortalecimiento del Subsistema de participaciòn juvenil
A11: MT008 | B11: 2 | C11: Transformación del Ser Humano | D11: Porcentaje de ejecución de las actividades del Plan de Acción de la Política Pública Departamental de Juventudes "Sucre Territorio Joven" | E11: 0,26700000000000002 | F11: Porcentaje | G11: 2023 | H11: Informe Polìtica Pùblica Departamental de Juventudes | I11: 0,5 | J11: 3. Salud y bienestar | K11: Inclusión Social | L11: 2 | M11: Sucre territorio Joven | N11: Trabajo | O11: 36 | P11: Fomento de la investigación, desarrollo tecnológico e innovación del sector trabajo | Q11: 3605 | R11: Servicios de información implementados | S11: 3605011 | T11: Sistema de información implementados | U11: 360501100 | V11: Corresponde al proceso que mejora en la disposición de la información para asegurar que sea accesible, confiable y oportuna. | W11: Número de sistemasde información | X11: Sí | Y11: Número | Z11: 1 | AA11: Acumulativo | AB11: Secretaria de Inclusión Social, Mujer y Equidad de Genero | AC11: 0 | AD11: 0 | AE11: 1 | AF11: 0 | AH11: CONVENIO CON LA CAJA DE COMPENSACIÓN DE COMFASUCRE PARA IMPLEMENTACIÓN DE LA ORDENANZA 028 DE 2022. (Tipo Banco: Banco de Gestiones) (Meta de la gestión: 1) IMPLEMENTACIÓN DE ACTIVIDADES DE CORTE TECNOLOGICO EN CUMPLIMIENTO DE LA ORDENANZA 028 DE 2022 PARA LA PLATAFORMA DE JUVENTUDES DEL DEPARTAMENTO DE SUCRE (BPIN: 2024002700093) (Tipo de Banco: Banco Territorial) | AJ11: CONVENIO CON LA CAJA DE COMPENSACIÓN DE COMFASUCRE PARA IMPLEMENTACIÓN DE LA ORDENANZA 028 DE 2022. (Meta Programada: 1) (Tipo de Banco: Banco de Gestiones) | AK11: CONVENIO CON LA CAJA DE COMPENSACIÓN DE COMFASUCRE PARA IMPLEMENTACIÓN DE LA ORDENANZA 028 DE 2022. (Meta programada: 1) (Ejecución: 1) (Tipo de banco: Banco de Gestiones) | AS11: 1 | AT11: 1 | AU11: Superior | AV11: 1 | AW11: 1 | AX11: Superior | AY11: 50000000 | AZ11: 0 | BA11: 0 | BB11: 0 | BC11: 0 | BD11: 0 | BE11: 0 | BF11: 0 | BG11: 0 | BH11: 0 | BI11: 50000000 | BJ11: 52500000 | BK11: 0 | BL11: 0 | BM11: 0 | BN11: 0 | BO11: 0 | BP11: 0 | BQ11: 0 | BR11: 0 | BS11: 0 | BT11: 52500000 | BU11: 55125000 | BV11: 0 | BW11: 0 | BX11: 0 | BY11: 0 | BZ11: 0 | CA11: 0 | CB11: 0 | CC11: 0 | CD11: 0 | CE11: 55125000 | CF11: 57881250 | CG11: 0 | CH11: 0 | CI11: 0 | CJ11: 0 | CK11: 0 | CL11: 0 | CM11: 0 | CN11: 0 | CO11: 0 | CP11: 57881250 | CQ11: 215506250 | CR11: Se tiene previsto la contratación y ejecutación durante la vigencia 2025, no cuenta con financiación, pero se esta realizando gestiones para la aplicación de un software de otras entidades. | CS11: Pllataforma ordenanza empleo joven
A12: MT009 | B12: 5 | C12: Transformación del Ser Humano | D12: Porcentaje de ejecución de las actividades del Plan de Acción de la Política Pública Departamental de Juventudes "Sucre Territorio Joven" | E12: 0,26700000000000002 | F12: Porcentaje | G12: 2023 | H12: Informe Polìtica Pùblica Departamental de Juventudes | I12: 0,5 | J12: 3. Salud y bienestar | K12: Inclusión Social | L12: 2 | M12: Sucre territorio Joven | N12: Inclusión Social y Reconciliación | O12: 41 | P12: Desarrollo integral de la primera infancia a la juventud, y fortalecimiento de las capacidades de las familias de niñas, niños y adolescentes | Q12: 4102 | R12: Servicios de educación informal a niños, niñas, adolescentes y jóvenes para el reconocimiento de sus derechos | S12: 4102045 | T12: Personas capacitadas | U12: 410204500 | V12: Servicios mediante los cuales se socializan a los niños, niñas, adolescentes y jóvenes; al igual que a sus padres, madres, cuidadores y docentes, los temas relacionados con el reconocimiento de los derechos de la niñez, la adolescencia y la juventud. | W12: Número de personas | X12: No | Y12: Número | Z12: 150 | AA12: Acumulativo | AB12: Secretaria de Inclusión Social, Mujer y Equidad de Genero | AC12: 0 | AD12: 50 | AE12: 50 | AF12: 50 | AH12: CAMPAÑA SUCRE TERRITORIO JOVEN EN LA INSTITUCIÓN EDUCATIVA ALTOS DEL ROSARIO Y CAPACITACIÓN A LOS CONSEJEROS MUNICIPALES DE JUVENTUD ELECTOS CON COLOMBIA LIDER Y LA RAP CARIBE (Tipo Banco: Banco de Gestiones) (Meta de la gestión: 0) RUTA DE LA LECTURA JUVENIL. (Tipo Banco: Banco de Gestiones) (Meta de la gestión: ) CAPACITACIÓN EN CUIDADO DEL MEDIO AMBIENTE CON JOVENES DEL MUNICIPIO DE COLOSO (Tipo Banco: Banco de Gestiones) (Meta de la gestión: 50) | AI12: CAMPAÑA SUCRE TERRITORIO JOVEN EN LA INSTITUCIÓN EDUCATIVA ALTOS DEL ROSARIO Y CAPACITACIÓN A LOS CONSEJEROS MUNICIPALES DE JUVENTUD ELECTOS CON COLOMBIA LIDER Y LA RAP CARIBE (Tipo de banco: Banco de Gestiones) (Meta de la gestión: 0) (Ejecutado: 195) RUTA DE LA LECTURA JUVENIL. (Tipo de banco: Banco de Gestiones) (Meta de la gestión: ) (Ejecutado: 53) CAPACITACIÓN EN CUIDADO DEL MEDIO AMBIENTE CON JOVENES DEL MUNICIPIO DE COLOSO (Tipo de banco: Banco de Gestiones) (Meta de la gestión: 50) (Ejecutado: 32) | AJ12: Sensibilizacion dia de las manos rojas para entornos protectores. Prevencion del consumo de sustancias psicoactivas y embarazo adolescentes. Sensibilizacion en genro, diversidad sexual y no violencia. Jornada de formacion ambiental juvenil. Sensibilizacion en salud mental y buen uso dela inteligencia artificial. Capacitacion en uso responsable y creativo de las TICS. Formacion ambiental juvenil. Charla pedagogica sobre salud mental. (Meta Programada: 693) (Tipo de Banco: Banco de Gestiones) | AK12: Sensibilizacion dia de las manos rojas para entornos protectores. Prevencion del consumo de sustancias psicoactivas y embarazo adolescentes. Sensibilizacion en genro, diversidad sexual y no violencia. Jornada de formacion ambiental juvenil. Sensibilizacion en salud mental y buen uso dela inteligencia artificial. Capacitacion en uso responsable y creativo de las TICS. Formacion ambiental juvenil. Charla pedagogica sobre salud mental. (Meta programada: 693) (Ejecución: 693) (Tipo de banco: Banco de Gestiones) | AP12: 280 | AQ12: 1 | AR12: Superior | AS12: 693 | AT12: 1 | AU12: Superior | AV12: 973 | AW12: 1 | AX12: Superior | AY12: 0 | AZ12: 0 | BA12: 0 | BB12: 0 | BC12: 0 | BD12: 0 | BE12: 0 | BF12: 0 | BG12: 0 | BH12: 0 | BI12: 0 | BJ12: 0 | BK12: 0 | BL12: 0 | BM12: 0 | BN12: 0 | BO12: 0 | BP12: 0 | BQ12: 0 | BR12: 0 | BS12: 0 | BT12: 0 | BU12: 0 | BV12: 0 | BW12: 0 | BX12: 0 | BY12: 0 | BZ12: 0 | CA12: 0 | CB12: 0 | CC12: 0 | CD12: 0 | CE12: 0 | CF12: 0 | CG12: 0 | CH12: 0 | CI12: 0 | CJ12: 0 | CK12: 0 | CL12: 0 | CM12: 0 | CN12: 0 | CO12: 0 | CP12: 0 | CQ12: 0 | CR12: Se tenia previsto formular proyecto, pero no cuenta con financiación | CS12: Mujeres, jovenes, niños, niñas y adolescentes y familias capacitados con formaciones para su crecimiento academico y autonomia economica
A13: MT010 | B13: 1 | C13: Transformación del Ser Humano | D13: Porcentaje de ejecución de las actividades del Plan de acción de la Política Pública para el fortalecimiento integral de las familias de sucre 2023-2037 | E13: 0 | F13: Porcentaje | G13: 2023 | H13: Informe de avance Política Pública para el fortalecimiento integral de las familias | I13: 0,25 | J13: 3. Salud y bienestar 10- Reducción de las desigualdades. | K13: Inclusión Social | L13: 3 | M13: Familias con Oportunidades | N13: Inclusión Social y Reconciliación | O13: 41 | P13: Desarrollo integral de la primera infancia a la juventud, y fortalecimiento de las capacidades de las familias de niñas, niños y adolescentes | Q13: 4102 | R13: Servicios de educación informal a niños, niñas, adolescentes y jóvenes para el reconocimiento de sus derechos | S13: 4102045 | T13: Personas capacitadas | U13: 410204500 | V13: Servicios mediante los cuales se socializan a los niños, niñas, adolescentes y jóvenes; al igual que a sus padres, madres, cuidadores y docentes, los temas relacionados con el reconocimiento de los derechos de la niñez, la adolescencia y la juventud. | W13: Número de personas | X13: No | Y13: Número | Z13: 150 | AA13: Acumulativo | AB13: Secretaria de Inclusión Social, Mujer y Equidad de Genero | AC13: 0 | AD13: 50 | AE13: 50 | AF13: 50 | AG13: SE ASISTIERON TECNICAMENTE 174 PERSONAS EN LOS TEMAS DE: MARCO LEGAL Y CONSTITUCIONAL DE FAMILIAS, POLITICA PUBLICA DE FAMILIAS, ENTRE OTROS (BPIN: Por Gestión) (Meta del Proyecto: 174) (Ejecución 2024: 174) | AH13: CAPACITAR A FAMILIAS POR AÑO EN EL RESCATE DE LOS VALORES Y EL FORTALECIMIENTO FAMILIAR EN EL MARCO DEL MES DE LA FAMILIA (Tipo Banco: Banco de Gestiones) (Meta de la gestión: 50) | AI13: CAPACITAR A FAMILIAS POR AÑO EN EL RESCATE DE LOS VALORES Y EL FORTALECIMIENTO FAMILIAR EN EL MARCO DEL MES DE LA FAMILIA (Tipo de banco: Banco de Gestiones) (Meta de la gestión: 50) (Ejecutado: 50) | AJ13: CAPACITAR A 50 FAMILIAS POR AÑO EN EL RESCATE DE LOS VALORES Y EL FORTALECIMIENTO FAMILIAR EN EL MARCO DEL MES DE LA FAMILIA Implementación DE ACCIONES DE APOYO PSICOSOCIAL COMO ESTRATEGIA FRENTE A LAS PROBLEMÁTICAS DE SALUD MENTAL EN EL DEPARTAMENTO DE Sucre (BPIN: 202500000050658) (Meta del proyecto: 1040) (Tipo de Banco: Banco Territorial) | AL13: CAPACITAR A 50 FAMILIAS POR AÑO EN EL RESCATE DE LOS VALORES Y EL FORTALECIMIENTO FAMILIAR EN EL MARCO DEL MES DE LA FAMILIA | AM13: 174 | AN13: 1 | AO13: Superior | AP13: 50 | AQ13: 1 | AR13: Superior | AT13: 1 | AU13: Superior | AV13: 224 | AW13: 1 | AX13: Superior | AY13: 0 | AZ13: 0 | BA13: 0 | BB13: 0 | BC13: 0 | BD13: 0 | BE13: 0 | BF13: 0 | BG13: 0 | BH13: 0 | BI13: 0 | BJ13: 0 | BK13: 0 | BL13: 0 | BM13: 0 | BN13: 0 | BO13: 0 | BP13: 0 | BQ13: 0 | BR13: 0 | BS13: 0 | BT13: 0 | BU13: 0 | BV13: 0 | BW13: 0 | BX13: 0 | BY13: 0 | BZ13: 0 | CA13: 0 | CB13: 0 | CC13: 0 | CD13: 0 | CE13: 0 | CF13: 0 | CG13: 0 | CH13: 0 | CI13: 0 | CJ13: 0 | CK13: 0 | CL13: 0 | CM13: 0 | CN13: 0 | CO13: 0 | CP13: 0 | CQ13: 0 | CS13: Mujeres, jovenes, niños, niñas y adolescentes y familias capacitados con formaciones para su crecimiento academico y autonomia economica
A14: MT011 | B14: 3 | C14: Transformación del Ser Humano | D14: Porcentaje de ejecución de las actividades del Plan de acción de la Política Pública para el fortalecimiento integral de las familias de sucre 2023-2037 | E14: 0 | F14: Porcentaje | G14: 2023 | H14: Informe de avance Política Pública para el fortalecimiento integral de las familias | I14: 0,25 | J14: 3. Salud y bienestar 10- Reducción de las desigualdades. | K14: Inclusión Social | L14: 3 | M14: Familias con Oportunidades | N14: Inclusión Social y Reconciliación | O14: 41 | P14: Desarrollo integral de la primera infancia a la juventud, y fortalecimiento de las capacidades de las familias de niñas, niños y adolescentes | Q14: 4102 | R14: Servicio de promoción de temas de dinámica relacional y desarrollo autónomo | S14: 4102043 | T14: Familias atendidas | U14: 410204300 | V14: Incluye el desarrollo de acciones de asesoría, orientación y acompañamiento a las familias, que buscan generar cultura en las familias y las comunidades sobre vínculos de cuidado mutuo en las situaciones de dinámica relacional o en aquellas que requieran apoyo ante situaciones de vulnerabilidad sociocultural o de garantía de derechos. | W14: Número de familias | X14: No | Y14: Número | Z14: 820 | AA14: No acumulativo | AB14: Secretaria de Inclusión Social, Mujer y Equidad de Genero | AC14: 820 | AD14: 820 | AE14: 820 | AF14: 820 | AG14: SUCRE ESCUCHA EN EL DEPARTAMENTO DE SUCRE (BPIN: 2022000020011) (Meta del Proyecto: 2600) (Ejecución 2024: 2600) APOYO PARA LA REALIZACIÓN DE ACTIVIDADES RECREATIVAS, CULTURALES Y DE EMPRENDIMIENTO EN EL MARCO DEL MES DE LA FAMILIA 2024 EL DEPARTAMENTO DE SUCRE (BPIN: 2024002700060) (Meta del Proyecto: ) (Ejecución 2024: 1) | AH14: Apuesta institucional de la estrategia SUCRE TERRITORIO DE FAMILIAS UNIDAS (Tipo Banco: Banco de Gestiones) (Meta de la gestión: 388) APOYO PARA LA REALIZACIÓN DE ACTIVIDADES RECREATIVAS, CULTURALES Y DE EMPRENDIMIENTO EN EL MARCO DEL MES DE LA FAMILIA 2025 EL DEPARTAMENTO DE SUCRE (BPIN: 202400000004252) (Tipo de Banco: Banco Territorial) | AI14: Apoyo PARA LA REALIZACIÓN DE ACTIVIDADES RECREATIVAS, CULTURALES, Y DE EMPRENDIMIENTO EN EL MARCO DEL MES DE LA FAMILIA 2025 EN EL DEPARTAMENTO DE Sucre (Bpin: 202400000004252) (Tipo de Banco: Banco Territorial) (Meta total del indicador: 432.0) (Meta total de la vigencia: 432.0) (Ejecutado: 432.0) Apuesta institucional de la estrategia SUCRE TERRITORIO DE FAMILIAS UNIDAS (Tipo de banco: Banco de Gestiones) (Meta de la gestión: 388) (Ejecutado: 388) | AJ14: INICIATIVA DE IMPLEMENTACIÓN DE ACTIVIDADES DE LA POLÍTICA PÚBLICA DE FAMILIA SUCRE ESCUCHA FAMILIA Fortalecimiento DE CAPACIDADES PSICOSOCIALES, PRODUCTIVAS Y PARTICIPATIVAS DE LAS FAMILAS VULNERABLES DEL DEPARTAMENTO DE Sucre (BPIN: 202600000005053) (Meta del proyecto: 297) (Tipo de Banco: Banco Territorial) Jornada de sensibilización a los padres de familia de la Institución Educativa La Unión (Meta Programada: 820) (Tipo de Banco: Banco de Gestiones) | AK14: Jornada de sensibilización a los padres de familia de la Institución Educativa La Unión (Meta programada: 820) (Ejecución: 620) (Tipo de banco: Banco de Gestiones) | AL14: INICIATIVA DE IMPLEMENTACIÓN DE ACTIVIDADES DE LA POLÍTICA PÚBLICA DE FAMILIA (Bpin: ) | AM14: 2601 | AN14: 1 | AO14: Superior | AP14: 820 | AQ14: 1 | AR14: Superior | AS14: 620 | AT14: 1 | AU14: Superior | AV14: 4041 | AW14: 1 | AX14: Superior | AY14: 50000000 | AZ14: 0 | BA14: 0 | BB14: 0 | BC14: 0 | BD14: 0 | BE14: 0 | BF14: 0 | BG14: 1000000000 | BH14: 0 | BI14: 1050000000 | BJ14: 52500000 | BK14: 0 | BL14: 0 | BM14: 0 | BN14: 0 | BO14: 0 | BP14: 0 | BQ14: 0 | BR14: 1000000000 | BS14: 0 | BT14: 1052500000 | BU14: 55125000 | BV14: 0 | BW14: 0 | BX14: 0 | BY14: 0 | BZ14: 0 | CA14: 0 | CB14: 0 | CC14: 1000000000 | CD14: 0 | CE14: 1055125000 | CF14: 57881250 | CG14: 0 | CH14: 0 | CI14: 0 | CJ14: 0 | CK14: 0 | CL14: 0 | CM14: 0 | CN14: 1000000000 | CO14: 0 | CP14: 1057881250 | CQ14: 4215506250 | CR14: - El proyecto de mes de la familia para 2024 fue homologado porque se formuló con un indicador de Sucre Diferente - Se dio orientación de mantenimiento porque se está programando sobrecumplir la meta con los proyectos que asociaron | CS14: Sucre escucha familia
A15: MT012 | B15: 4 | C15: Transformación del Ser Humano | D15: Porcentaje de ejecución de las actividades del Plan de acción de la Política Pública para el fortalecimiento integral de las familias de sucre 2023-2037 | E15: 0 | F15: Porcentaje | G15: 2023 | H15: Informe de avance Política Pública para el fortalecimiento integral de las familias | I15: 0,25 | J15: 3. Salud y bienestar 10- Reducción de las desigualdades. | K15: Inclusión Social | L15: 3 | M15: Familias con Oportunidades | N15: Gobierno Territorial | O15: 45 | P15: Fortalecimiento del buen gobierno para el respeto y garantía de los derechos humanos | Q15: 4502 | R15: Servicio de apoyo financiero para la implementación de proyectos en materia de derechos humanos | S15: 4502021 | T15: Proyectos cofinanciados | U15: 450202100 | V15: Contempla la asignación de recursos financieros a iniciativas en temas relacionados con derechos humanos y el Derecho Internacional Humanitario. | W15: Número de proyectos | X15: No | Y15: Número | Z15: 1 | AA15: Acumulativo | AB15: Secretaria de Inclusión Social, Mujer y Equidad de Genero | AC15: 0 | AD15: 0 | AE15: 1 | AF15: 0 | AH15: IMPLEMENTACION DE UNA ESTRATEGIA DE APROPIACION CULTURAL PARA LAS FAMILIAS INDIGENAS DEL DEPARTAMENTO DE SUCRE (Tipo Banco: Banco de Gestiones) (Meta de la gestión: ) Fortalecimiento Productivo y Comercial para Familias Artesanas Indígenas Víctimas de Violencia Intrafamiliar en el Departamento de Sucre (Por Formular) (BPIN: ) (Tipo de Banco: Sin Tipo de Banco) | AJ15: BANCO DE ALIMENTOS (BPIN: Por Gestión) | AP15: 0 | AT15: 0 | AU15: Minimo | AV15: 0 | AW15: 0 | AX15: Minimo | AY15: 75000000 | AZ15: 0 | BA15: 0 | BB15: 0 | BC15: 0 | BD15: 0 | BE15: 0 | BF15: 0 | BG15: 0 | BH15: 0 | BI15: 75000000 | BJ15: 78750000 | BK15: 0 | BL15: 0 | BM15: 0 | BN15: 0 | BO15: 0 | BP15: 0 | BQ15: 0 | BR15: 0 | BS15: 0 | BT15: 78750000 | BU15: 82687500 | BV15: 0 | BW15: 0 | BX15: 0 | BY15: 0 | BZ15: 0 | CA15: 0 | CB15: 0 | CC15: 0 | CD15: 0 | CE15: 82687500 | CF15: 86821875 | CG15: 0 | CH15: 0 | CI15: 0 | CJ15: 0 | CK15: 0 | CL15: 0 | CM15: 0 | CN15: 0 | CO15: 0 | CP15: 86821875 | CQ15: 323259375 | CR15: Se realizo el cambio de vigencia de la iniciativa BANCO DE ALIMENTOS (Por gestión de cofinanciación) | CS15: Banco de alimentos
A16: MT013 | B16: 1 | C16: Transformación del Ser Humano | D16: Porcentaje de ejecución de las actividades del Plan de Acción de la Política Pública Departamental para la protección del adulto mayor | E16: 0,5 | F16: Porcentaje | G16: 2023 | H16: Informe Politica Publica de Adulto Mayor | I16: 0,75 | J16: 3 Salud y bienestar | K16: Inclusión Social | L16: 4 | M16: Edad plateada con oportunidades | N16: Inclusión Social y Reconciliación | O16: 41 | P16: Atención integral de población en situación permanente de desprotección social y/o familiar | Q16: 4104 | R16: Servicio de atención y protección integral al adulto mayor | S16: 4104008 | T16: Adultos mayores atendidos con servicios integrales | U16: 410400800 | V16: Servicios integrales que incluyen aspectos relacionados con protección a la salud y bienestar social, educación, cultura, recreación, entorno físico y social favorable, productividad para los adultos mayores. | W16: Número de adultos mayores | X16: No | Y16: Número | Z16: 7200 | AA16: Acumulativo | AB16: Secretaria de Inclusión Social, Mujer y Equidad de Genero | AC16: 2800 | AD16: 1700 | AE16: 1700 | AF16: 1000 | AG16: FASES MUNICIPALES PROGRAMA NUEVO COMIENZO (BPIN: Por Gestión) (Meta del Proyecto: 932) (Ejecución 2024: 932) FORTALECIMIENTO DEL PROGRAMA DE ATENCIÓN INTEGRAL PARA LA PROTECCIÓN Y LOS DERECHOS DE LAS PERSONAS MAYORES DURANTE EL AÑO 2024 EN LOS CENTROS DE VIDA DEL DEPARTAMENTO DE SUCRE (BPIN: 2024002700107) (Meta del Proyecto: 2771) (Ejecución 2024: 2771) FASE DEPARTAMENTAL PROGRAMA NUEVO COMIENZO (BPIN: Por Gestión) (Meta del Proyecto: 65) (Ejecución 2024: 65) | AH16: APOYO A LOS CENTROS DE BIENESTAR PARA LA ATENCIÓN INTEGRAL DE LAS PERSONAS MAYORES DURANTE EL AÑO 2024 EN LOS MUNICIPIOS DE SAN MARCOS Y SAN ONOFRE DEL DEPARTAMENTO DE SUCRE (BPIN: 2024002700106) (Tipo de Banco: Banco Territorial) FORTALECIMIENTO DEL PROGRAMA DE ATENCIÓN INTEGRAL PARA LA PROTECCIÓN Y GARANTÍA DE LOS DERECHOS DE LAS PERSONAS MAYORES DURANTE EL AÑO 2025 EN LOS CENTROS DE VIDA DEL DEPARTAMENTO DE SUCRE (BPIN: 202500000026392) (Tipo de Banco: Banco Territorial) APOYO A LOS CENTROS DE BIENESTAR PARA LA ATENCIÓN INTEGRAL DE LAS PERSONAS MAYORES DURANTE EL AÑO 2025 EN LOS MUNICIPIOS DE SAN MARCOS, SAN ONOFRE Y SINCELEJO EN EL DEPARTAMENTO DE SUCRE (BPIN: ) (Tipo de Banco: Banco Territorial) FORTALECIMIENTO E IMPLEMENTACION DE ACTIVIDADES DE LA POLITICA PUBLICA DEL ADULTO MAYOR EN EL MARCO DEL MES POBLACIONAL EN EL DEPARTAMENTO DE SUCRE (BPIN: ) (Tipo de Banco: Banco Territorial) FOMENTO Y FORTALECIMIENTO DE UNIDADES PRODUCTIVAS PARA LA PERSONA MAYOR (BPIN: ) (Tipo de Banco: Banco Territorial) FORTALECIMIENTO DE LOS ESPACIOS DE PARTICIPACIÓN DE LA PERSONA MAYOR EN EL MARCO DE LA ESTRATEGIA NACIONAL “NUEVO COMIENZO OTRO MOTIVO PARA VIVIR 2024 DEL DEPARTAMENTO DE SUCRE (BPIN: 2024002700097) (Tipo de Banco: Banco Territorial) Fortalecimiento DE LOS ESPACIOS DE PARTICIPACIÓN DE LA PERSONA MAYOR EN EL MARCO DE LA ESTRATEGIA NACIONAL “NUEVO COMIENZO OTRO MOTIVO PARA VIVIR" 2025 DEL DEPARTAMENTO DE Sucre (BPIN: 202500000032732) (Tipo de Banco: Banco Territorial) | AI16: Fortalecimiento DE LOS ESPACIOS DE PARTICIPACIÓN DE LA PERSONA MAYOR EN EL MARCO DE LA ESTRATEGIA NACIONAL “NUEVO COMIENZO OTRO MOTIVO PARA VIVIR" 2025 DEL DEPARTAMENTO DE Sucre (Bpin: 202500000032732) (Tipo de Banco: Banco Territorial) (Meta total del indicador: 10.0) (Meta total de la vigencia: 10.0) (Ejecutado: 10.0) Fortalecimiento DE LOS ESPACIOS DE PARTICIPACIÓN DE LA PERSONA MAYOR EN EL MARCO DE LA ESTRATEGIA NACIONAL NUEVO COMIENZO OTRO MOTIVO PARA VIVIR 2024 DEL DEPARTAMENTO DE Sucre (Bpin: 2024002700097) (Tipo de Banco: Banco Territorial) (Meta total del indicador: 12.0) (Meta total de la vigencia: 12.0) (Ejecutado: 12.0) Apoyo A LOS CENTROS DE BIENESTAR PARA LA ATENCIÓN INTEGRAL DE LAS PERSONAS MAYORES DURANTE EL AÑO 2024 EN LOS MUNICIPIOS DE SAN MARCOS Y SAN ONOFRE DEL DEPARTAMENTO DE Sucre (Bpin: 2024002700106) (Tipo de Banco: Banco Territorial) (Meta total del indicador: 55.0) (Meta total de la vigencia: 55.0) (Ejecutado: 22.0) Fortalecimiento del Programa de atención integral para la protección y garantía de los derechos de las personas mayores durante el año 2025en los Centros de Vida del Departamento de Sucre (Bpin: 202500000026392) (Tipo de Banco: Banco Territorial) (Meta total del indicador: 2473.0) (Meta total de la vigencia: 2473.0) (Ejecutado: 2473.0) | AJ16: Apoyo AL CENTRO DE BIENESTAR PARA LA ATENCIÓN INTEGRAL DE LAS PERSONAS MAYORES DURANTE EL AÑO 2025 EN EL MUNICIPIO DE SAN ONOFRE, EN EL DEPARTAMENTO DE Sucre (BPIN: 202500000034941) (Meta del proyecto: 22) (Tipo de Banco: Banco Territorial) (Estado en Portafolio: En Ejecución) FORTALECIMIENTO DEL PROGRAMA DE ATENCIÓN INTEGRAL PARA LA PROTECCIÓN Y LOS DERECHOS DE LAS PERSONAS MAYORES DURANTE EL AÑO 2026 EN LOS CENTROS DE VIDA DEL DEPARTAMENTO DE SUCRE APOYO A LOS CENTROS DE BIENESTAR PARA LA ATENCIÓN INTEGRAL DE LAS PERSONAS MAYORES DURANTE EL AÑO 2026 EN LOS MUNICIPIOS DE SAN MARCOS, SAN ONOFRE Y SINCELEJO EN EL DEPARTAMENTO DE SUCRE FORTALECIMIENTO DE LOS ESPACIOS DE PARTICIPACIÓN DE LA PERSONA MAYOR EN EL MARCO DE LA ESTRATEGIA NACIONAL “NUEVO COMIENZO OTRO MOTIVO PARA VIVIR DEL DEPARTAMENTO DE SUCRE FASES MUNICIPALES PROGRAMA NUEVO COMIENZO (BPIN: Por Gestión) FORTALECIMIENTO DE EMPRENDIMIENTOS DE LAS PERSONAS MAYORES EN ETAPA PRODUCTIVA EN EL DEPARTAMENTO DE SUCRE | AL16: FASES MUNICIPALES PROGRAMA NUEVO COMIENZO (Bpin: Por Gestión) FORTALECIMIENTO DE LOS ESPACIOS DE PARTICIPACIÓN DE LA PERSONA MAYOR EN EL MARCO DE LA ESTRATEGIA NACIONAL “NUEVO COMIENZO OTRO MOTIVO PARA VIVIR DEL DEPARTAMENTO DE SUCRE APOYO A LOS CENTROS DE BIENESTAR PARA LA ATENCIÓN INTEGRAL DE LAS PERSONAS MAYORES DURANTE EL AÑO 2027 EN LOS MUNICIPIOS DE SAN MARCOS, SAN ONOFRE Y SINCELEJO EN EL DEPARTAMENTO DE SUCRE FORTALECIMIENTO DEL PROGRAMA DE ATENCIÓN INTEGRAL PARA LA PROTECCIÓN Y LOS DERECHOS DE LAS PERSONAS MAYORES DURANTE EL AÑO 2027 EN LOS CENTROS DE VIDA DEL DEPARTAMENTO DE SUCRE | AM16: 3768 | AN16: 1 | AO16: Superior | AP16: 2517 | AQ16: 1 | AR16: Superior | AT16: 1 | AU16: Superior | AV16: 6285 | AW16: 0.87291667 | AX16: Alto | AY16: 0 | AZ16: 5.8067529e+09 | BA16: 0 | BB16: 0 | BC16: 0 | BD16: 0 | BE16: 0 | BF16: 0 | BG16: 0 | BH16: 0 | BI16: 5.8067529e+09 | BJ16: 0 | BK16: 7.766532e+09 | BL16: 0 | BM16: 0 | BN16: 0 | BO16: 0 | BP16: 0 | BQ16: 0 | BR16: 0 | BS16: 0 | BT16: 7.766532e+09 | BU16: 0 | BV16: 8.2325239e+09 | BW16: 0 | BX16: 0 | BY16: 0 | BZ16: 0 | CA16: 0 | CB16: 0 | CC16: 0 | CD16: 0 | CE16: 8.2325239e+09 | CF16: 0 | CG16: 8.7264754e+09 | CH16: 0 | CI16: 0 | CJ16: 0 | CK16: 0 | CL16: 0 | CM16: 0 | CN16: 0 | CO16: 0 | CP16: 8.7264754e+09 | CQ16: 3.0532284e+10 | CR16: - Los beneficiarios de cada año para adulto mayor, están sobre pasando la meta. - Hay dos proyectos para apoyo al emprendimiento de la persona mayor, uno para 2025 que se propondría por recursos propios (mínimo una mínima) y uno para 2026 que es un proyecto grande ($2.500millones) 03/10/2024: Se tiene una meta de cuatrienio por 7.200, pero en la meta por vigencia suman aproximadamente 15.500, se definio con el profesional que esta meta debe ser de mantenimiento, Pasandode 7.200 a 3.000. El numero de benefiriarios se presentan de la siguiente manetar, 2771 centro vida y centro de bienestar 55. | CS16: Centro de bienestar del adulto mayor, programa edad plateada con oportunidades
A17: MT014 | B17: 2 | C17: Transformación del Ser Humano | D17: Porcentaje de ejecución de las actividades del Plan de Acción de la Política Pública Departamental para la protección del adulto mayor | E17: 0,5 | F17: Porcentaje | G17: 2023 | H17: Informe Politica Publica de Adulto Mayor | I17: 0,75 | J17: 3 Salud y bienestar | K17: Inclusión Social | L17: 4 | M17: Edad plateada con oportunidades | N17: Inclusión Social y Reconciliación | O17: 41 | P17: Atención integral de población en situación permanente de desprotección social y/o familiar | Q17: 4104 | R17: Servicio de educación informal a los cuidadores del adulto mayor | S17: 4104010 | T17: Cuidadores cualificados | U17: 410401000 | V17: Servicios dirigidos a fortalecer las habilidades y competencias de los cuidadores del adulto mayor en temas de protección y atención integral a esta población. | W17: Número de cuidadores | X17: No | Y17: Número | Z17: 80 | AA17: Acumulativo | AB17: Secretaria de Inclusión Social, Mujer y Equidad de Genero | AC17: 0 | AD17: 30 | AE17: 30 | AF17: 20 | AH17: Formación a cuidadores de personas mayores en los centros vida del Departamento de Sucre. (Tipo Banco: Banco de Gestiones) (Meta de la gestión: ) | AI17: Formación a cuidadores de personas mayores en los centros vida del Departamento de Sucre. (Tipo de banco: Banco de Gestiones) (Meta de la gestión: ) (Ejecutado: 271) | AJ17: IMPLEMENTACIÓN DEL SISTEMA INTEGRAL DE CUIDADO DIRIGIDO A LA PRIMERA INFANCIA, PERSONAS CON DISCAPACIDAD Y PERSONAS MAYORES FORMACIÓN EN EMPRENDIMIENTO A CUIDADORAS DE PERSONAS MAYORES | AL17: FORMACIÓN EN EMPRENDIMIENTO A CUIDADORAS DE PERSONAS MAYORES (Bpin: ) | AP17: 271 | AQ17: 1 | AR17: Superior | AT17: 1 | AU17: Superior | AV17: 271 | AW17: 1 | AX17: Superior | AY17: 0 | AZ17: 314620000 | BA17: 0 | BB17: 0 | BC17: 0 | BD17: 0 | BE17: 0 | BF17: 0 | BG17: 0 | BH17: 0 | BI17: 314620000 | BJ17: 0 | BK17: 354550000 | BL17: 0 | BM17: 0 | BN17: 0 | BO17: 0 | BP17: 0 | BQ17: 0 | BR17: 0 | BS17: 0 | BT17: 354550000 | BU17: 0 | BV17: 354820000 | BW17: 0 | BX17: 0 | BY17: 0 | BZ17: 0 | CA17: 0 | CB17: 0 | CC17: 0 | CD17: 0 | CE17: 354820000 | CF17: 0 | CG17: 423090000 | CH17: 0 | CI17: 0 | CJ17: 0 | CK17: 0 | CL17: 0 | CM17: 0 | CN17: 0 | CO17: 0 | CP17: 423090000 | CQ17: 1447080000 | CR17: Esta meta se encuentra incluida en el proyecto de cuidadores del programa soy capaz | CS17: Cuidadores de poblaciòn adulto mayor y personas en condiciòn de discapacidad capacitados
A18: MT015 | B18: 3 | C18: Transformación del Ser Humano | D18: Porcentaje de ejecución de las actividades del Plan de Acción de la Política Pública Departamental para la protección del adulto mayor | E18: 0,5 | F18: Porcentaje | G18: 2023 | H18: Informe Politica Publica de Adulto Mayor | I18: 0,75 | J18: 3 Salud y bienestar | K18: Inclusión Social | L18: 4 | M18: Edad plateada con oportunidades | N18: Inclusión Social y Reconciliación | O18: 41 | P18: Atención integral de población en situación permanente de desprotección social y/o familiar | Q18: 4104 | R18: Centros de protección social para el adulto mayor adecuados | S18: 4104002 | T18: Centros de protección social para el adulto mayor adecuados | U18: 410400200 | V18: Corresponde a la adecuación de infraestructura destinada al ofrecimiento de servicios de hospedaje, bienestar social y cuidado integral de manera permanente o temporal a los adultos mayores en condicionesde descuido, abandono o víctimas de violencia intrafamiliar. | W18: Número de centros | X18: No | Y18: Número | Z18: 1 | AA18: Acumulativo | AB18: Secretaria de Inclusión Social, Mujer y Equidad de Genero | AC18: 0 | AD18: 0 | AE18: 1 | AF18: 0 | AT18: 0 | AU18: Minimo | AV18: 0 | AW18: 0 | AX18: Minimo | AY18: 0 | AZ18: 3.2140699e+09 | BA18: 0 | BB18: 0 | BC18: 0 | BD18: 0 | BE18: 0 | BF18: 0 | BG18: 0 | BH18: 0 | BI18: 3.2140699e+09 | BJ18: 0 | BK18: 4.2988185e+09 | BL18: 0 | BM18: 0 | BN18: 0 | BO18: 0 | BP18: 0 | BQ18: 0 | BR18: 0 | BS18: 0 | BT18: 4.2988185e+09 | BU18: 0 | BV18: 4.5567476e+09 | BW18: 0 | BX18: 0 | BY18: 0 | BZ18: 0 | CA18: 0 | CB18: 0 | CC18: 0 | CD18: 0 | CE18: 4.5567476e+09 | CF18: 0 | CG18: 4.8301524e+09 | CH18: 0 | CI18: 0 | CJ18: 0 | CK18: 0 | CL18: 0 | CM18: 0 | CN18: 0 | CO18: 0 | CP18: 4.8301524e+09 | CQ18: 1.6899788e+10 | CR18: GESTIÓN DE TATIANA CON LA SAE | CS18: Adecuacion locativa para los adultos mayores
A19: MT016 | B19: 1 | C19: Transformación del Ser Humano | D19: Porcentaje de ejecución de las actividades del Plan de Acción de la Política Pública de discapacidad 2019-2029 implementadas en el departamento de Sucre | E19: 0,25 | F19: Porcentaje | G19: 2023 | H19: Informe Politica Publica de Discapacidad | I19: 0,5 | J19: 3. Salud y bienestar | K19: Inclusión Social | L19: 5 | M19: Soy Capaz | N19: Inclusión Social y Reconciliación | O19: 41 | P19: Atención integral de población en situación permanente de desprotección social y/o familiar | Q19: 4104 | R19: Servicio de atención integral a población en condición de discapacidad | S19: 4104020 | T19: Personas con discapacidad atendidas con servicios integrales | U19: 410402000 | V19: Servicios integrales que incluyen aspectos relacionados con atención en salud, cuidado, alimentación, hospedaje, formación para el trabajo, inclusión productiva, recreación, entre otros, para población en condición de discapacidad. | W19: Número de personas | X19: No | Y19: Número | Z19: 160 | AA19: No acumulativo | AB19: Secretaria de Inclusión Social, Mujer y Equidad de Genero | AC19: 160 | AD19: 160 | AE19: 160 | AF19: 160 | AG19: ADQUISICIÓN DE SILLAS DE RUEDA NEUROLOGICAS PARA PERSNAS EN CONDICIÓN DE DISCAPACIDAD DEL DEPAETAMENTO DE SUCRE (BPIN: 2024002700046) (Meta del Proyecto: 72) (Ejecución 2024: 72) | AH19: ADQUISICIÓN DE SILLAS DE RUEDAS PARA PERSONAS EN CONDICIÓN DE DISCAPACIDAD DEL DEPARTAMENTO DE SUCRE (BPIN: 202500000031435) (Tipo de Banco: Banco Territorial) DESARROLLO DE UNA ESTRATEGIA PARA EL FORTALECIMIENTO DEL EMPRENDIMIENTO Y EL TALENTO DE PERSONAS CON DISCAPACIDAD, COMO MECANISMO PARA LA SUPERACIÓN DE BARRERAS SOCIALES, EN EL MARCO DEL PROGRAMA SOY CAPAZ EN EL DEPARTAMENTO DE SUCRE (BPIN: 202500000026317) (Tipo de Banco: Banco Territorial) Fortalecimiento a la atención integral de personas en condición de discapacidad en el Departamento de Sucre (BPIN: ) (Tipo de Banco: Banco Territorial) | AI19: Adquisición DE SILLAS DE RUEDAS PARA PERSONAS EN CONDICIÓN DE DISCAPACIDAD DEL DEPARTAMENTO DE Sucre (Bpin: 202500000031435) (Tipo de Banco: Banco Territorial) (Meta total del indicador: 119.0) (Meta total de la vigencia: 119.0) (Ejecutado: 119.0) Desarrollo de una estrategia para el fortalecimiento del emprendimiento y el talento de personas con discapacidad , como mecanismo para lasuperación de barreras sociales, en el marco del programa "Soy Capaz" vigencia 2025, en el Departamento de Sucre (Bpin: 202500000026317) (Tipo de Banco: Banco Territorial) (Meta total del indicador: 25.0) (Meta total de la vigencia: 25.0) (Ejecutado: 25.0) | AJ19: Adquisición DE SILLAS DE RUEDA PARA PERSONAS EN CONDICIÓN DE DISCAPACIDAD VIGENCIA 2026 EN EL DEPARTAMENTO DE Sucre (BPIN: 202500000042332) (Meta del proyecto: 109) (Tipo de Banco: Banco Territorial) (Estado en Portafolio: Acta Final) APOYO AL PRIMER FESTIVAL LÚDICO CULTURAL Y DEPORTE DE LAS PERSONAS CON DISCAPACIDAD DEL DEPARTAMENTO DE SUCRE DESARROLLO DE UNA ESTRATEGIA PARA EL FORTALECIMIENTO DEL EMPRENDIMIENTO Y EL TALENTO DE PERSONAS CON DISCAPACIDAD, COMO MECANISMO PARA LA SUPERACIÓN DE BARRERAS SOCIALES, EN EL MARCO DEL PROGRAMA SOY CAPAZ EN EL DEPARTAMENTO DE SUCRE FORMULACIÓN DE UN PROYECTO QUE PERMITA ATENDER A LA POBLACIÓN CON DISCAPACIDAD DE MANERA INTEGRAL EN TODO EL CICLO VITAL, EN EL CUAL SE REALICE LA ENTREGA DE COMPLEMENTO ALIMENTARIO, JORNADAS INTEGRALES DE ATENCIÓN Y UN EJERCICIO DE SENSIBILIZACIÓN CON CU ADQUISICIÓN DE PRODUCTOS DE APOYO PARA PERSONAS EN CONDICIÓN DE DISCAPACIDAD DEL DEPAETAMENTO DE SUCRE | AK19: Adquisición DE SILLAS DE RUEDA PARA PERSONAS EN CONDICIÓN DE DISCAPACIDAD VIGENCIA 2026 EN EL DEPARTAMENTO DE Sucre (Bpin: 202500000042332) (Meta de la vigencia: 109,00) (Ejecucion: 109,00) (Tipo de banco: Banco Territorial) (Estado en portafolio: Acta Final) | AL19: APOYO AL PRIMER FESTIVAL LÚDICO CULTURAL Y DEPORTE DE LAS PERSONAS CON DISCAPACIDAD DEL DEPARTAMENTO DE SUCRE (Bpin: ) DESARROLLO DE UNA ESTRATEGIA PARA EL FORTALECIMIENTO DEL EMPRENDIMIENTO Y EL TALENTO DE PERSONAS CON DISCAPACIDAD, COMO MECANISMO PARA LA SUPERACIÓN DE BARRERAS SOCIALES, EN EL MARCO DEL PROGRAMA SOY CAPAZ EN EL DEPARTAMENTO DE SUCRE (Bpin: ) FORMULACIÓN DE UN PROYECTO QUE PERMITA ATENDER A LA POBLACIÓN CON DISCAPACIDAD DE MANERA INTEGRAL EN TODO EL CICLO VITAL, EN EL CUAL SE REALICE LA ENTREGA DE COMPLEMENTO ALIMENTARIO, JORNADAS INTEGRALES DE ATENCIÓN Y UN EJERCICIO DE SENSIBILIZACIÓN CON CU (Bpin: ) ADQUISICIÓN DE PRODUCTOS DE APOYO PARA PERSONAS EN CONDICIÓN DE DISCAPACIDAD DEL DEPAETAMENTO DE SUCRE (Bpin: ) | AM19: 72 | AN19: 0.45 | AO19: Medio | AP19: 144 | AQ19: 0.9 | AR19: Alto | AS19: 109 | AT19: 0.68125 | AU19: Alto | AV19: 325 | AW19: 1 | AX19: Superior | AY19: 60000000 | AZ19: 0 | BA19: 0 | BB19: 0 | BC19: 0 | BD19: 0 | BE19: 0 | BF19: 0 | BG19: 0 | BH19: 0 | BI19: 60000000 | BJ19: 63000000 | BK19: 0 | BL19: 0 | BM19: 0 | BN19: 0 | BO19: 0 | BP19: 0 | BQ19: 0 | BR19: 0 | BS19: 0 | BT19: 63000000 | BU19: 66150000 | BV19: 0 | BW19: 0 | BX19: 0 | BY19: 0 | BZ19: 0 | CA19: 0 | CB19: 0 | CC19: 0 | CD19: 0 | CE19: 66150000 | CF19: 69457500 | CG19: 0 | CH19: 0 | CI19: 0 | CJ19: 0 | CK19: 0 | CL19: 0 | CM19: 0 | CN19: 0 | CO19: 0 | CP19: 69457500 | CQ19: 258607500 | CR19: 03/10/2024: Se realizo la adquisición de sillas de ruedas neurologicas, la Gobernación es la encargada de realizar la entrega de las mismas. | CS19: Feria Sucre sin limites y entrega de ayudas tecnicas a personas con discapacidad
A20: MT017 | B20: 2 | C20: Transformación del Ser Humano | D20: Porcentaje de ejecución de las actividades del Plan de Acción de la Política Pública de discapacidad 2019-2029 implementadas en el departamento de Sucre | E20: 0,25 | F20: Porcentaje | G20: 2023 | H20: Informe Politica Publica de Discapacidad | I20: 0,5 | J20: 3 Salud y bienestar | K20: Inclusión Social | L20: 5 | M20: Soy Capaz | N20: Inclusión Social y Reconciliación | O20: 41 | P20: Atención integral de población en situación permanente de desprotección social y/o familiar | Q20: 4104 | R20: Servicio de educación informal a los cuidadores del adulto mayor | S20: 4104010 | T20: Cuidadores cualificados | U20: 410401000 | V20: Servicios dirigidos a fortalecer las habilidades y competencias de los cuidadores del adulto mayor en temas de protección y atención integral a esta población. | W20: Número de cuidadores | X20: No | Y20: Número | Z20: 80 | AA20: Acumulativo | AB20: Secretaria de Inclusión Social, Mujer y Equidad de Genero | AC20: 0 | AD20: 30 | AE20: 30 | AF20: 20 | AH20: CAPACITAR NIÑOS, NIÑAS Y ADOLECENTES EN TEMAS DE MEDIO AMBIENTE Y CUIDADO DE RECURSOS (Tipo Banco: Banco de Gestiones) (Meta de la gestión: 411) Formación a cuidadores en articulacion en el convenio de cooperación internacional No 109 del 2024, suscrito entre el ministerio de igualdad y equidad de Colombia - dirección de cuidado - y el programa de la Naciones Unidad para el Desarrollo PNUD. En la estrategia redes del cuidado, estrategia de fortalecimiento politico a persona cuidadoras. (Tipo Banco: Banco de Gestiones) (Meta de la gestión: 81) FORMACIÓN A CUIDADORES DE PERSONAS CON DISCAPACIDAD Y ADULTOS MAYORES PARA EL FORTALECIMIENTO DE UNIDADES PRODUCTIVAS EN EL DEPARTAMENTO DE SUCRE (BPIN: ) (Tipo de Banco: Banco Territorial) | AI20: CAPACITAR NIÑOS, NIÑAS Y ADOLECENTES EN TEMAS DE MEDIO AMBIENTE Y CUIDADO DE RECURSOS (Tipo de banco: Banco de Gestiones) (Meta de la gestión: 411) (Ejecutado: 411) Formación a cuidadores en articulacion en el convenio de cooperación internacional No 109 del 2024, suscrito entre el ministerio de igualdad y equidad de Colombia - dirección de cuidado - y el programa de la Naciones Unidad para el Desarrollo PNUD. En la estrategia redes del cuidado, estrategia de fortalecimiento politico a persona cuidadoras. (Tipo de banco: Banco de Gestiones) (Meta de la gestión: 81) (Ejecutado: 81) FORMACIÓN A CUIDADORES DE PERSONAS CON DISCAPACIDAD Y ADULTOS MAYORES PARA EL FORTALECIMIENTO DE UNIDADES PRODUCTIVAS EN EL DEPARTAMENTO DE SUCRE (BPIN: ) (Tipo de banco: Banco Territorial) (Meta total del proyecto: 30) (Ejecutado: 80.0) | AJ20: PROCESO FORMATIVO A CUIDADORES DE PERSONAS CON DISCAPACIDAD QUE PERMITA ADEMÁS LA ENTREGA DE UN CAPITAL SEMILLA AL FINAL DEL PROCESO PARA PROPICIAR CONDICIONES DE GENERACIÓN DE INGRESO Y SOSTENIBILIDAD A LAS FAMILIAS | AL20: PROCESO FORMATIVO A CUIDADORES DE PERSONAS CON DISCAPACIDAD QUE PERMITA ADEMÁS LA ENTREGA DE UN CAPITAL SEMILLA AL FINAL DEL PROCESO PARA PROPICIAR CONDICIONES DE GENERACIÓN DE INGRESO Y SOSTENIBILIDAD A LAS FAMILIAS (Bpin: ) | AP20: 572 | AQ20: 1 | AR20: Superior | AT20: 1 | AU20: Superior | AV20: 572 | AW20: 1 | AX20: Superior | AY20: 0 | AZ20: 100000000 | BA20: 0 | BB20: 0 | BC20: 0 | BD20: 0 | BE20: 0 | BF20: 0 | BG20: 0 | BH20: 0 | BI20: 100000000 | BJ20: 0 | BK20: 200000000 | BL20: 0 | BM20: 0 | BN20: 0 | BO20: 0 | BP20: 0 | BQ20: 0 | BR20: 0 | BS20: 0 | BT20: 200000000 | BU20: 0 | BV20: 200000000 | BW20: 0 | BX20: 0 | BY20: 0 | BZ20: 0 | CA20: 0 | CB20: 0 | CC20: 0 | CD20: 0 | CE20: 200000000 | CF20: 0 | CG20: 200000000 | CH20: 0 | CI20: 0 | CJ20: 0 | CK20: 0 | CL20: 0 | CM20: 0 | CN20: 0 | CO20: 0 | CP20: 200000000 | CQ20: 700000000 | CS20: Cuidadores de poblaciòn adulto mayor y personas en condiciòn de discapacidad capacitados
A21: MT018 | B21: 3 | C21: Transformación del Ser Humano | D21: Porcentaje de ejecución de las actividades del Plan de Acción de la Política Pública de discapacidad 2019-2029 implementadas en el departamento de Sucre | E21: 0,25 | F21: Porcentaje | G21: 2023 | H21: Informe Politica Publica de Discapacidad | I21: 0,5 | J21: 3. Salud y bienestar | K21: Inclusión Social | L21: 5 | M21: Soy Capaz | N21: Inclusión Social y Reconciliación | O21: 45 | P21: Fortalecimiento del buen gobierno para el respeto y garantía de los derechos humanos | Q21: 4502 | R21: Servicio de promoción de la garantía de derechos | S21: 4502038 | T21: Estrategias de promoción de la garantía de derechos implementadas | U21: 450203800 | V21: Incluye el desarrollo de acciones orientadas a divulgar y promover los mecanismos de atención, protección y ejercicio de los derechos de las mujeres, población LGTBI y personas y comunidades en riesgo así como la prevención de su vulneración. | W21: Número de estrategias | X21: No | Y21: Número | Z21: 1 | AA21: Acumulativo | AB21: Secretaria de Inclusión Social, Mujer y Equidad de Genero | AC21: 0 | AD21: 1 | AE21: 0 | AF21: 0 | AH21: Diseño e implementación de la Campaña Soy Capaz, para la inclusión, empoderamiento, prevención de estigma y/o violencias contra las personas con discapacidad y participación activa de personas con discapacidad en el Departamento de Sucre (Tipo Banco: Banco de Gestiones) (Meta de la gestión: 1) | AI21: Diseño e implementación de la Campaña Soy Capaz, para la inclusión, empoderamiento, prevención de estigma y/o violencias contra las personas con discapacidad y participación activa de personas con discapacidad en el Departamento de Sucre (Tipo de banco: Banco de Gestiones) (Meta de la gestión: 1) (Ejecutado: 1) | AP21: 1 | AQ21: 1 | AR21: Superior | AV21: 1 | AW21: 1 | AX21: Superior | AY21: 0 | AZ21: 0 | BA21: 0 | BB21: 0 | BC21: 0 | BD21: 0 | BE21: 0 | BF21: 0 | BG21: 0 | BH21: 0 | BI21: 0 | BJ21: 0 | BK21: 0 | BL21: 0 | BM21: 0 | BN21: 0 | BO21: 0 | BP21: 0 | BQ21: 0 | BR21: 0 | BS21: 0 | BT21: 0 | BU21: 0 | BV21: 0 | BW21: 0 | BX21: 0 | BY21: 0 | BZ21: 0 | CA21: 0 | CB21: 0 | CC21: 0 | CD21: 0 | CE21: 0 | CF21: 0 | CG21: 0 | CH21: 0 | CI21: 0 | CJ21: 0 | CK21: 0 | CL21: 0 | CM21: 0 | CN21: 0 | CO21: 0 | CP21: 0 | CQ21: 0 | CS21: Campaña para la promociòn de los derechos de la poblaciòn en condiciòn de discapacidad Rutas de implementaciòn de atenciòn a victimas de violencia
A22: MT019 | B22: 1 | C22: Transformación del Ser Humano | D22: Porcentaje de ejecución de las actividades del Plan de Acción de la Política Pública de Mujer implementadas en el departamento de Sucre | E22: 0,25 | F22: Porcentaje | G22: 2023 | H22: Informe de cumplimiento política pública de mujer | I22: 0,5 | J22: 3. Salud y bienestar | K22: Inclusión Social | L22: 6 | M22: Mujeres empoderadas, productivas y con oportunidades | N22: Gobierno Territorial | O22: 45 | P22: Fortalecimiento del buen gobierno para el respeto y garantía de los derechos humanos | Q22: 4502 | R22: Servicio de integración de la oferta pública | S22: 4502033 | T22: Espacios de integración de oferta pública generados | U22: 450203300 | V22: Corresponde al diseño e implementación de espacios que articulen la oferta institucional para que los ciudadanos conozcan sus derechos y deberes y los mecanismos de acceso a la oferta publica. | W22: Número de espacios | X22: No | Y22: Número | Z22: 40 | AA22: Acumulativo | AB22: Secretaria de Inclusión Social, Mujer y Equidad de Genero | AC22: 10 | AD22: 10 | AE22: 10 | AF22: 10 | AG22: Se realizaron concejos consultivos en Galeras, Sampues, Sincé y Morroa; de igual forma con asociacones de mujeres en sampues, corozal, sincelejo y guaranda. Se llevo la oferta institucional We effect en ovejas y los palmitos (BPIN: Por Gestión) (Meta del Proyecto: 10) (Ejecución 2024: 10) APOYO LOGISTICO PARA EL DESARROLLO DE REUNIONES, ENCUENTROS Y MECANISMOS PARA LA GENERACIÓN INTERACCIÓN PÚBLICA Y DIVULGACIÓN DE LA OFERTA INSTITUCIONAL DE LA GOBERNACIÓN DE SUCRE (450203300: Espacios de integración de oferta pública generados - HOMOLOGAD (BPIN: 2024002700026) (Meta del Proyecto: 31) (Ejecución 2024: 31) | AH22: PROYECTO CRISALIDA, EMPODERAMIENTO ECONOMICO, PSICOLOGICO Y SOCIOPOLITICO DE LAS MUJERES DE LA CAMPAÑA YO SOY EMPODERADA Y PRODUCTIVA DEL DEPARTAMENTO DE SUCRE (BPIN: ) (Tipo de Banco: Banco Territorial) | AI22: OFERTA DE LA CAMPAÑA MUJER EMPODERADA Y PRODUCTIVA A LAS MUJERES RURAL (Tipo de banco: Banco de Gestiones) (Meta de la gestión: ) (Ejecutado: 11) | AJ22: Meta alcanzada por gestión (BPIN: Por Gestión) CURSO SOBRE MANIPULACIÓN DE ALIMENTOS DIRIGIDO A MUJERES RURALES (Meta Programada: 1) (Tipo de Banco: Banco de Gestiones) | AK22: CURSO SOBRE MANIPULACIÓN DE ALIMENTOS DIRIGIDO A MUJERES RURALES (Meta programada: 1) (Ejecución: 1) (Tipo de banco: Banco de Gestiones) | AL22: Meta alcanzada por gestión (Bpin: Por Gestión) | AM22: 41 | AN22: 1 | AO22: Superior | AP22: 11 | AQ22: 1 | AR22: Superior | AS22: 1 | AT22: 1 | AU22: Superior | AV22: 53 | AW22: 1 | AX22: Superior | AY22: 80000000 | AZ22: 0 | BA22: 0 | BB22: 0 | BC22: 0 | BD22: 0 | BE22: 0 | BF22: 0 | BG22: 0 | BH22: 0 | BI22: 80000000 | BJ22: 84000000 | BK22: 0 | BL22: 0 | BM22: 0 | BN22: 0 | BO22: 0 | BP22: 0 | BQ22: 0 | BR22: 0 | BS22: 0 | BT22: 84000000 | BU22: 88200000 | BV22: 0 | BW22: 0 | BX22: 0 | BY22: 0 | BZ22: 0 | CA22: 0 | CB22: 0 | CC22: 0 | CD22: 0 | CE22: 88200000 | CF22: 92610000 | CG22: 0 | CH22: 0 | CI22: 0 | CJ22: 0 | CK22: 0 | CL22: 0 | CM22: 0 | CN22: 0 | CO22: 0 | CP22: 92610000 | CQ22: 344810000 | CR22: Se realizo la redistribución de la meta por vigencia para dar alcance por gestión | CS22: Mecanismo articulador de mujeres para la prevenciòn de las violencias basadas en genero.
A23: MT020 | B23: 2 | C23: Transformación del Ser Humano | D23: Porcentaje de ejecución de las actividades del Plan de Acción de la Política Pública de Mujer implementadas en el departamento de Sucre | E23: 0,25 | F23: Porcentaje | G23: 2023 | H23: Informe de cumplimiento política pública de mujer | I23: 0,5 | J23: 3. Salud y bienestar | K23: Inclusión Social | L23: 6 | M23: Mujeres empoderadas, productivas y con oportunidades | N23: Gobierno Territorial | O23: 45 | P23: Fortalecimiento del buen gobierno para el respeto y garantía de los derechos humanos | Q23: 4502 | R23: Servicio de apoyo para la implementación de medidas en derechos humanos y derecho internacional humanitario | S23: 4502024 | T23: Medidas implementadas en cumplimiento de las obligaciones internacionales en materia de Derechos Humanos y Derecho Internacional Humanitario | U23: 450202400 | V23: Implementar decisiones de instancias internacionales frente a violaciones de Derechos Humanos para el cumplimiento de las obligaciones que tiene el Estado colombiano. | W23: Número de medidas | X23: No | Y23: Número | Z23: 2 | AA23: No acumulativo | AB23: Secretaria de Inclusión Social, Mujer y Equidad de Genero | AC23: 2 | AD23: 2 | AE23: 2 | AF23: 2 | AG23: ESTRATEGIA "SOY MUJER EMPODERADA Y PRODUCTIVA" (BPIN: Por Gestión) (Meta del Proyecto: ) (Ejecución 2024: 1) | AH23: APOYO A LAS MEDIDAS DE ATENCIÓN TEMPORAL PARA CASOS DE TRATA DE PERSONAS Y OTRAS FORMAS DE VIOLENCIA REPORTADAS EN LA VIGENCIA 2025 EN EL DEPARTAMENTO DE SUCRE (BPIN: 202400000006061) (Tipo de Banco: Banco Territorial) “FORTALECIMIENTO ESTRATEGICO PARA PREVENIR, DETECTAR Y ACOMPAÑAR A VÍCTIMAS DE VIOLENCIA BASADAS EN GÉNERO MEDIANTE UNA SOLUCION TECNOLOGICA INTEGRADA, EN EL DEPARTAMENTO DE SUCRE” (BPIN: 202400000001165) (Tipo de Banco: Banco Territorial) | AI23: Apoyo a las medidas de atención temporal para casos de trata de personas y otras formas de violencia reportadas en la vigencia 2025 en el departamento de Sucre (Bpin: 202400000006061) (Tipo de Banco: Banco Territorial) (Meta total del indicador: 1.0) (Meta total de la vigencia: 1.0) (Ejecutado: 0.0) “FORTALECIMIENTO ESTRATEGICO PARA PREVENIR, DETECTAR Y ACOMPAÑAR A VÍCTIMAS DE VIOLENCIA BASADAS EN GÉNERO MEDIANTE UNA SOLUCION TECNOLOGICA INTEGRADA, EN EL DEPARTAMENTO DE SUCRE” (BPIN: 202400000001165) (Tipo de banco: Banco Territorial) (Meta total del proyecto: 1) (Ejecutado: 1.0) | AJ23: Apoyo a las medidas de atención temporal para casos de trata de personas y otras formas de violencia reportadas en la vigencia 2026 en eldepartamento de Sucre (BPIN: 202500000047992) (Meta del proyecto: 1) (Tipo de Banco: Banco Territorial) (Estado en Portafolio: En proceso de contratación) Fortalecimiento DE CAPACIDADES PSICOSOCIALES, PRODUCTIVAS Y PARTICIPATIVAS DE LAS MUJERES DEL DEPARTAMENTO DE Sucre (BPIN: 202600000000479) (Meta del proyecto: 1) (Tipo de Banco: Banco Territorial) (Estado en Portafolio: En proceso de contratación) PROYECTO APOYO A LAS MEDIDAS DE ATENCIÓN TEMPORAL PARA CASOS DE TRATA DE PERSONAS Y OTRAS FORMAS DE VIOLENCIAS REPORTADAS EN LA VIGENCIA 2026 EN EL DEPARTAMENTO DE SUCRE | AL23: PROYECTO APOYO A LAS MEDIDAS DE ATENCIÓN TEMPORAL PARA CASOS DE TRATA DE PERSONAS Y OTRAS FORMAS DE VIOLENCIAS REPORTADAS EN LA VIGENCIA 2027 EN EL DEPARTAMENTO DE SUCRE (Bpin: ) | AM23: 1 | AN23: 0.5 | AO23: Medio | AP23: 1 | AQ23: 0.5 | AR23: Medio | AT23: 0 | AU23: Minimo | AV23: 2 | AW23: 1 | AX23: Superior | AY23: 50000000 | AZ23: 0 | BA23: 0 | BB23: 0 | BC23: 0 | BD23: 0 | BE23: 0 | BF23: 0 | BG23: 0 | BH23: 0 | BI23: 50000000 | BJ23: 52500000 | BK23: 0 | BL23: 0 | BM23: 0 | BN23: 0 | BO23: 0 | BP23: 0 | BQ23: 0 | BR23: 0 | BS23: 0 | BT23: 52500000 | BU23: 55125000 | BV23: 0 | BW23: 0 | BX23: 0 | BY23: 0 | BZ23: 0 | CA23: 0 | CB23: 0 | CC23: 0 | CD23: 0 | CE23: 55125000 | CF23: 57881250 | CG23: 0 | CH23: 0 | CI23: 0 | CJ23: 0 | CK23: 0 | CL23: 0 | CM23: 0 | CN23: 0 | CO23: 0 | CP23: 57881250 | CQ23: 215506250 | CR23: 03/10/2024: se reviso la meta encontrandose una diferencia entre la meta cuatrenio y la meta por vigencia, dejando la meta como de mantenimiento con una meta de dos por vigencia. Se realizo proyecto casa refugio, APOYO A LAS MEDIDAS DE ATENCIÓN TEMPORAL PARA CASOS DE TRATA DE PERSONAS Y OTRAS FORMAS DE VIOLENCIA REPORTADAS EN LA VIGENCIA 2024 EN EL DEPARTAMENTO DE SUCRE (2024002700051), el cual no cuenta con financiación. | CS23: CASA REFUGIO PARA MUJERES VICTIMAS DE LA VIOLENCIA Y SUS HIJOS Y CASA PARA LA DIGNIDAD
A24: MT021 | B24: 3 | C24: Transformación del Ser Humano | D24: Porcentaje de ejecución de las actividades del Plan de Acción de la Política Pública de Mujer implementadas en el departamento de Sucre | E24: 0,25 | F24: Porcentaje | G24: 2023 | H24: Informe de cumplimiento política pública de mujer | I24: 0,5 | J24: 3. Salud y bienestar | K24: Inclusión Social | L24: 6 | M24: Mujeres empoderadas, productivas y con oportunidades | N24: Gobierno Territorial | O24: 45 | P24: Fortalecimiento del buen gobierno para el respeto y garantía de los derechos humanos | Q24: 4502 | R24: Servicio de apoyo financiero para empresas y emprendimientos productivos | S24: 4502039 | T24: Personas y empresas beneficiadas | U24: 450203900 | V24: Comprende el apoyo con recursos monetarios para el fortalecimiento de empresas y el desarrollo de emprendimientos de personas y comunidades en riesgo, mujeres y población LGTBI. | W24: Número de personas y empresas | X24: No | Y24: Número | Z24: 930 | AA24: Acumulativo | AB24: Secretaria de Inclusión Social, Mujer y Equidad de Genero | AC24: 0 | AD24: 400 | AE24: 265 | AF24: 265 | AH24: ENTREGA DE ROLLOS DE TELA A MUJERES VULNERABLES (Tipo Banco: Banco de Gestiones) (Meta de la gestión: ) FORTALECIMIENTO DEL SECTOR AGROINDUSTRIAL MEDIANTE LA DOTACIÓN DE ACTIVOS Y FORMACIÓN A LA ASOCIACIÓN AMUCIPALMITO EN SU PLANTA PILOTO DE TRANSFORMACIÓN DE FRUTAS Y VERDURAS EN EL CORREGIMIENTO DEL PIÑAL, MUNICIPIO DE LOS PALMITOS DEL DEPARTAMENTO DE SUCRE (BPIN: 202400000000536) (Tipo de Banco: Banco Territorial) | AI24: ENTREGA DE ROLLOS DE TELA A MUJERES VULNERABLES (Tipo de banco: Banco de Gestiones) (Meta de la gestión: ) (Ejecutado: 730) | AJ24: Fortalecimiento de la economía arcoíris y promoción del ejercicio y goce pleno de los derechos del sector poblacional LGBTIQ+ en el departamento de Sucre ( Proyecto Arcoiris)- Fortalecimiento de la capacidad productiva de mujeres vulnerables de los munic Fortalecimiento DE CAPACIDADES PSICOSOCIALES, PRODUCTIVAS Y PARTICIPATIVAS DE LAS MUJERES DEL DEPARTAMENTO DE Sucre (BPIN: 202600000000479) (Meta del proyecto: 36) (Tipo de Banco: Banco Territorial) ENTREGA DE ALEVINOS A MUJERES RURALES DEL MUNICIPIO DE SAN MARCOS. ENTREGA DE TELAS A MUJERES AFRO. (Meta Programada: 265) (Tipo de Banco: Banco de Gestiones) | AK24: ENTREGA DE ALEVINOS A MUJERES RURALES DEL MUNICIPIO DE SAN MARCOS. ENTREGA DE TELAS A MUJERES AFRO. (Meta programada: 265) (Ejecución: 117) (Tipo de banco: Banco de Gestiones) | AL24: Fortalecimiento de la economía arcoíris y promoción del ejercicio y goce pleno de los derechos del sector poblacional LGBTIQ+ en el departamento de Sucre ( Proyecto Arcoiris)- Fortalecimiento de la capacidad productiva de mujeres vulnerables de los munic (Bpin: ) | AP24: 730 | AQ24: 1 | AR24: Superior | AS24: 117 | AT24: 1 | AU24: Superior | AV24: 847 | AW24: 0.91075269 | AX24: Alto | AY24: 75000000 | AZ24: 0 | BA24: 0 | BB24: 0 | BC24: 0 | BD24: 0 | BE24: 0 | BF24: 0 | BG24: 0 | BH24: 0 | BI24: 75000000 | BJ24: 78750000 | BK24: 0 | BL24: 0 | BM24: 0 | BN24: 0 | BO24: 0 | BP24: 0 | BQ24: 0 | BR24: 0 | BS24: 0 | BT24: 78750000 | BU24: 82687500 | BV24: 0 | BW24: 0 | BX24: 0 | BY24: 0 | BZ24: 0 | CA24: 0 | CB24: 0 | CC24: 0 | CD24: 0 | CE24: 82687500 | CF24: 86821875 | CG24: 0 | CH24: 0 | CI24: 0 | CJ24: 0 | CK24: 0 | CL24: 0 | CM24: 0 | CN24: 0 | CO24: 0 | CP24: 86821875 | CQ24: 323259375 | CR24: se actualizará en proyecto y Se adelantará proceso contractual para la vigencia 2025. los proyectos señalados para el alcandce de las metas por vigencia 2025, no cuentan con presupuesto para su financiación. | CS24: CONMEMORACIÒN DEL MES DE LA MUJER y proyecto productyivo para personas LGTBIQ+
A25: MT022 | B25: 4 | C25: Transformación del Ser Humano | D25: Porcentaje de ejecución de las actividades del Plan de Acción de la Política Pública de Mujer implementadas en el departamento de Sucre | E25: 0,25 | F25: Porcentaje | G25: 2023 | H25: Informe de cumplimiento política pública de mujer | I25: 0,5 | J25: 3. Salud y bienestar | K25: Inclusión Social | L25: 6 | M25: Mujeres empoderadas, productivas y con oportunidades | N25: Inclusión Social y Reconciliación | O25: 45 | P25: Fortalecimiento del buen gobierno para el respeto y garantía de los derechos humanos | Q25: 4502 | R25: Servicio de promoción de la garantía de derechos | S25: 4502038 | T25: Estrategias de promoción de la garantía de derechos implementadas | U25: 450203800 | V25: Incluye el desarrollo de acciones orientadas a divulgar y promover los mecanismos de atención, protección y ejercicio de los derechos de las mujeres, población LGTBI y personas y comunidades en riesgo así como la prevención de su vulneración. | W25: Número de estrategias | X25: No | Y25: Número | Z25: 59 | AA25: Acumulativo | AB25: Secretaria de Inclusión Social, Mujer y Equidad de Genero | AC25: 14 | AD25: 15 | AE25: 15 | AF25: 15 | AG25: TALLERES SALUD MENTAL, PREVENCIÓN VBG, PREVENCIÓN DE EMBARAZO EN ADOLESCENTES, PREVENCIÓN DE SUSTANCIAS PSICOACTIVAS, NUEVAS MASCULINIDADES, PROYECTO DE VIDA Y AUTOESTIMA, LEY 1257 FUNCIONARIOS, LEY 1257 MUJERES, FORMACION LIDERAZGO SOCIOPOLITICO (BPIN: Por gestión) (Meta del Proyecto: 9) (Ejecución 2024: 9) LINEA "YO SI TE CREO", CAMPAÑA MUJER EN LA CARCEL "SOY PODEROSA", MECANISMO ARTICULADOR, FERIAS DE EMPRENDIMIENTO Y FORTALECIMIENTO A LA ASOCIATIVIDAD (BPIN: Por gestión) (Meta del Proyecto: 5) (Ejecución 2024: 5) | AH25: Mecanismo articulador, Linea yo si te creo, nuevas masculinidades, campaña mujer empoderada y productiva, red mujeres de primera, campaña prevención de embarazos, Defensores y defensoritos, Sistema departamental del Cuidado, Estrategia de lucha contra el hambre, Salvia, estrategia soy poderosa, Donación por parte de COMFASUCRE de 400 latas de suplementos nutricionales para niños y niñas de 1 a 5 años, Donación por parte de la Fundación éxito de 1500 paquetes alimentarios (Tipo Banco: Banco de Gestiones) (Meta de la gestión: ) APOYO A LA CREACIÓN DEL BANCO DE ALIMENTOS DEL DEPARTAMENTO DE SUCRE (BPIN: 202500000024121) (Tipo de Banco: Banco Territorial) FORTALECIMIENTO DE LIDERAZGOS POLITICOS DE MUJERES COMUNALES Y LIDERESAS DEL DEPARTAMENTO DE SUCRE (BPIN: 202500000028833) (Tipo de Banco: Banco Territorial) Apoyo logístico para la realización de actividades culturales y productivas enmarcadas en la conmemoración del día de la mujer durante el año 2025 en el departamento de Sucre (BPIN: 202400000006014) (Tipo de Banco: Banco Territorial) Apoyo PARA LA REALIZACIÓN DE ACTIVIDADES CULTURALES Y ORGANIZATIVAS ENFOCADAS EN LA POBLACIÓN LGBTIQ+ DURANTE EL AÑO 2025 EN ELDEPARTAMENTO DE Sucre (BPIN: 202400000006010) (Tipo de Banco: Banco Territorial) | AI25: Apoyo a la creación del banco de alimentos del departamento de Sucre (Bpin: 202500000024121) (Tipo de Banco: Banco Territorial) (Meta total del indicador: 1.0) (Meta total de la vigencia: 0.0) (Ejecutado: 0.0) Apoyo PARA LA REALIZACIÓN DE ACTIVIDADES CULTURALES Y ORGANIZATIVAS ENFOCADAS EN LA POBLACIÓN LGBTIQ+ DURANTE EL AÑO 2025 EN ELDEPARTAMENTO DE Sucre (Bpin: 202400000006010) (Tipo de Banco: Banco Territorial) (Meta total del indicador: 4.0) (Meta total de la vigencia: 4.0) (Ejecutado: 3.0) Apoyo logístico para la realización de actividades culturales y productivas enmarcadas en la conmemoración del día de la mujer durante el año 2025 en el departamento de Sucre (Bpin: 202400000006014) (Tipo de Banco: Banco Territorial) (Meta total del indicador: 1.0) (Meta total de la vigencia: 1.0) (Ejecutado: 1.0) Fortalecimiento de Liderazgos políticos de mujeres Comunales y Lideresas del Departamento de Sucre (Bpin: 202500000028833) (Tipo de Banco: Banco Territorial) (Meta total del indicador: 1.0) (Meta total de la vigencia: 1.0) (Ejecutado: 1.0) Mecanismo articulador, Linea yo si te creo, nuevas masculinidades, campaña mujer empoderada y productiva, red mujeres de primera, campaña prevención de embarazos, Defensores y defensoritos, Sistema departamental del Cuidado, Estrategia de lucha contra el hambre, Salvia, estrategia soy poderosa, Donación por parte de COMFASUCRE de 400 latas de suplementos nutricionales para niños y niñas de 1 a 5 años, Donación por parte de la Fundación éxito de 1500 paquetes alimentarios (Tipo de banco: Banco de Gestiones) (Meta de la gestión: ) (Ejecutado: 13) | AJ25: Apoyo a la creación del banco de alimentos del departamento de Sucre (BPIN: 202500000024121) (Meta del proyecto: 1) (Tipo de Banco: Banco Territorial) (Estado en Portafolio: En Ejecución) Fortalecimiento a la salud y nutrición a personas viviendo con vih/sida para el mejoramiento de sus condiciones de vida en los municipios de Sincelejo, Corozal, San Marcos, Toluviejo, Sampués y Sincé, en el departamento de Sucre (BPIN: 202500000028388) (Meta del proyecto: 1) (Tipo de Banco: Banco Territorial) (Estado en Portafolio: En proceso de liquidación) Fortalecimiento a la salud y nutrición a personas viviendo con vih/sida para el mejoramiento de sus condiciones de vida en los municipios de Sincelejo, Corozal, San Marcos, Toluviejo, Sampués y Sincé durante el año 2026 en el departamento de Sucre (BPIN: 202500000047734) (Meta del proyecto: 1) (Tipo de Banco: Banco Territorial) (Estado en Portafolio: En proceso de contratación) Apoyo a la creación del banco de alimentos del departamento de Sucre (BPIN: 202500000024121) (Meta del proyecto: 1) (Tipo de Banco: Banco Territorial) (Estado en Portafolio: En estudios previos) FORTALECIMIENTO DE LA ECONOMÍA ARCOÍRIS Y PROMOCIÓN DEL EJERCICIO Y GOCE PLENO DE LOS DERECHOS DEL SECTOR POBLACIONAL LGBTIQ+ EN EL DEPARTAMENTO DE SUCRE (PROYECTO ARCOIRIS) APOYO LOGÍSTICO PARA LA CREACIÓN, EL FORTALECIMIENTO Y LA CONSOLIDACIÓN DE LA RED MUJER ESCUCHA DEL DEPARTAMENTO DE SUCRE Y EL I ENCUENTRO POLÍTICO DE MUJERES DEL DEPARTAMENTO DE SUCRE. PROYECTO APOYO A LAS MEDIDAS DE ATENCIÓN TEMPORAL PARA CASOS DE TRATA DE PERSONAS Y OTRAS FORMAS DE VIOLENCIAS REPORTADAS EN LA VIGENCIA 2024 EN EL DEPARTAMENTO DE SUCRE PROYECTO FORTALECIMIENTO A LA SALUD Y NUTRICIÓN A PERSONAS VIVIENDO CON VIH/SIDA PARA EL MEJORAMIENTO DE SUS CONDICIONES DE VIDA EN LOS MUNICIPIOS DE SINCELEJO, COROZAL, SAN MARCOS, TOLUVIEJO, TOLU, SAN ONOFRE, SAMPUÉS, MAJAGUAL, SINCÉ Y LOS PALMITOS EN E CASA PARA LA DIGNIDAD DE LA MUJER (339 DE LA LEY 2294 DE 2023 PND) Apoyo AL FORTALECIMIENTO DEL BANCO DE ALIMENTOS DEL DEPARTAMENTO DE Sucre (BPIN: 202500000048057) (Meta del proyecto: 1) (Tipo de Banco: Banco Territorial) ARTICULACIÓN CON SALVIA (SISTEMA DE PREVENCIÓN DE VIOLENCIAS DEL MINISTERIO DE LA IGUALDAD) ESTRATEGIA "YO SI TE CREO" SISTEMA DEL CUIDADO DEPARTAMENTAL. ESTRATEGIA "SOY MUJER EMPODERADA Y PRODUCTIVA" ESTRATEGIA "MUJERES CON LIDERAZGO" MECANISMO ARTICULADOR. CAMPAÑAS DE PREVENCIÓN DE EMBARAZO. NUEVAS MASCULINIDADES. ESTRATEGIA LUCHA CONTRA EL HAMBRE. (Meta Programada: 9) (Tipo de Banco: Banco de Gestiones) | AK25: ARTICULACIÓN CON SALVIA (SISTEMA DE PREVENCIÓN DE VIOLENCIAS DEL MINISTERIO DE LA IGUALDAD) ESTRATEGIA "YO SI TE CREO" SISTEMA DEL CUIDADO DEPARTAMENTAL. ESTRATEGIA "SOY MUJER EMPODERADA Y PRODUCTIVA" ESTRATEGIA "MUJERES CON LIDERAZGO" MECANISMO ARTICULADOR. CAMPAÑAS DE PREVENCIÓN DE EMBARAZO. NUEVAS MASCULINIDADES. ESTRATEGIA LUCHA CONTRA EL HAMBRE. (Meta programada: 9) (Ejecución: 9) (Tipo de banco: Banco de Gestiones) Fortalecimiento a la salud y nutrición a personas viviendo con vih/sida para el mejoramiento de sus condiciones de vida en los municipios de Sincelejo, Corozal, San Marcos, Toluviejo, Sampués y Sincé, en el departamento de Sucre (Bpin: 202500000028388) (Meta de la vigencia: 1,00) (Ejecucion: 1,00) (Tipo de banco: Banco Territorial) (Estado en portafolio: En proceso de liquidación) | AL25: APOYO LOGÍSTICO PARA LA CREACIÓN, EL FORTALECIMIENTO Y LA CONSOLIDACIÓN DE LA RED MUJER ESCUCHA DEL DEPARTAMENTO DE SUCRE Y EL I ENCUENTRO POLÍTICO DE MUJERES DEL DEPARTAMENTO DE SUCRE. (Bpin: ) CASA PARA LA DIGNIDAD DE LA MUJER (339 DE LA LEY 2294 DE 2023 PND) (Bpin: ) FORTALECIMIENTO DE LA ECONOMÍA ARCOÍRIS Y PROMOCIÓN DEL EJERCICIO Y GOCE PLENO DE LOS DERECHOS DEL SECTOR POBLACIONAL LGBTIQ+ EN EL DEPARTAMENTO DE SUCRE (PROYECTO ARCOIRIS) (Bpin: ) PROYECTO FORTALECIMIENTO A LA SALUD Y NUTRICIÓN A PERSONAS VIVIENDO CON VIH/SIDA PARA EL MEJORAMIENTO DE SUS CONDICIONES DE VIDA EN LOS MUNICIPIOS DE SINCELEJO, COROZAL, SAN MARCOS, TOLUVIEJO, TOLU, SAN ONOFRE, SAMPUÉS, MAJAGUAL, SINCÉ Y LOS PALMITOS EN E (Bpin: ) PROYECTO APOYO A LAS MEDIDAS DE ATENCIÓN TEMPORAL PARA CASOS DE TRATA DE PERSONAS Y OTRAS FORMAS DE VIOLENCIAS REPORTADAS EN LA VIGENCIA 2024 EN EL DEPARTAMENTO DE SUCRE (Bpin: ) | AM25: 14 | AN25: 1 | AO25: Superior | AP25: 18 | AQ25: 1 | AR25: Superior | AS25: 10 | AT25: 0.66666667 | AU25: Alto | AV25: 42 | AW25: 0.71186441 | AX25: Alto | AY25: 50000000 | AZ25: 0 | BA25: 0 | BB25: 0 | BC25: 0 | BD25: 0 | BE25: 0 | BF25: 0 | BG25: 0 | BH25: 0 | BI25: 50000000 | BJ25: 52500000 | BK25: 0 | BL25: 0 | BM25: 0 | BN25: 0 | BO25: 0 | BP25: 0 | BQ25: 0 | BR25: 0 | BS25: 0 | BT25: 52500000 | BU25: 55125000 | BV25: 0 | BW25: 0 | BX25: 0 | BY25: 0 | BZ25: 0 | CA25: 0 | CB25: 0 | CC25: 0 | CD25: 0 | CE25: 55125000 | CF25: 57881250 | CG25: 0 | CH25: 0 | CI25: 0 | CJ25: 0 | CK25: 0 | CL25: 0 | CM25: 0 | CN25: 0 | CO25: 0 | CP25: 57881250 | CQ25: 215506250 | CR25: 03/10/2024: Se tiene proyecto contratado y se realizara la primera entrega el 9 de octubre, se espera beneficiar a 150 personas. De los proyectos programados para alcanzar la meta 2025 4 no cuentan con financiación, solo el proyecto PROYECTO APOYO A LAS MEDIDAS DE ATENCIÓN TEMPORAL PARA CASOS DE TRATA DE PERSONAS Y OTRAS FORMAS DE VIOLENCIAS REPORTADAS EN LA VIGENCIA 2024 EN EL DEPARTAMENTO DE SUCRE, cuenta con recursos.
A26: MT023 | B26: 5 | C26: Transformación del Ser Humano | D26: Porcentaje de ejecución de las actividades del Plan de Acción de la Política Pública de Mujer implementadas en el departamento de Sucre | E26: 0,25 | F26: Porcentaje | G26: 2023 | H26: Informe de cumplimiento política pública de mujer | I26: 0,5 | J26: 3. Salud y bienestar | K26: Inclusión Social | L26: 6 | M26: Mujeres empoderadas, productivas y con oportunidades | N26: Gobierno Territorial | O26: 45 | P26: Fortalecimiento del buen gobierno para el respeto y garantía de los derechos humanos | Q26: 4502 | R26: Servicio de educación informal | S26: 4502034 | T26: Personas Capacitadas | U26: 450203400 | V26: Corresponde al diseño y desarrollo de estrategias educativas que tienen como objetivo brindar oportunidades para apropiar, complementar, actualizar, perfeccionar, renovar o profundizar conocimientos, habilidades, técnicas y prácticas, este conocimiento libre y espontáneo adquirido, puede provenir de personas, entidades, medios masivos de comunicación, medios impresos, tradiciones, costumbres, comportamientos sociales y otros no estructurados y su duración es inferior a 160 horas. | W26: Número de personas | X26: No | Y26: Número | Z26: 250 | AA26: Acumulativo | AB26: Secretaria de Inclusión Social, Mujer y Equidad de Genero | AC26: 160 | AD26: 30 | AE26: 30 | AF26: 30 | AG26: APOYO LOGÍSTICO PARA LA REALIZACIÓN DE ACTIVIDADES CULTURALES Y PRODUCTIVAS ENMARCADAS EN LA CONMEMORACIÓN DEL DÍA DE LA MUJER EN EL DEPARTAMENTO DE SUCRE (BPIN: 2024002700028) (Meta del Proyecto: 160) (Ejecución 2024: 160) CAPACITACIONES EN TEMAS CONTABLES FINANCIERON, EMPRENDIMIENTO, MARKETING DIGITAL,FOTOGRAFÍA, EN GÉNERO, ASOCIATIVIDAD, ENTRE OTROS. (BPIN: Por Gestión) (Meta del Proyecto: 440) (Ejecución 2024: 440) | AH26: TALLER TU MARCA, TU PODER (Tipo Banco: Banco de Gestiones) (Meta de la gestión: 26) FORMAR A LOS FUNCIONARIOS EN LA LEY 1257 DE 2008 (Tipo Banco: Banco de Gestiones) (Meta de la gestión: 50) FORTALECIMIENTO DE LIDERAZGOS POLITICOS DE MUJERES COMUNALES Y LIDERESAS DEL DEPARTAMENTO DE SUCRE (BPIN: 202500000028833) (Tipo de Banco: Banco Territorial) APOYO PARA LA REALIZACIÓN DE ACTIVIDADES CULTURALES Y PRODUCTIVAS ENMARCADAS EN LA CONMEMORACIÓN DEL DIA DE LA MUJER EN EL DEPARTAMENTO DE SUCRE (BPIN: 202400000006014) (Tipo de Banco: Banco Territorial) Apoyo a la creación del banco de alimentos del departamento de Sucre (BPIN: 202500000024121) (Tipo de Banco: Banco Territorial) Apoyo PARA LA REALIZACIÓN DE ACTIVIDADES CULTURALES Y ORGANIZATIVAS ENFOCADAS EN LA POBLACIÓN LGBTIQ+ DURANTE EL AÑO 2025 EN ELDEPARTAMENTO DE Sucre (BPIN: 202400000006010) (Tipo de Banco: Banco Territorial) | AI26: Apoyo a la creación del banco de alimentos del departamento de Sucre (Bpin: 202500000024121) (Tipo de Banco: Banco Territorial) (Meta total del indicador: 300.0) (Meta total de la vigencia: 0.0) (Ejecutado: 0.0) Apoyo PARA LA REALIZACIÓN DE ACTIVIDADES CULTURALES Y ORGANIZATIVAS ENFOCADAS EN LA POBLACIÓN LGBTIQ+ DURANTE EL AÑO 2025 EN ELDEPARTAMENTO DE Sucre (Bpin: 202400000006010) (Tipo de Banco: Banco Territorial) (Meta total del indicador: 133.0) (Meta total de la vigencia: 133.0) (Ejecutado: 76.0) Apoyo logístico para la realización de actividades culturales y productivas enmarcadas en la conmemoración del día de la mujer durante el año 2025 en el departamento de Sucre (Bpin: 202400000006014) (Tipo de Banco: Banco Territorial) (Meta total del indicador: 741.0) (Meta total de la vigencia: 741.0) (Ejecutado: 413.0) Fortalecimiento de Liderazgos políticos de mujeres Comunales y Lideresas del Departamento de Sucre (Bpin: 202500000028833) (Tipo de Banco: Banco Territorial) (Meta total del indicador: 100.0) (Meta total de la vigencia: 100.0) (Ejecutado: 100.0) TALLER TU MARCA, TU PODER (Tipo de banco: Banco de Gestiones) (Meta de la gestión: 26) (Ejecutado: 26) FORMAR A LOS FUNCIONARIOS EN LA LEY 1257 DE 2008 (Tipo de banco: Banco de Gestiones) (Meta de la gestión: 50) (Ejecutado: 61) | AJ26: CAPACITACIÓN A MUEJRES VULNERABLES PARA EL FORTALECIMIENTO DE SU ACTIVIDAD ECONOMICA Apoyo a la creación del banco de alimentos del departamento de Sucre (BPIN: 202500000024121) (Meta del proyecto: 300) (Tipo de Banco: Banco Territorial) Fortalecimiento a la salud y nutrición a personas viviendo con vih/sida para el mejoramiento de sus condiciones de vida en los municipios de Sincelejo, Corozal, San Marcos, Toluviejo, Sampués y Sincé, en el departamento de Sucre (BPIN: 202500000028388) (Meta del proyecto: 150) (Tipo de Banco: Banco Territorial) Fortalecimiento a la salud y nutrición a personas viviendo con vih/sida para el mejoramiento de sus condiciones de vida en los municipios de Sincelejo, Corozal, San Marcos, Toluviejo, Sampués y Sincé durante el año 2026 en el departamento de Sucre (BPIN: 202500000047734) (Meta del proyecto: 150) (Tipo de Banco: Banco Territorial) Apoyo AL FORTALECIMIENTO DEL BANCO DE ALIMENTOS DEL DEPARTAMENTO DE Sucre (BPIN: 202500000048057) (Meta del proyecto: 200) (Tipo de Banco: Banco Territorial) | AK26: Fortalecimiento a la salud y nutrición a personas viviendo con vih/sida para el mejoramiento de sus condiciones de vida en los municipios de Sincelejo, Corozal, San Marcos, Toluviejo, Sampués y Sincé durante el año 2026 en el departamento de Sucre (Bpin: 202500000047734) (Meta de la vigencia: 150,00) (Ejecucion: 150,00) (Tipo de banco: Banco Territorial) (Estado en portafolio: ) | AL26: CAPACITACIÓN A MUEJRES VULNERABLES PARA EL FORTALECIMIENTO DE SU ACTIVIDAD ECONOMICA (Bpin: ) | AM26: 600 | AN26: 1 | AO26: Superior | AP26: 676 | AQ26: 1 | AR26: Superior | AS26: 150 | AT26: 1 | AU26: Superior | AV26: 1426 | AW26: 1 | AX26: Superior | AY26: 16000000 | AZ26: 0 | BA26: 0 | BB26: 0 | BC26: 0 | BD26: 0 | BE26: 0 | BF26: 0 | BG26: 0 | BH26: 0 | BI26: 16000000 | BJ26: 16800000 | BK26: 0 | BL26: 0 | BM26: 0 | BN26: 0 | BO26: 0 | BP26: 0 | BQ26: 0 | BR26: 0 | BS26: 0 | BT26: 16800000 | BU26: 17640000 | BV26: 0 | BW26: 0 | BX26: 0 | BY26: 0 | BZ26: 0 | CA26: 0 | CB26: 0 | CC26: 0 | CD26: 0 | CE26: 17640000 | CF26: 18522000 | CG26: 0 | CH26: 0 | CI26: 0 | CJ26: 0 | CK26: 0 | CL26: 0 | CM26: 0 | CN26: 0 | CO26: 0 | CP26: 18522000 | CQ26: 68962000 | CR26: 03/10/2024: Se realizó capacitación a benefiiciarios en temas de mochila wayu y crochet, por Gestión. El proyecto programado para cumplir con las metas de 2025, no cuenta con recursos. Esta meta sera cumplida en articulación la Secretaria de Educación Departamental y Bellas Artes. | CS26: Funcionarios capacitados y mujeres capacitadas con formaciònes para el trabajo y su autonomia productiva, Campañas de prevenciòn de la fobia, bifobia y transfobia. Niños, niñas y adolescentes formados y capacitados.
A27: MT024 | B27: 6 | C27: Transformación del Ser Humano | D27: Porcentaje de ejecución de las actividades del Plan de Acción de la Política Pública de Mujer implementadas en el departamento de Sucre | E27: 0,25 | F27: Porcentaje | G27: 2023 | H27: Informe de cumplimiento política pública de mujer | I27: 0,5 | J27: 3. Salud y bienestar | K27: Inclusión Social | L27: 6 | M27: Mujeres empoderadas, productivas y con oportunidades | N27: Gobierno Territorial | O27: 45 | P27: Fortalecimiento del buen gobierno para el respeto y garantía de los derechos humanos | Q27: 4502 | R27: Servicio de promoción a la participación ciudadana | S27: 4502001 | T27: Espacios de participación promovidos | U27: 450200100 | V27: Corresponde al diseño e implementación de acciones y estrategias que promuevan el ejercicio de la participación ciudadana para el respeto y garantía de los derechos humanos | W27: Número de iniciativas | X27: No | Y27: Número | Z27: 27 | AA27: Acumulativo | AB27: Secretaria de Inclusión Social, Mujer y Equidad de Genero | AC27: 10 | AD27: 7 | AE27: 7 | AF27: 3 | AG27: Se realizó el fortalecimiento a emprendimiento y/o Asociaciones en el ambito economico y psicosocial en los Municipos de Los palmitos, Coveñas, Sincelejo, Ovejas, El Roble, San Marcos, Corozal, Majagual, Sampues y San Onofre. (BPIN: Por Gestión) (Meta del Proyecto: 10) (Ejecución 2024: 10) | AH27: ESPACIO CON CUIDADORAS, CUIDARTE ES AMARTE, ENCUENTRA CON LIDERESAS, FORTALECIMIENTO A MUJERES DEL DEPARTAMENTO A TRAVES DE FORMACION EN PARTICIPACIÓN DE CONVOCATORIAS, LANZAMIENTO DEL VIOLENTOMETRO EN EL LIBRO TOTAL, CONMEMORACIÓN DEL 25N EN EL MUNICIPIO DE SAMPUES, RUMBATERAPIA EN EL MARCO DEL MES DE LA PREVENCIÓN DE LA LUCHA CONTRA CON EL CANCER, APOYO AL MES DE LA PREVENCIÓN DEL CANCER DE MAMA CON LA PARTICIPACIÓN DE LA RUTA DE PREVENCIÓN DEL CANCER DE MAMA Y LA REALIZACIÓN DE 30 EXAMENES. (Tipo Banco: Banco de Gestiones) (Meta de la gestión: 1) FORTALECIMIENTO DE LIDERAZGOS POLITICOS DE MUJERES COMUNALES Y LIDERESAS DEL DEPARTAMENTO DE SUCRE (BPIN: 202500000028833) (Tipo de Banco: Banco Territorial) | AI27: Fortalecimiento de Liderazgos políticos de mujeres Comunales y Lideresas del Departamento de Sucre (Bpin: 202500000028833) (Tipo de Banco: Banco Territorial) (Meta total del indicador: 1.0) (Meta total de la vigencia: 1.0) (Ejecutado: 1.0) ESPACIO CON CUIDADORAS, CUIDARTE ES AMARTE, ENCUENTRA CON LIDERESAS, FORTALECIMIENTO A MUJERES DEL DEPARTAMENTO A TRAVES DE FORMACION EN PARTICIPACIÓN DE CONVOCATORIAS, LANZAMIENTO DEL VIOLENTOMETRO EN EL LIBRO TOTAL, CONMEMORACIÓN DEL 25N EN EL MUNICIPIO DE SAMPUES, RUMBATERAPIA EN EL MARCO DEL MES DE LA PREVENCIÓN DE LA LUCHA CONTRA CON EL CANCER, APOYO AL MES DE LA PREVENCIÓN DEL CANCER DE MAMA CON LA PARTICIPACIÓN DE LA RUTA DE PREVENCIÓN DEL CANCER DE MAMA Y LA REALIZACIÓN DE 30 EXAMENES. (Tipo de banco: Banco de Gestiones) (Meta de la gestión: 1) (Ejecutado: 7) | AJ27: Apoyo logístico para la Creación y el Fortalecimiento de los Consejos Consultivos Municipales de (municipios priorizados) Población LGBTIQ+ y del Fortalecimiento del Consejo Consultivo Departamental Y el I ENCUENTRO Departamental de Consejeros lgbtiq+ Fortalecimiento DE CAPACIDADES PSICOSOCIALES, PRODUCTIVAS Y PARTICIPATIVAS DE LAS MUJERES DEL DEPARTAMENTO DE Sucre (BPIN: 202600000000479) (Meta del proyecto: 2) (Tipo de Banco: Banco Territorial) 2 SOCIALIZACIONES CONVOCATORIA FONDO MUJER. OFERTA INSTITUCIONAL BARRIO LAS MARGARITAS. (Meta Programada: 3) (Tipo de Banco: Banco de Gestiones) | AK27: 2 SOCIALIZACIONES CONVOCATORIA FONDO MUJER. OFERTA INSTITUCIONAL BARRIO LAS MARGARITAS. (Meta programada: 3) (Ejecución: 3) (Tipo de banco: Banco de Gestiones) | AL27: Apoyo logístico para la Creación y el Fortalecimiento de los Consejos Consultivos Municipales de (municipios priorizados) Población LGBTIQ+ y del Fortalecimiento del Consejo Consultivo Departamental Y el I ENCUENTRO Departamental de Consejeros lgbtiq+ (Bpin: ) | AM27: 10 | AN27: 1 | AO27: Superior | AP27: 8 | AQ27: 1 | AR27: Superior | AS27: 3 | AT27: 0.42857143 | AU27: Medio | AV27: 21 | AW27: 0.77777778 | AX27: Alto | AY27: 42000000 | AZ27: 0 | BA27: 0 | BB27: 0 | BC27: 0 | BD27: 0 | BE27: 0 | BF27: 0 | BG27: 0 | BH27: 0 | BI27: 42000000 | BJ27: 44100000 | BK27: 0 | BL27: 0 | BM27: 0 | BN27: 0 | BO27: 0 | BP27: 0 | BQ27: 0 | BR27: 0 | BS27: 0 | BT27: 44100000 | BU27: 46305000 | BV27: 0 | BW27: 0 | BX27: 0 | BY27: 0 | BZ27: 0 | CA27: 0 | CB27: 0 | CC27: 0 | CD27: 0 | CE27: 46305000 | CF27: 48620250 | CG27: 0 | CH27: 0 | CI27: 0 | CJ27: 0 | CK27: 0 | CL27: 0 | CM27: 0 | CN27: 0 | CO27: 0 | CP27: 48620250 | CQ27: 181025250 | CR27: Proyecto en proceso de contratación | CS27: Sesiones Consejo Departamental de Juventudes y asiistencias tecnicas a las alcaldias municipales para el fortalecimiento del Subsistema de participaciòn juvenil
A28: MT025 | B28: 7 | C28: Transformación del Ser Humano | D28: Porcentaje de ejecución de las actividades del Plan de Acción de la Política Pública de Mujer implementadas en el departamento de Sucre | E28: 0,25 | F28: Porcentaje | G28: 2023 | H28: Informe de cumplimiento política pública de mujer | I28: 0,5 | J28: 3. Salud y bienestar | K28: Inclusión Social | L28: 6 | M28: Mujeres empoderadas, productivas y con oportunidades | N28: Salud y Protección Social | O28: 19 | P28: Salud Pública | Q28: 1905 | R28: Servicio de gestión del riesgo en temas de salud sexual y reproductiva | S28: 1905021 | T28: Campañas de gestión del riesgo en temas de salud sexual y reproductiva implementadas | U28: 190502100 | V28: Corresponde a las acciones relacionadas con la prevención y mitigación de riesgos que afectan la salud sexual y reproductiva de las personas en el curso de su vida desde un enfoque de derechos. | W28: Número de campañas | X28: No | Y28: Número | Z28: 300 | AA28: Acumulativo | AB28: Secretaria de Inclusión Social, Mujer y Equidad de Genero | AC28: 30 | AD28: 90 | AE28: 90 | AF28: 90 | AG28: Campañas para promover la salud sexual y reproductiva en 7 instituciones educativas y 1 en el Auditorio fortunato chadid (BPIN: Por Gestión) (Meta del Proyecto: 8) (Ejecución 2024: 8) | AH28: PROYECTO CRISALIDA, EMPODERAMIENTO ECONOMICO, PSICOLOGICO Y SOCIOPOLITICO DE LAS MUJERES DE LA CAMPAÑA YO EMPODERADA Y PRODUCTIVA DEL DEPARTAMENTO DE SUCRE (BPIN: ) (Tipo de Banco: Banco Territorial) | AJ28: Campañas para promover la salud sexual y reproductiva PREVENCIÓN DE EMBARAZO ADOLESCENTE. VIOLENCIAS BASADAS EN GENERO Y SALUD SEXUAL. (Meta Programada: 2) (Tipo de Banco: Banco de Gestiones) | AK28: PREVENCIÓN DE EMBARAZO ADOLESCENTE. VIOLENCIAS BASADAS EN GENERO Y SALUD SEXUAL. (Meta programada: 2) (Ejecución: 2) (Tipo de banco: Banco de Gestiones) | AL28: Campañas para promover la salud sexual y reproductiva (Bpin: ) | AM28: 8 | AN28: 0.26666667 | AO28: Minimo | AP28: 0 | AQ28: 0 | AR28: Minimo | AS28: 2 | AT28: 0.022222222 | AU28: Minimo | AV28: 10 | AW28: 0.033333333 | AX28: Minimo | AY28: 0 | AZ28: 0 | BA28: 0 | BB28: 0 | BC28: 0 | BD28: 0 | BE28: 0 | BF28: 0 | BG28: 0 | BH28: 0 | BI28: 0 | BJ28: 0 | BK28: 0 | BL28: 0 | BM28: 0 | BN28: 0 | BO28: 0 | BP28: 0 | BQ28: 0 | BR28: 0 | BS28: 0 | BT28: 0 | BU28: 0 | BV28: 0 | BW28: 0 | BX28: 0 | BY28: 0 | BZ28: 0 | CA28: 0 | CB28: 0 | CC28: 0 | CD28: 0 | CE28: 0 | CF28: 0 | CG28: 0 | CH28: 0 | CI28: 0 | CJ28: 0 | CK28: 0 | CL28: 0 | CM28: 0 | CN28: 0 | CO28: 0 | CP28: 0 | CQ28: 0 | CR28: Esta meta sera cumplida en articulación la Secretaria de Salud Departamental. | CS28: Campañas para promover la salud sexual y reproductiva
A29: MT026 | B29: 8 | C29: Transformación del Ser Humano | D29: Porcentaje de ejecución de las actividades del Plan de Acción de la Política Pública de Mujer implementadas en el departamento de Sucre | E29: 0,25 | F29: Porcentaje | G29: 2023 | H29: Informe de cumplimiento política pública de mujer | I29: 0,5 | J29: 3. Salud y bienestar | K29: Inclusión Social | L29: 6 | M29: Mujeres empoderadas, productivas y con oportunidades | N29: Deporte y Recreación | O29: 43 | P29: Fomento a la recreación, la actividad física y el deporte | Q29: 4301 | R29: Servicio de educación informal en recreación | S29: 4301035 | T29: Personas capacitadas | U29: 430103500 | V29: Corresponde a la formación a la ciudadanía en recreación, actividad física, deportes social comunitario y/o aprovechamiento del tiempo libre con enfoque diferencial. | W29: Número de personas | X29: No | Y29: Número | Z29: 600 | AA29: Acumulativo | AB29: Secretaria de Inclusión Social, Mujer y Equidad de Genero | AC29: 0 | AD29: 0 | AE29: 300 | AF29: 300 | AJ29: FOMENTO DE LA CULTURA DEPORTIVA PARA MUEJERES DEL DEPARTAMENTO DE SUCRE CURSO DE DEFENSA PERSONAL (Meta Programada: 16) (Tipo de Banco: Banco de Gestiones) | AK29: CURSO DE DEFENSA PERSONAL (Meta programada: 16) (Ejecución: 16) (Tipo de banco: Banco de Gestiones) | AL29: FOMENTO DE LA CULTURA DEPORTIVA PARA MUEJERES DEL DEPARTAMENTO DE SUCRE (Bpin: ) | AS29: 16 | AT29: 0.053333333 | AU29: Minimo | AV29: 16 | AW29: 0.026666667 | AX29: Minimo | AY29: 50000000 | AZ29: 0 | BA29: 0 | BB29: 0 | BC29: 0 | BD29: 0 | BE29: 0 | BF29: 0 | BG29: 0 | BH29: 0 | BI29: 50000000 | BJ29: 52500000 | BK29: 0 | BL29: 0 | BM29: 0 | BN29: 0 | BO29: 0 | BP29: 0 | BQ29: 0 | BR29: 0 | BS29: 0 | BT29: 52500000 | BU29: 55125000 | BV29: 0 | BW29: 0 | BX29: 0 | BY29: 0 | BZ29: 0 | CA29: 0 | CB29: 0 | CC29: 0 | CD29: 0 | CE29: 55125000 | CF29: 57881250 | CG29: 0 | CH29: 0 | CI29: 0 | CJ29: 0 | CK29: 0 | CL29: 0 | CM29: 0 | CN29: 0 | CO29: 0 | CP29: 57881250 | CQ29: 215506250 | CR29: Esta meta sera cumplida en articulación el Inder Departamental. | CS29: Personas capactidadas a traves de la red mujer empoderada y productiva
A30: MT027 | B30: 9 | C30: Transformación del Ser Humano | D30: Porcentaje de ejecución de las actividades del Plan de Acción de la Política Pública de Mujer implementadas en el departamento de Sucre | E30: 0,25 | F30: Porcentaje | G30: 2023 | H30: Informe de cumplimiento política pública de mujer | I30: 0,5 | J30: 3. Salud y bienestar | K30: Inclusión Social | L30: 6 | M30: Mujeres empoderadas, productivas y con oportunidades | N30: Inclusión Social y Reconciliación | O30: 41 | P30: Desarrollo integral de la primera infancia a la juventud, y fortalecimiento de las capacidades de las familias de niñas, niños y adolescentes | Q30: 4102 | R30: Servicios de educación informal a niños, niñas, adolescentes y jóvenes para el reconocimiento de sus derechos | S30: 4102045 | T30: Personas capacitadas | U30: 410204500 | V30: Servicios mediante los cuales se socializan a los niños, niñas, adolescentes y jóvenes; al igual que a sus padres, madres, cuidadores y docentes, los temas relacionados con el reconocimiento de los derechos de la niñez, la adolescencia y la juventud. | W30: Número de personas | X30: No | Y30: Número | Z30: 1100 | AA30: Acumulativo | AB30: Secretaria de Inclusión Social, Mujer y Equidad de Genero | AC30: 500 | AD30: 200 | AE30: 200 | AF30: 200 | AG30: CAPACITACION EN FLORES TROQUELADAS Y TIE DYE (BPIN: Por Gestión) (Meta del Proyecto: 34) (Ejecución 2024: 31) CAPACITACION EN MENTALIDAD Y CULTURA EMPRENDEDORA (BPIN: Por Gestión) (Meta del Proyecto: 23) (Ejecución 2024: 23) CAPACITACION EN CONVOCATORIA DEL FONDO MUJER FOMUR (BPIN: Por Gestión) (Meta del Proyecto: 360) (Ejecución 2024: 360) CAPACITACIÓN A NIÑOS, NIÑAS Y ADOLESCENTES COMO DEFENSORES Y DEFENSORITOS (BPIN: Por Gestión) (Meta del Proyecto: 105) (Ejecución 2024: 105) | AJ30: Fortalecimiento de la capacidad productiva de mujeres vulnerables de los municipios de Corozal, Sincelejo, Coveñas, Majagual, Los Palmitos, Ovejas, Morroa, San Marcos, El Roble, Sincé y Sampués en el departamento de Sucre | AL30: Fortalecimiento de la capacidad productiva de mujeres vulnerables de los municipios de Corozal, Sincelejo, Coveñas, Majagual, Los Palmitos, Ovejas, Morroa, San Marcos, El Roble, Sincé y Sampués en el departamento de Sucre (Bpin: ) | AM30: 519 | AN30: 1 | AO30: Superior | AP30: 0 | AQ30: 0.095 | AR30: Minimo | AT30: 0 | AU30: Minimo | AV30: 519 | AW30: 0.47181818 | AX30: Medio | AY30: 30000000 | AZ30: 0 | BA30: 0 | BB30: 0 | BC30: 0 | BD30: 0 | BE30: 0 | BF30: 0 | BG30: 0 | BH30: 0 | BI30: 30000000 | BJ30: 31500000 | BK30: 0 | BL30: 0 | BM30: 0 | BN30: 0 | BO30: 0 | BP30: 0 | BQ30: 0 | BR30: 0 | BS30: 0 | BT30: 31500000 | BU30: 33075000 | BV30: 0 | BW30: 0 | BX30: 0 | BY30: 0 | BZ30: 0 | CA30: 0 | CB30: 0 | CC30: 0 | CD30: 0 | CE30: 33075000 | CF30: 34728750 | CG30: 0 | CH30: 0 | CI30: 0 | CJ30: 0 | CK30: 0 | CL30: 0 | CM30: 0 | CN30: 0 | CO30: 0 | CP30: 34728750 | CQ30: 129303750 | CS30: Mujeres, jovenes, niños, niñas y adolescentes y familias capacitados con formaciones para su crecimiento academico y autonomia economica
A31: MT028 | B31: 1 | C31: Transformación del Ser Humano | D31: Porcentaje de ejecución de las actividades del plan de acción de la política pública de los sectores LGTBIQ+ en el departamento de Sucre | E31: 0 | F31: Porcentaje | G31: 2023 | H31: Informe Política Publica de los sectores LGTBIQ+ | I31: 0,25 | J31: 3. Salud y bienestar | K31: Inclusión Social | L31: 7 | M31: Oportunidades para la diversidad | N31: Inclusión Social y Reconciliación | O31: 41 | P31: Desarrollo integral de la primera infancia a la juventud, y fortalecimiento de las capacidades de las familias de niñas, niños y adolescentes | Q31: 4102 | R31: Servicios de educación informal a niños, niñas, adolescentes y jóvenes para el reconocimiento de sus derechos | S31: 4102045 | T31: Personas capacitadas | U31: 410204500 | V31: Servicios mediante los cuales se socializan a los niños, niñas, adolescentes y jóvenes; al igual que a sus padres, madres, cuidadores y docentes, los temas relacionados con el reconocimiento de los derechos de la niñez, la adolescencia y la juventud. | W31: Número de personas | X31: No | Y31: Número | Z31: 100 | AA31: Acumulativo | AB31: Secretaria de Inclusión Social, Mujer y Equidad de Genero | AC31: 100 | AD31: 0 | AE31: 0 | AF31: 0 | AG31: Campaña de sensibilización "17 de mayo dia internacional contra la homofobia, bifobia y transfobia" (BPIN: Por Gestión) (Meta del Proyecto: 100) (Ejecución 2024: 100) | AH31: Campaña sobre Homofobia, transfobia, bifobia y lesfobia en la Institución Educativa Carmelo Percy Vergara. (Tipo Banco: Banco de Gestiones) (Meta de la gestión: 64) | AI31: Campaña sobre Homofobia, transfobia, bifobia y lesfobia en la Institución Educativa Carmelo Percy Vergara. (Tipo de banco: Banco de Gestiones) (Meta de la gestión: 64) (Ejecutado: 63) | AJ31: CAMPAÑA HOMOFOBIA, BIFOBIA Y TRANSFOBIA (Meta Programada: 40) (Tipo de Banco: Banco de Gestiones) | AK31: CAMPAÑA HOMOFOBIA, BIFOBIA Y TRANSFOBIA (Meta programada: 40) (Ejecución: 40) (Tipo de banco: Banco de Gestiones) | AM31: 100 | AN31: 1 | AO31: Superior | AP31: 63 | AQ31: 1 | AR31: Superior | AS31: 40 | AV31: 203 | AW31: 1 | AX31: Superior | AY31: 0 | AZ31: 0 | BA31: 0 | BB31: 0 | BC31: 0 | BD31: 0 | BE31: 0 | BF31: 0 | BG31: 0 | BH31: 0 | BI31: 0 | BJ31: 0 | BK31: 0 | BL31: 0 | BM31: 0 | BN31: 0 | BO31: 0 | BP31: 0 | BQ31: 0 | BR31: 0 | BS31: 0 | BT31: 0 | BU31: 0 | BV31: 0 | BW31: 0 | BX31: 0 | BY31: 0 | BZ31: 0 | CA31: 0 | CB31: 0 | CC31: 0 | CD31: 0 | CE31: 0 | CF31: 0 | CG31: 0 | CH31: 0 | CI31: 0 | CJ31: 0 | CK31: 0 | CL31: 0 | CM31: 0 | CN31: 0 | CO31: 0 | CP31: 0 | CQ31: 0 | CR31: 03/10/2024: Se encuentra que la meta de cuatrenio es 100 y la meta de vigenta en 250, se procede a ajustar la meta de vigencia a 100. Se realizó el traslado de la meta para 2024 dado que se ejecutará un proyecto en la presente vigencia, donde se alcanzara la meta, Proyecto se eencuentra en ejecución. | CS31: Mujeres, jovenes, niños, niñas y adolescentes y familias capacitados con formaciones para su crecimiento academico y autonomia economica
A32: MT029 | B32: 2 | C32: Transformación del Ser Humano | D32: Porcentaje de ejecución de las actividades del plan de acción de la política pública de los sectores LGTBIQ+ en el departamento de Sucre | E32: 0 | F32: Porcentaje | G32: 2023 | H32: Informe Política Publica de los sectores LGTBIQ+ | I32: 0,25 | J32: 3. Salud y bienestar | K32: Inclusión Social | L32: 7 | M32: Oportunidades para la diversidad | N32: Gobierno Territorial | O32: 45 | P32: Fortalecimiento del buen gobierno para el respeto y garantía de los derechos humanos | Q32: 4502 | R32: Servicio de apoyo financiero para empresas y emprendimientos productivos | S32: 4502039 | T32: Personas y empresas beneficiadas | U32: 450203900 | V32: Comprende el apoyo con recursos monetarios para el fortalecimiento de empresas y el desarrollo de emprendimientos de personas y comunidades en riesgo, mujeres y población LGTBI. | W32: Número de personas y empresas | X32: No | Y32: Número | Z32: 100 | AA32: Acumulativo | AB32: Secretaria de Inclusión Social, Mujer y Equidad de Genero | AC32: 0 | AD32: 0 | AE32: 100 | AF32: 0 | AG32: SE BENEFICIARON DOS PERSONAS CON UN HORNO DE PANADERIA Y UNA MESA EN ACERO INOXIDABLE (BPIN: Por Gestión) (Meta del Proyecto: 2) (Ejecución 2024: 2) | AH32: APOYO LOGÍSTICO PARA LA REALIZACIÓN DE ACTIVIDADES CULTURALES Y ORGANIZATIVAS EN EL MES DE LA DIVERSIDAD ENFOCADAS EN LA POBLACION LGTBIQ+ DEL DEPARTAMENTO ENTREGA DE ROLLOS DE TELA 2 CONVOCATORIA FONDO MUJER 2 (Tipo Banco: Banco de Gestiones) (Meta de la gestión: ) | AI32: APOYO LOGÍSTICO PARA LA REALIZACIÓN DE ACTIVIDADES CULTURALES Y ORGANIZATIVAS EN EL MES DE LA DIVERSIDAD ENFOCADAS EN LA POBLACION LGTBIQ+ DEL DEPARTAMENTO ENTREGA DE ROLLOS DE TELA 2 CONVOCATORIA FONDO MUJER 2 (Tipo de banco: Banco de Gestiones) (Meta de la gestión: ) (Ejecutado: 18) | AJ32: Fortalecimiento de la economía arcoíris y promoción del ejercicio y goce pleno de los derechos del sector poblacional LGBTIQ+ en el departamento de Sucre (Proyecto Arcoiris) Apoyo PARA LA REALIZACIÓN DE ACTIVIDADES CULTURALES Y ORGANIZATIVAS ENFOCADAS EN LA POBLACIÓN LGBTIQ+ DURANTE EL AÑO 2026 EN EL DEPARTAMENTO DE Sucre (BPIN: 202600000001100) (Meta del proyecto: 34) (Tipo de Banco: Banco Territorial) | AM32: 2 | AN32: 1 | AO32: Superior | AP32: 18 | AQ32: 1 | AR32: Superior | AT32: 0 | AU32: Minimo | AV32: 20 | AW32: 0.2 | AX32: Minimo | AY32: 10000000 | AZ32: 0 | BA32: 0 | BB32: 0 | BC32: 0 | BD32: 0 | BE32: 0 | BF32: 0 | BG32: 0 | BH32: 0 | BI32: 10000000 | BJ32: 10500000 | BK32: 0 | BL32: 0 | BM32: 0 | BN32: 0 | BO32: 0 | BP32: 0 | BQ32: 0 | BR32: 0 | BS32: 0 | BT32: 10500000 | BU32: 11025000 | BV32: 0 | BW32: 0 | BX32: 0 | BY32: 0 | BZ32: 0 | CA32: 0 | CB32: 0 | CC32: 0 | CD32: 0 | CE32: 11025000 | CF32: 11576250 | CG32: 0 | CH32: 0 | CI32: 0 | CJ32: 0 | CK32: 0 | CL32: 0 | CM32: 0 | CN32: 0 | CO32: 0 | CP32: 11576250 | CQ32: 43101250 | CR32: proyecto productyivo para personas LGTBIQ+, en articulación con la Secretaria de Desarrollo Economico y Medio Ambiente se espera adelantar el proyecto agencia para las oportunidades el cual aportara al alcance de la meta. | CS32: proyecto productyivo para personas LGTBIQ+
A33: MT030 | B33: 3 | C33: Transformación del Ser Humano | D33: Porcentaje de ejecución de las actividades del plan de acción de la política pública de los sectores LGTBIQ+ en el departamento de Sucre | E33: 0 | F33: Porcentaje | G33: 2023 | H33: Informe Política Publica de los sectores LGTBIQ+ | I33: 0,25 | J33: 3. Salud y bienestar | K33: Inclusión Social | L33: 7 | M33: Oportunidades para la diversidad | N33: Gobierno Territorial | O33: 45 | P33: Fortalecimiento del buen gobierno para el respeto y garantía de los derechos humanos | Q33: 4502 | R33: Servicio de promoción a la participación ciudadana | S33: 4502001 | T33: Espacios de participación promovidos | U33: 450200100 | V33: Corresponde al diseño e implementación de acciones y estrategias que promuevan el ejercicio de la participación ciudadana para el respeto y garantía de los derechos humanos | W33: Número de iniciativas | X33: No | Y33: Número | Z33: 27 | AA33: Acumulativo | AB33: Secretaria de Inclusión Social, Mujer y Equidad de Genero | AC33: 13 | AD33: 3 | AE33: 5 | AF33: 6 | AG33: APOYO LOGÍSTICO PARA LA REALIZACIÓN DE ACTIVIDADES CULTURALES Y ORGANIZATIVAS EN EL MES DE LA DIVERSIDAD ENFOCADAS EN LA POBLACION LGTBIQ+ DEL DEPARTAMENTO (BPIN: 2024002700101) (Meta del Proyecto: 1) (Ejecución 2024: 1) | AH33: ESPACIOS DE PARTICIPACIÓN PROMOVIDOS CON MIEMBROS DE LA COMUNIDAD LGTBIQ+ (Tipo Banco: Banco de Gestiones) (Meta de la gestión: ) APOYO PARA LA REALIZACIÓN DE ACTIVIDADES CULTURALES Y ORGANIZATIVAS ENFOCADAS EN LA POBLACIÓN LGBTIQ+ EN EL DEPARTAMENTO DE SUCRE (BPIN: 202400000006010) (Tipo de Banco: Banco Territorial) | AI33: Apoyo PARA LA REALIZACIÓN DE ACTIVIDADES CULTURALES Y ORGANIZATIVAS ENFOCADAS EN LA POBLACIÓN LGBTIQ+ DURANTE EL AÑO 2025 EN ELDEPARTAMENTO DE Sucre (Bpin: 202400000006010) (Tipo de Banco: Banco Territorial) (Meta total del indicador: 2.0) (Meta total de la vigencia: 2.0) (Ejecutado: 2.0) ESPACIOS DE PARTICIPACIÓN PROMOVIDOS CON MIEMBROS DE LA COMUNIDAD LGTBIQ+ (Tipo de banco: Banco de Gestiones) (Meta de la gestión: ) (Ejecutado: 20) | AJ33: Apoyo PARA LA REALIZACIÓN DE ACTIVIDADES CULTURALES Y ORGANIZATIVAS ENFOCADAS EN LA POBLACIÓN LGBTIQ+ DURANTE EL AÑO 2026 EN EL DEPARTAMENTO DE Sucre (BPIN: 202600000001100) (Meta del proyecto: 3) (Tipo de Banco: Banco Territorial) (Estado en Portafolio: En proceso de contratación) Apoyo logístico para la Creación y el Fortalecimiento de los Consejos Consultivos Municipales de (municipios priorizados) Población LGBTIQ+ y del Fortalecimiento del Consejo Consultivo Departamental Y el I ENCUENTRO Departamental de Consejeros lgbtiq+ ASISTENCIA TECNICA A CONSEJO CONSULTIVOS DE LOS PALMITOS, SAMPUES, SUCRE Y LA UNIÓN (Meta Programada: 1) (Tipo de Banco: Banco de Gestiones) | AK33: ASISTENCIA TECNICA A CONSEJO CONSULTIVOS DE LOS PALMITOS, SAMPUES, SUCRE Y LA UNIÓN (Meta programada: 1) (Ejecución: 1) (Tipo de banco: Banco de Gestiones) | AL33: Apoyo logístico para la Creación y el Fortalecimiento de los Consejos Consultivos Municipales de (municipios priorizados) Población LGBTIQ+ y del Fortalecimiento del Consejo Consultivo Departamental Y el I ENCUENTRO Departamental de Consejeros lgbtiq+ (Bpin: ) | AM33: 1 | AN33: 0.076923077 | AO33: Minimo | AP33: 22 | AQ33: 1 | AR33: Superior | AS33: 1 | AT33: 1 | AU33: Superior | AV33: 24 | AW33: 0.88888889 | AX33: Alto | AY33: 42000000 | AZ33: 0 | BA33: 0 | BB33: 0 | BC33: 0 | BD33: 0 | BE33: 0 | BF33: 0 | BG33: 0 | BH33: 0 | BI33: 42000000 | BJ33: 44100000 | BK33: 0 | BL33: 0 | BM33: 0 | BN33: 0 | BO33: 0 | BP33: 0 | BQ33: 0 | BR33: 0 | BS33: 0 | BT33: 44100000 | BU33: 46305000 | BV33: 0 | BW33: 0 | BX33: 0 | BY33: 0 | BZ33: 0 | CA33: 0 | CB33: 0 | CC33: 0 | CD33: 0 | CE33: 46305000 | CF33: 48620250 | CG33: 0 | CH33: 0 | CI33: 0 | CJ33: 0 | CK33: 0 | CL33: 0 | CM33: 0 | CN33: 0 | CO33: 0 | CP33: 48620250 | CQ33: 181025250 | CS33: Sesiones y espacios del consejo consultivo LGTBIQ+
A34: MT031 | B34: 4 | C34: Transformación del Ser Humano | D34: Porcentaje de ejecución de las actividades del plan de acción de la política pública de los sectores LGTBIQ+ en el departamento de Sucre | E34: 0 | F34: Porcentaje | G34: 2023 | H34: Informe Política Publica de los sectores LGTBIQ+ | I34: 0,25 | J34: 3. Salud y bienestar | K34: Inclusión Social | L34: 7 | M34: Oportunidades para la diversidad | N34: Inclusión Social y Reconciliación | O34: 41 | P34: Inclusión social y productiva para la población en situación de vulnerabilidad | Q34: 4103 | R34: Servicio de gestión de oferta social para la población vulnerable | S34: 4103052 | T34: Beneficiarios potenciales para quienes se gestiona la oferta social | U34: 410305200 | V34: Incluye el desarrollo de acciones encaminadas a generar dinámicas de atención conjunta, articulada y eficiente entre las instituciones del estado hacia la población vulnerable. | W34: Número de beneficiarios | X34: No | Y34: Número | Z34: 150 | AA34: Acumulativo | AB34: Secretaria de Inclusión Social, Mujer y Equidad de Genero | AC34: 150 | AD34: 0 | AE34: 0 | AF34: 0 | AG34: PROYECTO FORTALECIMIENTO A LA SALUD Y NUTRICIÓN A PERSONAS VIVIENDO CON VIH/SIDA PARA EL MEJORAMIENTO DE SUS CONDICIONES DE VIDA EN LOS MUNICIPIOS DE SINCELEJO, COROZAL, SAN MARCOS, TOLUVIEJO, TOLU, SAN ONOFRE, SAMPUÉS, MAJAGUAL, SINCÉ Y LOS PALMITOS EN E (BPIN: 2024002700053) (Meta del Proyecto: 150) (Ejecución 2024: 150) | AH34: APOYO LOGÍSTICO PARA LA REALIZACIÓN DE ACTIVIDADES CULTURALES Y ORGANIZATIVAS EN EL MES DE LA DIVERSIDAD ENFOCADAS EN LA POBLACION LGTBIQ+ DEL DEPARTAMENTO 2025 (BPIN: ) (Tipo de Banco: Banco Territorial) | AJ34: APOYO LOGÍSTICO PARA LA REALIZACIÓN DE ACTIVIDADES CULTURALES Y ORGANIZATIVAS EN EL MES DE LA DIVERSIDAD ENFOCADAS EN LA POBLACION LGTBIQ+ DEL DEPARTAMENTO 2026 | AL34: APOYO LOGÍSTICO PARA LA REALIZACIÓN DE ACTIVIDADES CULTURALES Y ORGANIZATIVAS EN EL MES DE LA DIVERSIDAD ENFOCADAS EN LA POBLACION LGTBIQ+ DEL DEPARTAMENTO 2027 (Bpin: ) | AM34: 150 | AN34: 1 | AO34: Superior | AV34: 150 | AW34: 1 | AX34: Superior | AY34: 200000000 | AZ34: 0 | BA34: 0 | BB34: 0 | BC34: 0 | BD34: 0 | BE34: 0 | BF34: 0 | BG34: 0 | BH34: 0 | BI34: 200000000 | BJ34: 210000000 | BK34: 0 | BL34: 0 | BM34: 0 | BN34: 0 | BO34: 0 | BP34: 0 | BQ34: 0 | BR34: 0 | BS34: 0 | BT34: 210000000 | BU34: 220500000 | BV34: 0 | BW34: 0 | BX34: 0 | BY34: 0 | BZ34: 0 | CA34: 0 | CB34: 0 | CC34: 0 | CD34: 0 | CE34: 220500000 | CF34: 231525000 | CG34: 0 | CH34: 0 | CI34: 0 | CJ34: 0 | CK34: 0 | CL34: 0 | CM34: 0 | CN34: 0 | CO34: 0 | CP34: 231525000 | CQ34: 862025000 | CR34: 03/10/2024: Se encuentra una variacion entre la meta de cuatrenio que esta por 150 y la meta por vigencia que esta en 520, definiendo que el valor de la meta es de 150 y que sera de mantenimiento, teniedo en cuenta que se viene adelantando cada año, proyecto que se encuentra en ejecución hasta 24 de diciembre. | CS34: Proyecto mes de la diversidad
A35: MT032 | B35: 1 | C35: Transformación del Ser Humano | D35: Numero de documentos de politica publica para la atencion integral de la poblacion habitante de calle formuladas en el departamento de Sucre | E35: 0 | F35: Número | G35: 2023 | H35: Gobernación de Sucre | I35: 1 | J35: 3. Salud y bienestar | K35: Inclusión Social | L35: 8 | M35: Oportunidad para la inclusión | N35: Inclusión Social y Reconciliación | O35: 41 | P35: Desarrollo integral de la primera infancia a la juventud, y fortalecimiento de las capacidades de las familias de niñas, niños y adolescentes | Q35: 4102 | R35: Documentos de lineamientos técnicos | S35: 4102035 | T35: Documentos de lineamientos técnicos realizados | U35: 410203500 | V35: Documentos cuyo objetivo es describir y explicar instrumentos, estándares, requisitos y condiciones necesarias para llevar a cabo un proceso o actividad | W35: Número de documentos | X35: Sí | Y35: Numero | Z35: 1 | AA35: Acumulativo | AB35: Secretaria de Inclusión Social, Mujer y Equidad de Genero | AC35: 0 | AD35: 0 | AE35: 0 | AF35: 1 | AV35: 0 | AW35: 0 | AX35: Minimo | AY35: 30000000 | AZ35: 0 | BA35: 0 | BB35: 0 | BC35: 0 | BD35: 0 | BE35: 0 | BF35: 0 | BG35: 0 | BH35: 0 | BI35: 30000000 | BJ35: 31500000 | BK35: 0 | BL35: 0 | BM35: 0 | BN35: 0 | BO35: 0 | BP35: 0 | BQ35: 0 | BR35: 0 | BS35: 0 | BT35: 31500000 | BU35: 33075000 | BV35: 0 | BW35: 0 | BX35: 0 | BY35: 0 | BZ35: 0 | CA35: 0 | CB35: 0 | CC35: 0 | CD35: 0 | CE35: 33075000 | CF35: 34728750 | CG35: 0 | CH35: 0 | CI35: 0 | CJ35: 0 | CK35: 0 | CL35: 0 | CM35: 0 | CN35: 0 | CO35: 0 | CP35: 34728750 | CQ35: 129303750 | CS35: Formulaciòn de la politica publica para la atenciòn integral de la poblaciòn habitante de calle. Caracterizacion de la poblaciòn habitante de calle
A36: MT033 | B36: 2 | C36: Transformación del Ser Humano | D36: Numero de documentos de politica publica para la atencion integral de la poblacion habitante de calle formuladas en el departamento de Sucre | E36: 0 | F36: Número | G36: 2023 | H36: Gobernación de Sucre | I36: 1 | J36: 3. Salud y bienestar | K36: Inclusión Social | L36: 8 | M36: Oportunidad para la inclusión | N36: Inclusión Social y Reconciliación | O36: 41 | P36: Atención integral de población en situación permanente de desprotección social y/o familiar | Q36: 4104 | R36: Centros de atención de habitantes de la calle adecuados | S36: 4104029 | T36: Centros de atención de habitantes de la calle adecuados | U36: 410402900 | V36: Corresponde a la adecuación de infraestructura destinada al ofrecimiento de servicios de atención integral para población habitante de la calle. | W36: Número de centros | X36: No | Y36: Numero | Z36: 1 | AA36: Acumulativo | AB36: Secretaria de Inclusión Social, Mujer y Equidad de Genero | AC36: 0 | AD36: 0 | AE36: 0 | AF36: 1 | AV36: 0 | AW36: 0 | AX36: Minimo | AY36: 0 | AZ36: 0 | BA36: 0 | BB36: 0 | BC36: 0 | BD36: 0 | BE36: 0 | BF36: 0 | BG36: 0 | BH36: 0 | BI36: 0 | BJ36: 0 | BK36: 0 | BL36: 0 | BM36: 0 | BN36: 0 | BO36: 0 | BP36: 0 | BQ36: 0 | BR36: 0 | BS36: 3000000000 | BT36: 3000000000 | BU36: 0 | BV36: 0 | BW36: 0 | BX36: 0 | BY36: 0 | BZ36: 0 | CA36: 0 | CB36: 0 | CC36: 0 | CD36: 0 | CE36: 0 | CF36: 0 | CG36: 0 | CH36: 0 | CI36: 0 | CJ36: 0 | CK36: 0 | CL36: 0 | CM36: 0 | CN36: 0 | CO36: 0 | CP36: 0 | CQ36: 3000000000 | CS36: Centro para los habitantes de calle
A37: MT034 | B37: 3 | C37: Transformación del Ser Humano | D37: Numero de documentos de politica publica para la atencion integral de la poblacion habitante de calle formuladas en el departamento de Sucre | E37: 0 | F37: Número | G37: 2023 | H37: Gobernación de Sucre | I37: 1 | J37: 3. Salud y bienestar | K37: Inclusión Social | L37: 8 | M37: Oportunidad para la inclusión | N37: Inclusión Social y Reconciliación | O37: 41 | P37: Atención integral de población en situación permanente de desprotección social y/o familiar | Q37: 4104 | R37: Servicio de articulación de oferta social para la población habitante de calle | S37: 4104026 | T37: Personas atendidas con oferta institucional | U37: 410402600 | V37: Incluye el desarrollo de acciones encaminadas a generar dinámicas de atención conjunta, articulada y eficiente entre instituciones de carácter público y/o privado hacia la población habitante de la calle. | W37: Número de personas | X37: No | Y37: Numero | Z37: 20 | AA37: Acumulativo | AB37: Secretaria de Inclusión Social, Mujer y Equidad de Genero | AC37: 0 | AD37: 0 | AE37: 0 | AF37: 20 | AI37: Jornada de Atención integral, en el marco de la conmemoración del día de habitante de calle en la plaza caribe de la Gobernación de Sucre de 150 habitantes de calle (Tipo de banco: Banco de Gestiones) (Meta de la gestión: ) (Ejecutado: 200) | AP37: 200 | AQ37: 1 | AR37: Superior | AV37: 200 | AW37: 1 | AX37: Superior | AY37: 120000000 | AZ37: 0 | BA37: 0 | BB37: 0 | BC37: 0 | BD37: 0 | BE37: 0 | BF37: 0 | BG37: 0 | BH37: 0 | BI37: 120000000 | BJ37: 126000000 | BK37: 0 | BL37: 0 | BM37: 0 | BN37: 0 | BO37: 0 | BP37: 0 | BQ37: 0 | BR37: 0 | BS37: 0 | BT37: 126000000 | BU37: 132300000 | BV37: 0 | BW37: 0 | BX37: 0 | BY37: 0 | BZ37: 0 | CA37: 0 | CB37: 0 | CC37: 0 | CD37: 0 | CE37: 132300000 | CF37: 138915000 | CG37: 0 | CH37: 0 | CI37: 0 | CJ37: 0 | CK37: 0 | CL37: 0 | CM37: 0 | CN37: 0 | CO37: 0 | CP37: 138915000 | CQ37: 5.17215e+08 | CR37: Se espera hacer una brigada dirigida a habitantes de calle, por gestión | CS37: Proyecto para atenciòn de la poblaciòn habitante de calle
A38: MT035 | B38: 1 | C38: Transformación del Ser Humano | D38: Cobertura Neta en educación - Total, Cobertura bruta en educación - Total | E38: 92% - 105,42% | F38: Porcentaje (Multiplicado por 100) | G38: 2022 | H38: MEN - OAPF La cobertura se estimó con proyección censo DANE 2018 | I38: 92%, 105,5% | J38: 4. Educación de calidad | K38: Educación | L38: 9 | M38: Oportunidades Educativas en Educación Inicial, Preescolar, Básica y Media | N38: Educación | O38: 22 | P38: Calidad, cobertura y fortalecimiento de la educación inicial, prescolar, básica y media | Q38: 2201 | R38: Documentos de planeación | S38: 2201001 | T38: Documentos de planeación para la educación inicial, preescolar, básica y media emitidos. | U38: 220100100 | V38: Incluyen los servicio de asesoría y orientación técnica prestados a las Secretarías de Educación o por estas en los temas relacionados con la política educativa y aquellos definidos para la educación inicial, preescolar, básica y media. | W38: Número de documentos | X38: Sí | Y38: Número | Z38: 1 | AA38: Acumulativo | AB38: Secretaría de Educación | AC38: 1 | AD38: 0 | AE38: 0 | AF38: 0 | AG38: Elaboración plan sectorial de educación, está aprobado en comité ejecutivo de la Secretaría de Educación en 2024 (BPIN: Por Gestión) (Meta del Proyecto: 1) (Ejecución 2024: 1) | AM38: 1 | AN38: 1 | AO38: Superior | AV38: 1 | AW38: 1 | AX38: Superior | AY38: 0 | AZ38: 0 | BA38: 0 | BB38: 0 | BC38: 0 | BD38: 0 | BE38: 0 | BF38: 0 | BG38: 0 | BH38: 0 | BI38: 0 | BJ38: 0 | BK38: 0 | BL38: 0 | BM38: 0 | BN38: 0 | BO38: 0 | BP38: 0 | BQ38: 0 | BR38: 0 | BS38: 0 | BT38: 0 | BU38: 0 | BV38: 0 | BW38: 0 | BX38: 0 | BY38: 0 | BZ38: 0 | CA38: 0 | CB38: 0 | CC38: 0 | CD38: 0 | CE38: 0 | CF38: 0 | CG38: 0 | CH38: 0 | CI38: 0 | CJ38: 0 | CK38: 0 | CL38: 0 | CM38: 0 | CN38: 0 | CO38: 0 | CP38: 0 | CQ38: 0 | CR38: Se tiene el documento Plan Sectorial de Educación 2024 - 2027, el cual sera presentado para su revisión y aprobación, se espera tenerlo aprobado para el mes de noviembre | CS38: Incluyen los servicio de asesoría y orientación técnica prestados a las Secretarías de Educación o por estas en los temas relacionados con la política educativa y aquellos definidos para la educación inicial, preescolar, básica y media.
A39: MT036 | B39: 2 | C39: Transformación del Ser Humano | D39: Cobertura Neta en educación - Total, Cobertura bruta en educación - Total | E39: 92% - 105,42% | F39: Porcentaje (Multiplicado por 100) | G39: 2022 | H39: MEN - OAPF La cobertura se estimó con proyección censo DANE 2018 | I39: 92%, 105,5% | J39: 4. Educación de calidad | K39: Educación | L39: 9 | M39: Oportunidades Educativas en Educación Inicial, Preescolar, Básica y Media | N39: Educación | O39: 22 | P39: Calidad, cobertura y fortalecimiento de la educación inicial, prescolar, básica y media | Q39: 2201 | R39: Servicio de divulgación para la educación inicial, preescolar, básica y media | S39: 2201002 | T39: Procesos de socialización de lineamientos, política y normativa para la educación inicial, preescolar, básica y media realizados | U39: 220100200 | V39: Incluye la realización de todo tipo de campañas informativas que busquen socializar lineamientos de la política educativa en todos los temas que esta contempla. | W39: Número de procesos de socialización | X39: No | Y39: Número | Z39: 80 | AA39: Acumulativo | AB39: Secretaría de Educación | AC39: 10 | AD39: 20 | AE39: 20 | AF39: 30 | AG39: Campañas de socialización normativa realizadas por la Secretaría de Educación (BPIN: Por Gestión) (Meta del Proyecto: 10) (Ejecución 2024: 10) APOYO A LOS FOROS EDUCATIVOS "SUCRE, TIERRA DE OPORTUNIDADES, EDUCACIÓN Y PAZ EN SU SEGUNDA ETAPA EN EL DEPARTAMENTO DE SUCRE. (BPIN: 2024002700127) (Meta del Proyecto: 2) (Ejecución 2024: 2) APOYO AL FORO EDUCATIVO SUCRE TIERRA DE OPORTUNIDADES "EDUCACIÓN Y PAZ EN SU PRIMERA ETAPA EN EL DEPARTAMENTO DE SUCRE" (BPIN: 2024002700120) (Meta del Proyecto: 1) (Ejecución 2024: 1) | AH39: Campañas de socialización normativa realizadas por la Secretaría de Educación (Tipo Banco: Banco de Gestiones) (Meta de la gestión: 20) | AI39: Campañas de socialización normativa realizadas por la Secretaría de Educación (Tipo de banco: Banco de Gestiones) (Meta de la gestión: 20) (Ejecutado: 20) | AJ39: Gestión - Campañas de socialización normativa realizadas por la Secretaría de Educación (BPIN: Por Gestión) | AL39: Gestión - Campañas de socialización normativa realizadas por la Secretaría de Educación (Bpin: Por Gestión) | AM39: 13 | AN39: 1 | AO39: Superior | AP39: 20 | AQ39: 1 | AR39: Superior | AT39: 0 | AU39: Minimo | AV39: 33 | AW39: 0.4125 | AX39: Medio | AY39: 0 | AZ39: 0 | BA39: 0 | BB39: 0 | BC39: 0 | BD39: 0 | BE39: 0 | BF39: 0 | BG39: 0 | BH39: 0 | BI39: 0 | BJ39: 0 | BK39: 0 | BL39: 0 | BM39: 0 | BN39: 0 | BO39: 0 | BP39: 0 | BQ39: 0 | BR39: 0 | BS39: 0 | BT39: 0 | BU39: 0 | BV39: 0 | BW39: 0 | BX39: 0 | BY39: 0 | BZ39: 0 | CA39: 0 | CB39: 0 | CC39: 0 | CD39: 0 | CE39: 0 | CF39: 0 | CG39: 0 | CH39: 0 | CI39: 0 | CJ39: 0 | CK39: 0 | CL39: 0 | CM39: 0 | CN39: 0 | CO39: 0 | CP39: 0 | CQ39: 0 | CR39: Se realizó la socialización en 10 municipios del Departamento (Since, Galeras, Majagual, Guaranda, Toluviejo, Morroa, Ovejas, Betulia, Corozal y Sampues), en orientación de politica de educación inicial y los referentes técnicos (Decreto 1411 de 2022). | CS39: Gestionar los mecanismos institucionales necesarios a través de los distintos actores del sistema educativo para implementar el Plan Decenal de Educación con criterios de Eficiencia, Eficacia, Innovación y Sostenibilidad. Campañas de socialización normat
A40: MT037 | B40: 3 | C40: Transformación del Ser Humano | D40: Cobertura Neta en educación - Total, Cobertura bruta en educación - Total | E40: 92% - 105,42% | F40: Porcentaje (Multiplicado por 100) | G40: 2022 | H40: MEN - OAPF La cobertura se estimó con proyección censo DANE 2018 | I40: 92%, 105,5% | J40: 4. Educación de calidad | K40: Educación | L40: 9 | M40: Oportunidades Educativas en Educación Inicial, Preescolar, Básica y Media | N40: Educación | O40: 22 | P40: Calidad, cobertura y fortalecimiento de la educación inicial, prescolar, básica y media | Q40: 2201 | R40: Documentos normativos | S40: 2201004 | T40: Documentos normativos para la educación inicial, preescolar, básica y media expedidos | U40: 220100400 | V40: Incluye los documentos para la reglamentación de la política educativa y demás lineamientos técnicos del programa. | W40: Número de documentos | X40: No | Y40: Número | Z40: 1 | AA40: No acumulativo | AB40: Secretaría de Educación | AC40: 1 | AD40: 1 | AE40: 1 | AF40: 1 | AG40: Expedición del calendario escolar 2025 por parte de la Secretaría de Educación (BPIN: Por Gestión) (Meta del Proyecto: 1) (Ejecución 2024: 1) | AH40: Calendario Escolar Académico- Por norma se expide en Octubre (Tipo Banco: Banco de Gestiones) (Meta de la gestión: 1) | AI40: Calendario Escolar Académico- Por norma se expide en Octubre (Tipo de banco: Banco de Gestiones) (Meta de la gestión: 1) (Ejecutado: 1) | AM40: 1 | AN40: 1 | AO40: Superior | AP40: 1 | AQ40: 1 | AR40: Superior | AT40: 0 | AU40: Minimo | AV40: 2 | AW40: 1 | AX40: Superior | AY40: 0 | AZ40: 0 | BA40: 0 | BB40: 0 | BC40: 0 | BD40: 0 | BE40: 0 | BF40: 0 | BG40: 0 | BH40: 0 | BI40: 0 | BJ40: 0 | BK40: 0 | BL40: 0 | BM40: 0 | BN40: 0 | BO40: 0 | BP40: 0 | BQ40: 0 | BR40: 0 | BS40: 0 | BT40: 0 | BU40: 0 | BV40: 0 | BW40: 0 | BX40: 0 | BY40: 0 | BZ40: 0 | CA40: 0 | CB40: 0 | CC40: 0 | CD40: 0 | CE40: 0 | CF40: 0 | CG40: 0 | CH40: 0 | CI40: 0 | CJ40: 0 | CK40: 0 | CL40: 0 | CM40: 0 | CN40: 0 | CO40: 0 | CP40: 0 | CQ40: 0 | CR40: Se realizo el cambio en la meta a mantenimiento, teniendo en cuenta que por esta se pretende realizar la elaboración del calendario academico el cual es anual, y se espera tenerlo para el mes de noviembre. | CS40: Gestionar los mecanismos institucionales necesarios a través de los distintos actores del sistema educativo para implementar el Plan Decenal de Educación con criterios de Eficiencia, Eficacia, Innovación y Sostenibilidad. Documento normativo elaborado po
A41: MT038 | B41: 4 | C41: Transformación del Ser Humano | D41: Cobertura Neta en educación - Total, Cobertura bruta en educación - Total | E41: 92% - 105,42% | F41: Porcentaje (Multiplicado por 100) | G41: 2022 | H41: MEN - OAPF La cobertura se estimó con proyección censo DANE 2018 | I41: 92%, 105,5% | J41: 4. Educación de calidad | K41: Educación | L41: 9 | M41: Oportunidades Educativas en Educación Inicial, Preescolar, Básica y Media | N41: Educación | O41: 22 | P41: Calidad, cobertura y fortalecimiento de la educación inicial, prescolar, básica y media | Q41: 2201 | R41: Documentos de lineamientos técnicos | S41: 2201005 | T41: Documentos de lineamientos técnicos en educación inicial, preescolar, básica y media expedidos | U41: 220100500 | V41: Documentos cuyo objetivo es describir y explicar instrumentos, estándares, requisitos y condiciones necesarias para llevar a cabo un proceso o actividad | W41: Número de documentos | X41: Sí | Y41: Número | Z41: 1 | AA41: Acumulativo | AB41: Secretaría de Educación | AC41: 0 | AD41: 0 | AE41: 1 | AF41: 0 | AI41: Documentos de lineamientos técnicos en educación inicial, preescolar, básica y media expedidos (Tipo de banco: Banco de Gestiones) (Meta de la gestión: ) (Ejecutado: 1) | AJ41: Gestión - Documento técnico elaborado por la Secretaría de Educación | AP41: 1 | AQ41: 1 | AR41: Superior | AT41: 1 | AU41: Superior | AV41: 1 | AW41: 1 | AX41: Superior | AY41: 0 | AZ41: 0 | BA41: 0 | BB41: 0 | BC41: 0 | BD41: 0 | BE41: 0 | BF41: 0 | BG41: 0 | BH41: 0 | BI41: 0 | BJ41: 0 | BK41: 0 | BL41: 0 | BM41: 0 | BN41: 0 | BO41: 0 | BP41: 0 | BQ41: 0 | BR41: 0 | BS41: 0 | BT41: 0 | BU41: 0 | BV41: 0 | BW41: 0 | BX41: 0 | BY41: 0 | BZ41: 0 | CA41: 0 | CB41: 0 | CC41: 0 | CD41: 0 | CE41: 0 | CF41: 0 | CG41: 0 | CH41: 0 | CI41: 0 | CJ41: 0 | CK41: 0 | CL41: 0 | CM41: 0 | CN41: 0 | CO41: 0 | CP41: 0 | CQ41: 0 | CS41: Gestionar los mecanismos institucionales necesarios a través de los distintos actores del sistema educativo para implementar el Plan Decenal de Educación con criterios de Eficiencia, Eficacia, Innovación y Sostenibilidad. Documento técnico elaborado por
A42: MT039 | B42: 5 | C42: Transformación del Ser Humano | D42: Cobertura Neta en educación - Total, Cobertura bruta en educación - Total | E42: 92% - 105,42% | F42: Porcentaje (Multiplicado por 100) | G42: 2022 | H42: MEN - OAPF La cobertura se estimó con proyección censo DANE 2018 | I42: 92%, 105,5% | J42: 4. Educación de calidad | K42: Educación | L42: 9 | M42: Oportunidades Educativas en Educación Inicial, Preescolar, Básica y Media | N42: Educación | O42: 22 | P42: Calidad, cobertura y fortalecimiento de la educación inicial, prescolar, básica y media | Q42: 2201 | R42: Servicio de asistencia técnica en educación inicial, preescolar, básica y media | S42: 2201006 | T42: Entidades y organizaciones asistidas técnicamente | U42: 220100600 | V42: Incluyen los servicio de asesoría y orientación técnica prestados a las Secretarías de Educación o por estas en los temas relacionados con la política educativa y aquellos definidos para la prestación del servicio educativo. Así mismo, incorpora acciones de acompañamiento para la implementación de planes de mejoramiento en los establecimientos educativos oficiales de preescolar, básica y medial. | W42: Número de entidades y organizaciones | X42: No | Y42: Número | Z42: 306 | AA42: No acumulativo | AB42: Secretaría de Educación | AC42: 306 | AD42: 306 | AE42: 306 | AF42: 306 | AG42: Servicio de asistencia técnica en educación inicial Decreto 1411 y Ampliación del grado jardín. (BPIN: Por Gestión) (Meta del Proyecto: 30) (Ejecución 2024: 109) Asistencia técnica proyecto educativo institucional - PEI (BPIN: Por Gestión) (Meta del Proyecto: 80) (Ejecución 2024: 119) APOYO AL PROGRAMA DE FONDOS EDUCATIVOS (FOSE) PARA EL SEGUIMIENTO, CONTROL Y CONSOLIDACION FINANCIERA DE RECURSOS DE GRATUIDAD EDUCATIVA VIGENCIA 2024, PARA LOS ESTABLECIMIENTOS EDUCATIVOS DEL DEPARTAMENTO DE SUCRE (BPIN: 2024002700013) (Meta del Proyecto: 186) (Ejecución 2024: 108) | AH42: Acompañamiento para la caracterización de la población perteneciente a grupos étnicos en los establecimientos educativos para su registro en el Sistema integrado de matrícula (Tipo Banco: Banco de Gestiones) (Meta de la gestión: ) Asistencia tecnica FOSE (Tipo Banco: Banco de Gestiones) (Meta de la gestión: ) Proyecto de apoyo en recurso humano especializado (Contadores) al Programa de Fondos Educativos (Fose) para el Seguimiento, Control Y Consolidacion Financiera de Recursos de Gratuidad Educativa para los Establecimientos Educativos del departamento de Sucre (BPIN: ) (Tipo de Banco: Banco Territorial) | AI42: Servicio de asistencia técnica en educación inicial Decreto 1411 y Ampliación del grado jardín y Asistencia técnica proyecto educativo institucional - PEI (Tipo de banco: Banco de Gestiones) (Meta de la gestión: ) (Ejecutado: 129) Acompañamiento para la caracterización de la población perteneciente a grupos étnicos en los establecimientos educativos para su registro en el Sistema integrado de matrícula (Tipo de banco: Banco de Gestiones) (Meta de la gestión: ) (Ejecutado: 7) Asistencia tecnica FOSE (Tipo de banco: Banco de Gestiones) (Meta de la gestión: ) (Ejecutado: 235) | AJ42: Proyecto de apoyo en recurso humano especializado (Contadores) al Programa de Fondos Educativos (Fose) para el Seguimiento, Control Y Consolidacion Financiera de Recursos de Gratuidad Educativa para los Establecimientos Educativos del departamento de Sucr Gestión - Acompañamiento para la caracterización de la población perteneciente a grupos étnicos en los establecimientos educativos para su registro en el Sistema integrado de matrícula Gestión - Servicio de asistencia técnica en educación inicial Decreto 1411 y Ampliación del grado jardín. Gestión - Asistencia técnica proyecto educativo institucional - PEI Apoyo a la Realización del Foro Educativo y los Diferentes Encuentros Pedagógicos e Interactivos Vigencia 2026, de la Secretaria de Educación Departamental de Sucre (BPIN: 202500000038748) (Meta del proyecto: 1200) (Tipo de Banco: Banco Territorial) Apoyo al Programa de Fondos Educativos Fose para el Seguimiento, Control y Consolidación Financiera de Recursos de Gratuidad Educativa Vigencia 2026, para los Establecimientos Educativos del Departamento de Sucre (BPIN: 202500000039332) (Meta del proyecto: 259) (Tipo de Banco: Banco Territorial) | AL42: Proyecto de apoyo en recurso humano especializado (Contadores) al Programa de Fondos Educativos (Fose) para el Seguimiento, Control Y Consolidacion Financiera de Recursos de Gratuidad Educativa para los Establecimientos Educativos del departamento de Sucr (Bpin: ) Gestión - Asistencia técnica proyecto educativo institucional - PEI (Bpin: ) Gestión - Servicio de asistencia técnica en educación inicial Decreto 1411 y Ampliación del grado jardín. (Bpin: ) Gestión - Acompañamiento para la caracterización de la población perteneciente a grupos étnicos en los establecimientos educativos para su registro en el Sistema integrado de matrícula (Bpin: ) | AM42: 336 | AN42: 1 | AO42: Superior | AP42: 371 | AQ42: 1 | AR42: Superior | AT42: 0 | AU42: Minimo | AV42: 707 | AW42: 1 | AX42: Superior | AY42: 0 | AZ42: 0 | BA42: 174000000 | BB42: 0 | BC42: 0 | BD42: 0 | BE42: 0 | BF42: 0 | BG42: 0 | BH42: 0 | BI42: 174000000 | BJ42: 0 | BK42: 0 | BL42: 182700000 | BM42: 0 | BN42: 0 | BO42: 0 | BP42: 0 | BQ42: 0 | BR42: 0 | BS42: 0 | BT42: 182700000 | BU42: 0 | BV42: 0 | BW42: 191835000 | BX42: 0 | BY42: 0 | BZ42: 0 | CA42: 0 | CB42: 0 | CC42: 0 | CD42: 0 | CE42: 191835000 | CF42: 0 | CG42: 0 | CH42: 201426750 | CI42: 0 | CJ42: 0 | CK42: 0 | CL42: 0 | CM42: 0 | CN42: 0 | CO42: 0 | CP42: 201426750 | CQ42: 7.4996175e+08 | CR42: Se adelanto asistencia técnica a 20 IETAS en ciencias a gropecuarias y PEI, de igual forma se realizo asistenvcia técnica a 83 IE en temas de FOSE. | CS42: Proyecto de apoyo en recurso humano especializado (Contadores) al Programa de Fondos Educativos (Fose) para el Seguimiento, Control Y Consolidacion Financiera de Recursos de Gratuidad Educativa para los Establecimientos Educativos del departamento de Sucr
A43: MT040 | B43: 6 | C43: Transformación del Ser Humano | D43: Cobertura Neta en educación - Total, Cobertura bruta en educación - Total | E43: 92% - 105,42% | F43: Porcentaje (Multiplicado por 100) | G43: 2022 | H43: MEN - OAPF La cobertura se estimó con proyección censo DANE 2018 | I43: 92%, 105,5% | J43: 4. Educación de calidad | K43: Educación | L43: 9 | M43: Oportunidades Educativas en Educación Inicial, Preescolar, Básica y Media | N43: Educación | O43: 22 | P43: Calidad, cobertura y fortalecimiento de la educación inicial, prescolar, básica y media | Q43: 2201 | R43: Servicio de evaluación de la permanencia en la educación inicial, preescolar, básica y media | S43: 2201012 | T43: Documentos sobre evaluación de permanencia en la educación elaborados | U43: 220101200 | V43: Incluye la realización de estudios o investigaciones que permitan reportar información sobre el abandono escolar. | W43: Número de documentos | X43: No | Y43: Número | Z43: 1 | AA43: Acumulativo | AB43: Secretaría de Educación | AC43: 0 | AD43: 0 | AE43: 0 | AF43: 1 | AL43: Por Gestión - Documento sobre evaluación de permanencia elaborado por la Secretaría de Educación (Bpin: Por Gestión) | AV43: 0 | AW43: 0 | AX43: Minimo | AY43: 0 | AZ43: 0 | BA43: 0 | BB43: 0 | BC43: 0 | BD43: 0 | BE43: 0 | BF43: 0 | BG43: 0 | BH43: 0 | BI43: 0 | BJ43: 0 | BK43: 0 | BL43: 0 | BM43: 0 | BN43: 0 | BO43: 0 | BP43: 0 | BQ43: 0 | BR43: 0 | BS43: 0 | BT43: 0 | BU43: 0 | BV43: 0 | BW43: 0 | BX43: 0 | BY43: 0 | BZ43: 0 | CA43: 0 | CB43: 0 | CC43: 0 | CD43: 0 | CE43: 0 | CF43: 0 | CG43: 0 | CH43: 0 | CI43: 0 | CJ43: 0 | CK43: 0 | CL43: 0 | CM43: 0 | CN43: 0 | CO43: 0 | CP43: 0 | CQ43: 0 | CS43: Documento sobre evaluación de permanencia elaborado por la Secretaría de Educación
A44: MT041 | B44: 7 | C44: Transformación del Ser Humano | D44: Cobertura Neta en educación - Total, Cobertura bruta en educación - Total | E44: 92% - 105,42% | F44: Porcentaje (Multiplicado por 100) | G44: 2022 | H44: MEN - OAPF La cobertura se estimó con proyección censo DANE 2018 | I44: 92%, 105,5% | J44: 4. Educación de calidad | K44: Educación | L44: 9 | M44: Oportunidades Educativas en Educación Inicial, Preescolar, Básica y Media | N44: Educación | O44: 22 | P44: Calidad, cobertura y fortalecimiento de la educación inicial, prescolar, básica y media | Q44: 2201 | R44: Servicio de información para la gestión de la educación inicial y preescolar en condiciones de calidad | S44: 2201018 | T44: Sistemas de reporte de información operando | U44: 220101800 | V44: Incluye el desarrollo y operación de modelos, sistemas de información y herramientas de calidad de la educación que permitan: diagnosticar claramente la situación, comprender los problemas y sus causas y tener en cuenta las potencialidades para la planificación y ejecución de estrategias para el logro de la calidad | W44: Número de sistemasde reporte de información | X44: No | Y44: Número | Z44: 1 | AA44: No acumulativo | AB44: Secretaría de Educación | AC44: 1 | AD44: 1 | AE44: 1 | AF44: 1 | AG44: Sistema integrado de matricula - SIMAT (BPIN: Por Gestión) (Meta del Proyecto: 1) (Ejecución 2024: 1) | AH44: Sistema integrado de matricula - SIMAT (Tipo Banco: Banco de Gestiones) (Meta de la gestión: 1) IMPLEMENTACION DE UNA ESTRATEGIA PARA EL MEJORAMIENTO DE LA PRESTACIÓN DE LOS SERVICIOS Y LA CALIDAD EDUCATIVA EN LOS ESTABLECIMIENTOS EDUCATIVOS PRIORIZADOS DE LOS MUNICIPIOS NO CERTIFICADOS DEL DEPARTAMENTO DE SUCRE (BPIN: 202500000038818) (Tipo de Banco: Banco Territorial) | AI44: Implementación de una estrategia para el mejoramiento de la prestación de los servicios y la calidad educativa en los establecimientos educativos priorizados de los municipios no certificados del departamento de Sucre (Bpin: 202500000038818) (Tipo de Banco: Banco Territorial) (Meta total del indicador: 1.0) (Meta total de la vigencia: 1.0) (Ejecutado: 1.0) Sistema integrado de matricula - SIMAT (Tipo de banco: Banco de Gestiones) (Meta de la gestión: 1) (Ejecutado: 1) | AJ44: Fortalecimiento del proceso de Asistencia Técnica, Inspección, Vigilancia y Control (AIVC) en los Establecimientos Educativos de los municipios no certificados del departamento de Sucre (BPIN: 202600000006916) (Meta del proyecto: 1) (Tipo de Banco: Banco Territorial) (Estado en Portafolio: En Ejecución) Gestión - sistema integrado de matricula - SIMAT Sistema integrado de matricula - SIMAT (Meta Programada: 1) (Tipo de Banco: Banco de Gestiones) | AK44: Sistema integrado de matricula - SIMAT (Meta programada: 1) (Ejecución: 1) (Tipo de banco: Banco de Gestiones) | AL44: Gestión - sistema integrado de matricula - SIMAT (Bpin: ) | AM44: 1 | AN44: 1 | AO44: Superior | AP44: 2 | AQ44: 1 | AR44: Superior | AS44: 1 | AT44: 1 | AU44: Superior | AV44: 4 | AW44: 1 | AX44: Superior | AY44: 0 | AZ44: 0 | BA44: 0 | BB44: 0 | BC44: 0 | BD44: 0 | BE44: 0 | BF44: 0 | BG44: 0 | BH44: 0 | BI44: 0 | BJ44: 0 | BK44: 0 | BL44: 0 | BM44: 0 | BN44: 0 | BO44: 0 | BP44: 0 | BQ44: 0 | BR44: 0 | BS44: 0 | BT44: 0 | BU44: 0 | BV44: 0 | BW44: 0 | BX44: 0 | BY44: 0 | BZ44: 0 | CA44: 0 | CB44: 0 | CC44: 0 | CD44: 0 | CE44: 0 | CF44: 0 | CG44: 0 | CH44: 0 | CI44: 0 | CJ44: 0 | CK44: 0 | CL44: 0 | CM44: 0 | CN44: 0 | CO44: 0 | CP44: 0 | CQ44: 0 | CR44: Se ralizo el cambio en el nombre del sistema ya que el SIMAT, es un sistema que se maneja 100% en ejecución
A45: MT042 | B45: 8 | C45: Transformación del Ser Humano | D45: Cobertura Neta en educación - Total, Cobertura bruta en educación - Total | E45: 92% - 105,42% | F45: Porcentaje (Multiplicado por 100) | G45: 2022 | H45: MEN - OAPF La cobertura se estimó con proyección censo DANE 2018 | I45: 92%, 105,5% | J45: 4. Educación de calidad | K45: Educación | L45: 9 | M45: Oportunidades Educativas en Educación Inicial, Preescolar, Básica y Media | N45: Educación | O45: 22 | P45: Calidad, cobertura y fortalecimiento de la educación inicial, prescolar, básica y media | Q45: 2201 | R45: Servicio educativos de promoción del bilingüismo | S45: 2201034 | T45: Estudiantes beneficiados con estrategias de promoción del bilingüismo. | U45: 220103400 | V45: Procesos de formación para el desarrollo de competencias en un segundo idioma | W45: Número de estudiantes | X45: No | Y45: Número | Z45: 7850 | AA45: Acumulativo | AB45: Secretaría de Educación | AC45: 700 | AD45: 1000 | AE45: 3000 | AF45: 3150 | AG45: Se realizó tour linguistico y cultural en las 5 subregiones, beneficiando a un gran numero de estudiantes en temas de bilinguismo, se tiene previsto la realización del proyecto foro de bilingüismo en el mes de noviembre. (BPIN: Por Gestión) (Meta del Proyecto: 300) (Ejecución 2024: 682) Programa Sucre Bilingüe (BPIN: Por Gestión) (Meta del Proyecto: 8800) (Ejecución 2024: 5351) Alianzas Italia - Colombia (BPIN: Por Gestión) (Meta del Proyecto: 56) (Ejecución 2024: 56) JEC_COMFASUCRE: Bilinguismo: Mejoramiento De Las Habilidades Comunicativas Y Metodológicas En El Idioma Extranjero Ingles (BPIN: Por Gestión) (Meta del Proyecto: 150) (Ejecución 2024: 150) | AH45: Tour Lingüístico y Cultural 2025 (Tipo Banco: Banco de Gestiones) (Meta de la gestión: 483) Convenio Cuerpo de Paz (Tipo Banco: Banco de Gestiones) (Meta de la gestión: 1652) JEC–COMFASUCRE (Tipo Banco: Banco de Gestiones) (Meta de la gestión: 400) | AI45: Tour Lingüístico y Cultural 2025 (Tipo de banco: Banco de Gestiones) (Meta de la gestión: 483) (Ejecutado: 483) Convenio Cuerpo de Paz (Tipo de banco: Banco de Gestiones) (Meta de la gestión: 1652) (Ejecutado: 1652) JEC–COMFASUCRE (Tipo de banco: Banco de Gestiones) (Meta de la gestión: 400) (Ejecutado: 400) | AJ45: Elaboración del foro bilingüismo 2026 | AL45: Elaboración del foro bilingüismo 2027 (Bpin: ) | AM45: 6239 | AN45: 1 | AO45: Superior | AP45: 2535 | AQ45: 1 | AR45: Superior | AT45: 1 | AU45: Superior | AV45: 8774 | AW45: 1 | AX45: Superior | AY45: 125000000 | AZ45: 0 | BA45: 0 | BB45: 0 | BC45: 0 | BD45: 0 | BE45: 0 | BF45: 0 | BG45: 0 | BH45: 100000000 | BI45: 225000000 | BJ45: 125000000 | BK45: 0 | BL45: 0 | BM45: 0 | BN45: 0 | BO45: 0 | BP45: 0 | BQ45: 0 | BR45: 0 | BS45: 105000000 | BT45: 230000000 | BU45: 125000000 | BV45: 0 | BW45: 0 | BX45: 0 | BY45: 0 | BZ45: 0 | CA45: 0 | CB45: 0 | CC45: 0 | CD45: 110250000 | CE45: 235250000 | CF45: 125000000 | CG45: 0 | CH45: 0 | CI45: 0 | CJ45: 0 | CK45: 0 | CL45: 0 | CM45: 0 | CN45: 0 | CO45: 115762500 | CP45: 240762500 | CQ45: 931012500 | CR45: Se tiene previsto la realización del foro en el mes de noviembre | CS45: Fortalecer la alianza SENA, Gobernación de Sucre, Instituciones Educativas Técnicas Agropecuarias y alcaldías, estableciendo un Convenio Marco que impulse la sostenibilidad y ampliación de coberturas en los programas de articulación y doble titulación e i
A46: MT043 | B46: 9 | C46: Transformación del Ser Humano | D46: Cobertura Neta en educación - Total, Cobertura bruta en educación - Total | E46: 92% - 105,42% | F46: Porcentaje (Multiplicado por 100) | G46: 2022 | H46: MEN - OAPF La cobertura se estimó con proyección censo DANE 2018 | I46: 92%, 105,5% | J46: 4. Educación de calidad | K46: Educación | L46: 9 | M46: Oportunidades Educativas en Educación Inicial, Preescolar, Básica y Media | N46: Educación | O46: 22 | P46: Calidad, cobertura y fortalecimiento de la educación inicial, prescolar, básica y media | Q46: 2201 | R46: Servicio de articulación entre la educación media y el sector productivo | S46: 2201035 | T46: Programas y proyectos de educación pertinente articulados con el sector productivo. | U46: 220103500 | V46: Incluye el desarrollo de estrategias que vinculen la educación media con el sector productivo, que promuevan la pertinencia en la educación | W46: Número de programas y proyectos | X46: No | Y46: Número | Z46: 20 | AA46: No acumulativo | AB46: Secretaría de Educación | AC46: 20 | AD46: 20 | AE46: 20 | AF46: 20 | AG46: Convenio Doble Titulación con SENA, programas productivos en las IETAS adscritas a la ETC Sucre. (BPIN: Por Gestión) (Meta del Proyecto: 20) (Ejecución 2024: 20) | AH46: IMPLEMENTACIÓN DE UNA ESTRATEGIA DIRIGIDA A FOMENTAR LA PRODUCTIVIDAD AGRICOLA EN LAS INSTITUCIONES EDUCATIVAS TÉCNICO AGROPECUARIAS EN EL DEPARTAMENTO DE SUCRE (BPIN: 202500000041223) (Tipo de Banco: Banco Territorial) Convenio Doble Titulación con SENA, programas productivos en las IETAS adscritas a la ETC Sucre. 2025 (Banco de Gestiones) (Meta Programada: 20) (Meta Ejecutada: 20) | AI46: Implementación de una estrategia dirigida a fomentar la productividad agrícola en las instituciones educativas técnico agropecuarias en elDepartamento de Sucre (Bpin: 202500000041223) (Tipo de Banco: Banco Territorial) (Meta total del indicador: 1.0) (Meta total de la vigencia: 1.0) (Ejecutado: 1.0) Convenio Doble Titulación con SENA, programas productivos en las IETAS adscritas a la ETC Sucre. 2025 (Banco de Gestiones) (Meta Programada: 20) (Meta Ejecutada: 20) | AJ46: Convenio Sena Doble Titulación 2026 Convenio Doble Titulación con SENA, programas productivos en las IETAS adscritas a la ETC Sucre. 2025 (Meta Programada: 20) (Tipo de Banco: Banco de Gestiones) | AK46: Convenio Doble Titulación con SENA, programas productivos en las IETAS adscritas a la ETC Sucre. 2025 (Meta programada: 20) (Ejecución: 20) (Tipo de banco: Banco de Gestiones) | AL46: Convenio Sena Doble Titulación 2027 (Bpin: ) | AM46: 20 | AN46: 1 | AO46: Superior | AP46: 21 | AQ46: 1 | AR46: Superior | AS46: 20 | AT46: 1 | AU46: Superior | AV46: 61 | AW46: 1 | AX46: Superior | AY46: 110000000 | AZ46: 0 | BA46: 0 | BB46: 0 | BC46: 0 | BD46: 0 | BE46: 0 | BF46: 0 | BG46: 0 | BH46: 0 | BI46: 110000000 | BJ46: 115500000 | BK46: 0 | BL46: 0 | BM46: 0 | BN46: 0 | BO46: 0 | BP46: 0 | BQ46: 0 | BR46: 0 | BS46: 0 | BT46: 115500000 | BU46: 121275000 | BV46: 0 | BW46: 0 | BX46: 0 | BY46: 0 | BZ46: 0 | CA46: 0 | CB46: 0 | CC46: 0 | CD46: 0 | CE46: 121275000 | CF46: 115220000 | CG46: 0 | CH46: 0 | CI46: 0 | CJ46: 0 | CK46: 0 | CL46: 0 | CM46: 0 | CN46: 0 | CO46: 0 | CP46: 115220000 | CQ46: 461995000 | CR46: Se viene trabajando el los programas productivos en las IETAS adscritas a la ETC Sucre, es de resaltar que estos programas terminan una vez sean graduados los estudiantes aprendices, por lo que la meta se cumplira al fimnalizar el año escolar, (Por Gestión). | CS46: Gestionar los recursos económicos mediante el acceso a las convocatorias del orden internacional, nacional y regional para el fortalecimiento de los proyectos pedagógicos y productivos sostenibles en las IETAS del departamento. Incluye el desarrollo de es
A47: MT044 | B47: 10 | C47: Transformación del Ser Humano | D47: Cobertura Neta en educación - Total, Cobertura bruta en educación - Total | E47: 92% - 105,42% | F47: Porcentaje (Multiplicado por 100) | G47: 2022 | H47: MEN - OAPF La cobertura se estimó con proyección censo DANE 2018 | I47: 92%, 105,5% | J47: 4. Educación de calidad | K47: Educación | L47: 9 | M47: Oportunidades Educativas en Educación Inicial, Preescolar, Básica y Media | N47: Educación | O47: 22 | P47: Calidad, cobertura y fortalecimiento de la educación inicial, prescolar, básica y media | Q47: 2201 | R47: Servicios de asistencia técnica en innovación educativa en la educación inicial, preescolar, básica y media | S47: 2201046 | T47: Entidades o instituciones asistidas técnicamente en innovación educativa. | U47: 220104600 | V47: Es el servicio que se presta para generar y fortalecer la capacidad institucional de entidades públicas y privadas en temas de innovación educativa en la educación inicial, preescolar, básica y media | W47: Número de entidades | X47: No | Y47: Número | Z47: 5 | AA47: Acumulativo | AB47: Secretaría de Educación | AC47: 5 | AD47: 0 | AE47: 0 | AF47: 0 | AG47: Convenio de entendimiento con Tommy INC (BPIN: Por Gestión) (Meta del Proyecto: 5) (Ejecución 2024: 5) | AH47: Convenio de entendimiento con Tommy INC (Tipo Banco: Banco de Gestiones) (Meta de la gestión: ) | AJ47: Convenio de entendimiento con Tommy INC | AL47: Convenio de entendimiento con Tommy INC (Bpin: ) | AM47: 5 | AN47: 1 | AO47: Superior | AV47: 5 | AW47: 1 | AX47: Superior | AY47: 0 | AZ47: 0 | BA47: 0 | BB47: 0 | BC47: 0 | BD47: 0 | BE47: 50000000 | BF47: 0 | BG47: 0 | BH47: 0 | BI47: 50000000 | BJ47: 0 | BK47: 0 | BL47: 0 | BM47: 0 | BN47: 0 | BO47: 0 | BP47: 52500000 | BQ47: 0 | BR47: 0 | BS47: 0 | BT47: 52500000 | BU47: 0 | BV47: 0 | BW47: 0 | BX47: 0 | BY47: 0 | BZ47: 0 | CA47: 55125000 | CB47: 0 | CC47: 0 | CD47: 0 | CE47: 55125000 | CF47: 0 | CG47: 0 | CH47: 0 | CI47: 0 | CJ47: 0 | CK47: 0 | CL47: 57881250 | CM47: 0 | CN47: 0 | CO47: 0 | CP47: 57881250 | CQ47: 215506250 | CR47: Se adelanto la convocatoria para la inscripción de los tablecimientos educativos, a los cuales se espera brindar una asistencia técnica de 20 horas en modelos de innovación, se tiene previsto iniciar el 14 de octubre de 2024. | CS47: Gestionar los procesos de formación continua en el uso e implementación de prácticas de aula transformadoras y creativas que permitan potenciar el aprendizaje significativo de los estudiantes. Implementación de Piloto Maestro Tomi. Convenio de entendimie
A48: MT045 | B48: 11 | C48: Transformación del Ser Humano | D48: Cobertura Neta en educación - Total, Cobertura bruta en educación - Total | E48: 92% - 105,42% | F48: Porcentaje (Multiplicado por 100) | G48: 2022 | H48: MEN - OAPF La cobertura se estimó con proyección censo DANE 2018 | I48: 92%, 105,5% | J48: 4. Educación de calidad | K48: Educación | L48: 9 | M48: Oportunidades Educativas en Educación Inicial, Preescolar, Básica y Media | N48: Educación | O48: 22 | P48: Calidad, cobertura y fortalecimiento de la educación inicial, prescolar, básica y media | Q48: 2201 | R48: Servicios de apoyo a la implementación de modelos de innovación educativa | S48: 2201047 | T48: Establecimientos educativos apoyados para la implementación de modelos de innovación educativa. | U48: 220104700 | V48: Corresponde a la implementación de ideas, procesos y estrategias de innovación educativa en la educación inicial preescolar básica y media | W48: Número de establecimientos educativos | X48: No | Y48: Número | Z48: 5 | AA48: Acumulativo | AB48: Secretaría de Educación | AC48: 0 | AD48: 1 | AE48: 1 | AF48: 3 | AG48: Se entregó un equipo Tomi 8 al Centro Educativo Galapago Se entregaron 4 Tomi Routers: Institucion Educativa Las Palmas - Sede Principal Institucion Educativa Macajan - Sede Principal Institucion Educativa Normal Superior De La Mojana - Sede Principal Gei (BPIN: Por Gestión) (Meta del Proyecto: 5) (Ejecución 2024: 5) PROYECTO FORTALECIMIENTO DE LOS ESTABLECIMIENTOS EDUCATIVOS MEDIANTE EL PROGRAMA DE EDUCACION INCLUSIVA CON CALIDAD Y EQUIDAD PARA LA ATENCIÓN A LA DIVERSIDAD, DURANTE LA VIGENCIA 2024 EN EL DEPARTAMENTO DE SUCRE. (BPIN: 2023002700152) (Meta del Proyecto: 210) (Ejecución 2024: 215) | AH48: Fortalecimiento de los establecimientos educativos mediante el programa de educación inclusiva con calidad y equidad para la atención a estudiantes con discapacidad, capacidades y talentos excepcionales y atención a jóvenes del sistema de responsabilidad penal para adolescentes (SRPA) vigencia 2025 en el Departamento de Sucre (BPIN: 202500000019337) (Tipo de Banco: Banco Territorial) | AI48: Fortalecimiento de los establecimientos educativos mediante el programa de educación inclusiva con calidad y equidad para la atención a estudiantes con discapacidad, capacidades y talentos excepcionales y atención a jóvenes del sistema de responsabilidad penal para adolescentes (SRPA) vigencia 2025 en el Departamento de Sucre (Bpin: 202500000019337) (Tipo de Banco: Banco Territorial) (Meta total del indicador: 211.0) (Meta total de la vigencia: 211.0) (Ejecutado: 236.0) | AJ48: Gestionar los procesos de formación continua en el uso e implementación de prácticas de aula transformadoras y creativas que permitan potenciar el aprendizaje significativo de los estudiantes (Por Gestión). (BPIN: Por Gestión) | AM48: 220 | AN48: 1 | AO48: Superior | AP48: 236 | AQ48: 1 | AR48: Superior | AT48: 1 | AU48: Superior | AV48: 456 | AW48: 1 | AX48: Superior | AY48: 0 | AZ48: 0 | BA48: 0 | BB48: 0 | BC48: 0 | BD48: 0 | BE48: 50000000 | BF48: 0 | BG48: 300000000 | BH48: 50000000 | BI48: 400000000 | BJ48: 0 | BK48: 0 | BL48: 0 | BM48: 0 | BN48: 0 | BO48: 0 | BP48: 52500000 | BQ48: 0 | BR48: 700000000 | BS48: 52500000 | BT48: 805000000 | BU48: 0 | BV48: 0 | BW48: 0 | BX48: 0 | BY48: 0 | BZ48: 0 | CA48: 55125000 | CB48: 0 | CC48: 700000000 | CD48: 55125000 | CE48: 810250000 | CF48: 0 | CG48: 0 | CH48: 0 | CI48: 0 | CJ48: 0 | CK48: 0 | CL48: 0 | CM48: 0 | CN48: 300000000 | CO48: 57881250 | CP48: 357881250 | CQ48: 2373131250 | CR48: Se adelanto la convocatoria para la inscripción de los tablecimientos educativos, y se espera realizar la implementacion a 5 establecimientos educativos, posterior a la asistencia técnica en modelos de innovación educativa. | CS48: Gestionar los procesos de formación continua en el uso e implementación de prácticas de aula transformadoras y creativas que permitan potenciar el aprendizaje significativo de los estudiantes.
A49: MT046 | B49: 12 | C49: Transformación del Ser Humano | D49: Cobertura Neta en educación - Total, Cobertura bruta en educación - Total | E49: 92% - 105,42% | F49: Porcentaje (Multiplicado por 100) | G49: 2022 | H49: MEN - OAPF La cobertura se estimó con proyección censo DANE 2018 | I49: 92%, 105,5% | J49: 4. Educación de calidad | K49: Educación | L49: 9 | M49: Oportunidades Educativas en Educación Inicial, Preescolar, Básica y Media | N49: Educación | O49: 22 | P49: Calidad, cobertura y fortalecimiento de la educación inicial, prescolar, básica y media | Q49: 2201 | R49: Servicio de educación informal | S49: 2201049 | T49: Personas beneficiadas con procesos de formación informal | U49: 220104900 | V49: Corresponde a la oferta educativa informal como talleres, foros, capacitaciones presenciales o virtuales dirigida a los miembros de la comunidad educativa que tienen como objetivo brindar oportunidades para complementar, actualizar, perfeccionar, renovar o profundizar conocimientos, habilidades, técnicas y prácticas, este conocimiento libre y espontáneo adquirido, puede provenir de personas, entidades, medios masivos de comunicación, medios impresos, tradiciones, costumbres, comportamientos sociales y otros no estructurados y su duración es inferior a 160 horas. | W49: Número de personas | X49: No | Y49: Número | Z49: 3300 | AA49: Acumulativo | AB49: Secretaría de Educación | AC49: 1680 | AD49: 540 | AE49: 540 | AF49: 540 | AG49: APOYO A LA IMPLEMENTACIÓN DEL PROGRAMA PRENSA ESCUELA PARA EL FORTALECIMIENTO DE COMPETENCIAS INTEGRALES EN LOS ESTUDIANTES DE LOS ESTABLECIMIENTOS OFICIALES DE LOS MUNICIPIOS NO CERTIFICADOS DEL DEPARTAMENTO DE SUCRE (BPIN: 2024002700057) (Meta del Proyecto: 1680) (Ejecución 2024: 1680) APOYO A LOS PROCESOS DE BIENESTAR LABORAL Y CAPACITACION A DOCENTES, DIRECTIVOS DOCENTES Y ADMINISTRATIVOS DE LA SECRETARÍA DE EDUCACIÓN DEL DEPARTAMENTO DE SUCRE (BPIN: 2024002700128) (Meta del Proyecto: 3816) (Ejecución 2024: 2096) | AH49: APOYO A LA REALIZACION DEL FORO EDUCATIVO Y LOS DIFERENTES ENCUENTROS PEDAGOGICOS E INTERACTIVOS DE LA SECRETARIA DE EDUCACION DEPARTAMENTAL DE SUCRE (BPIN: 202500000029898) (Tipo de Banco: Banco Territorial) APOYO A LOS PROCESOS DE BIENESTAR LABORAL Y CAPACITACION A DOCENTES, DIRECTIVOS DOCENTES Y ADMINISTRATIVOS DE LA SECRETARÍA DE EDUCACIÓN DEL DEPARTAMENTO DE SUCRE (BPIN: 2024002700128) (Tipo de Banco: Banco Territorial) APOYO A LA IMPLEMENTACIÓN DEL PROGRAMA PRENSA ESCUELA PARA EL FORTALECIMIENTO DE COMPETENCIAS INTEGRALES EN LOS ESTUDIANTES DE LOS ESTABLECIMIENTOS EDUCATIVOS OFICIALES DE LOS MUNICIPIOS NO CERTIFICADOS PARA LA VIGENCIA 2025 DEL DEPARTAMENTO DE SUCRE (BPIN: 202400000004287) (Tipo de Banco: Banco Territorial) FORTALECIMIENTO A DOCENTES Y DIRECTIVOS DOCENTES EN COMPETENCIAS BÁSICAS, ESPECIFICAS, CIUDADANAS Y SOCIOEMOCIONALES DURANTE LA VIGENCIA 2025 EN EL DEPARTAMENTO DE SUCRE (BPIN: 202400000002259) (Tipo de Banco: Banco Territorial) | AI49: Apoyo a los procesos de bienestar laboral y capacitación a docentes directivos docentes y administrativos de la secretaria de educación del departamento de Sucre (Bpin: 2024002700128) (Tipo de Banco: Banco Territorial) (Meta total del indicador: 6723.0) (Meta total de la vigencia: 6723.0) (Ejecutado: 1540.0) Apoyo a la implementación del programa prensa escuela para el fortalecimiento de competencias integrales en los estudiantes de los establecimientos educativos oficiales de los municipios no certificados para la vigencia 2025 en el departamento Sucre (Bpin: 202400000004287) (Tipo de Banco: Banco Territorial) (Meta total del indicador: 1770.0) (Meta total de la vigencia: 1770.0) (Ejecutado: 1770.0) Apoyo a la realización del Foro Educativo y los diferentes encuentros pedagógicos e interactivos de la Secretaría de Educación Departamental de Sucre (Bpin: 202500000029898) (Tipo de Banco: Banco Territorial) (Meta total del indicador: 1200.0) (Meta total de la vigencia: 1200.0) (Ejecutado: 1200.0) Fortalecimiento a docentes y directivos docentes en competencias básicas, específicas, ciudadanas y socioemocionales durante la vigencia 2025 en el departamento de Sucre (Bpin: 202400000002259) (Tipo de Banco: Banco Territorial) (Meta total del indicador: 400.0) (Meta total de la vigencia: 400.0) (Ejecutado: 400.0) | AJ49: Apoyo A LOS PROCESOS DE BIENESTAR LABORAL Y CAPACITACIÓN A DOCENTES, DIRECTIVOS DOCENTES Y ADMNISTRATIVOS PARA LA VIGENCIA 2026 DE LA SECRETARIA DE EDUCACIÓN DEL DEPARTAMENTO DE Sucre (BPIN: 202500000049594) (Meta del proyecto: 1402) (Tipo de Banco: Banco Territorial) (Estado en Portafolio: Registrado en banco) Apoyo A LA IMPLEMENTACION DEL PROGRAMA PRENSA ESCUELA PARA EL FORTALECIMIENTO DE COMPETENCIAS INTEGRALES EN LOS ESTUDIANTES DE LOS ESTABLECIMIENTOS EDUCATIVOS OFICIALES DE 8 DE LOS MUNICIPIOS NO CERTIFICADOS, PARA LA VIGENCIA 2026 EN EL DEPARTAMENTO DE Sucre (BPIN: 202600000001437) (Meta del proyecto: 1452) (Tipo de Banco: Banco Territorial) (Estado en Portafolio: Registrado en banco) Fortalecimiento de las competencias comunicativas y transversales a través de la educación no formal en establecimientos educativos de los municipios no certificados del departamento de Sucre (BPIN: 202600000002945) (Meta del proyecto: 300) (Tipo de Banco: Banco Territorial) (Estado en Portafolio: Registrado en banco) APOYO A LA REALIZACIÓN DEL FORO EDUCATIVO Y LOS DIFERENTES ENCUENTROS PEDAGÓGICOS E INTERACTIVOS VIGENCIA 2026 DE LA SECRETARIA DE EDUCACIÓN DEPARTAMENTAL DE SUCRE. (BPIN: 202500000038478) (Meta del proyecto: 1200) (Tipo de Banco: Banco Territorial) APOYO A LA IMPLEMENTACIÓN DEL PROGRAMA PRENSA ESCUELA PARA EL FORTALECIMIENTO DE COMPETENCIAS INTEGRALES EN LOS ESTUDIANTES DE LOS ESTABLECIMIENTOS OFICIALES DE LOS MUNICIPIOS NO CERTIFICADOS DEL DEPARTAMENTO DE SUCRE | AL49: APOYO A LA IMPLEMENTACIÓN DEL PROGRAMA PRENSA ESCUELA PARA EL FORTALECIMIENTO DE COMPETENCIAS INTEGRALES EN LOS ESTUDIANTES DE LOS ESTABLECIMIENTOS OFICIALES DE LOS MUNICIPIOS NO CERTIFICADOS DEL DEPARTAMENTO DE SUCRE (Bpin: ) APOYO A LOS FOROS EDUCATIVOS PARA LA VIGENCIA 2027 EN EL DEPARTAMENTO DE SUCRE (Bpin: ) | AM49: 3776 | AN49: 1 | AO49: Superior | AP49: 4910 | AQ49: 1 | AR49: Superior | AT49: 1 | AU49: Superior | AV49: 8686 | AW49: 1 | AX49: Superior | AY49: 20000000 | AZ49: 0 | BA49: 690000000 | BB49: 0 | BC49: 0 | BD49: 0 | BE49: 0 | BF49: 0 | BG49: 0 | BH49: 0 | BI49: 710000000 | BJ49: 20000000 | BK49: 0 | BL49: 724500000 | BM49: 0 | BN49: 0 | BO49: 0 | BP49: 0 | BQ49: 0 | BR49: 0 | BS49: 0 | BT49: 744500000 | BU49: 20000000 | BV49: 0 | BW49: 760725000 | BX49: 0 | BY49: 0 | BZ49: 0 | CA49: 0 | CB49: 0 | CC49: 0 | CD49: 0 | CE49: 780725000 | CF49: 20000000 | CG49: 0 | CH49: 798761250 | CI49: 0 | CJ49: 0 | CK49: 0 | CL49: 0 | CM49: 0 | CN49: 0 | CO49: 0 | CP49: 818761250 | CQ49: 3053986250 | CR49: Se encuentra en ejecución el proyecto denominado APOYO A LA IMPLEMENTACIÓN DEL PROGRAMA PRENSA ESCUELA PARA EL FORTALECIMIENTO DE COMPETENCIAS INTEGRALES EN LOS ESTUDIANTES DE LOS ESTABLECIMIENTOS OFICIALES DE LOS MUNICIPIOS NO CERTIFICADOS DEL DEPARTAMENTO DE SUCRE (2024002700057), por medio del cual se benefician 1,680 estudiantes, con lo que se da cumplimiento a la meta. | CS49: Gestionar recursos y establecer alianzas público y privadas para cualificar a los docentes en los distintos enfoques de evaluación, especialmente en la evaluación formativa. Corresponde a la oferta educativa informal como talleres, foros, capacitaciones p
A50: MT047 | B50: 13 | C50: Transformación del Ser Humano | D50: Cobertura Neta en educación - Total, Cobertura bruta en educación - Total | E50: 92% - 105,42% | F50: Porcentaje (Multiplicado por 100) | G50: 2022 | H50: MEN - OAPF La cobertura se estimó con proyección censo DANE 2018 | I50: 92%, 105,5% | J50: 4. Educación de calidad | K50: Educación | L50: 9 | M50: Oportunidades Educativas en Educación Inicial, Preescolar, Básica y Media | N50: Educación | O50: 22 | P50: Calidad, cobertura y fortalecimiento de la educación inicial, prescolar, básica y media | Q50: 2201 | R50: Servicio de fortalecimiento a las capacidades de los docentes de educación Inicial, preescolar, básica y media | S50: 2201074 | T50: Docentes y agentes educativos de educación inicial, preescolar, básica y media beneficiados con estrategias de mejoramiento de sus capacidades | U50: 220107400 | V50: Incluye el apoyo prestado a docentes, directivos docentes y agentes educativos para la realización de estudios en los diferentes niveles educativos con el fin de que estos fortalezcan sus capacidades. | W50: Número de docentes y agentes educativos | X50: No | Y50: Número | Z50: 1500 | AA50: Acumulativo | AB50: Secretaría de Educación | AC50: 400 | AD50: 400 | AE50: 350 | AF50: 350 | AG50: Se adelantó diplomado con la IAFIT, beneficiándo 7 docentes, uno en herramientas TIC ejecutado por Celsia, Beneficiando 45 docentes. (BPIN: Por Gestión) (Meta del Proyecto: 400) (Ejecución 2024: 444) IMPLEMENTACIÓN PROGRAMA DE FORMACIÓN DE CAPACIDADES EN CIENCIA, TECNOLOGÍA E INNOVACIÓN EN EL DEPARTAMENTO DE SUCRE. (FORMACIÓN MAESTRIAS Y DOCTORADOS) (BPIN: 2013000100074) (Meta del Proyecto: ) (Ejecución 2024: ) | AH50: CAPACITACITACIONES – PRIMER ENCUENTRO DEPARTAMENTAL DE LÍDERES DE LA CONVIVENCIA ESCOLAR (Tipo Banco: Banco de Gestiones) (Meta de la gestión: 400) SEMINARIO DE RESOLUCIÓN DE CONFLICTOS ESCOLARES (Tipo Banco: Banco de Gestiones) (Meta de la gestión: 400) | AI50: CAPACITACITACIONES – PRIMER ENCUENTRO DEPARTAMENTAL DE LÍDERES DE LA CONVIVENCIA ESCOLAR (Tipo de banco: Banco de Gestiones) (Meta de la gestión: 400) (Ejecutado: 319) SEMINARIO DE RESOLUCIÓN DE CONFLICTOS ESCOLARES (Tipo de banco: Banco de Gestiones) (Meta de la gestión: 400) (Ejecutado: 210) | AJ50: Fortalecimiento en competencias gerenciales y de innovación en ciencias agropecuarias a directivos docentes y docentes de las Instituciones Educativas Técnicas Agropecuarias - IETA del Departamento de Sucre, Vigencia 2026 Sucre (BPIN: 202500000039142) (Meta del proyecto: 500) (Tipo de Banco: Banco Territorial) (Estado en Portafolio: Verificación de requisitos en banco) FORTALECIMIENTO A DOCENTES Y DIRECTIVOS DOCENTES EN COMPETENCIAS BÁSICAS, ESPECIFICAS, CIUDADANAS Y SOCIOEMOCIONALES DURANTE LA VIGENCIA 2026 EN EL DEPARTAMENTO DE SUCRE | AL50: FORTALECIMIENTO A DOCENTES Y DIRECTIVOS DOCENTES EN COMPETENCIAS BÁSICAS, ESPECIFICAS, CIUDADANAS Y SOCIOEMOCIONALES DURANTE LA VIGENCIA 2027 EN EL DEPARTAMENTO DE SUCRE (Bpin: ) | AM50: 444 | AN50: 1 | AO50: Superior | AP50: 529 | AQ50: 1 | AR50: Superior | AT50: 0 | AU50: Minimo | AV50: 973 | AW50: 0.64866667 | AX50: Alto | AY50: 0 | AZ50: 0 | BA50: 390000000 | BB50: 0 | BC50: 0 | BD50: 0 | BE50: 0 | BF50: 0 | BG50: 0 | BH50: 0 | BI50: 390000000 | BJ50: 0 | BK50: 0 | BL50: 409500000 | BM50: 0 | BN50: 0 | BO50: 0 | BP50: 0 | BQ50: 0 | BR50: 0 | BS50: 0 | BT50: 409500000 | BU50: 0 | BV50: 0 | BW50: 429975000 | BX50: 0 | BY50: 0 | BZ50: 0 | CA50: 0 | CB50: 0 | CC50: 0 | CD50: 0 | CE50: 429975000 | CF50: 0 | CG50: 0 | CH50: 451473750 | CI50: 0 | CJ50: 0 | CK50: 0 | CL50: 0 | CM50: 0 | CN50: 0 | CO50: 0 | CP50: 451473750 | CQ50: 1680948750 | CR50: Se esta adelantando un diplomado en pensamiento computacional con la IAFIT, mediante el cual se beneficiaran 62 docentes, de igual forma se esta adelantando un diplomado en formación en herramientas TIC financiados con recursos de obras por impuestos, ejecutado por el contribuyente Celsia, Beneficiando 45 docentes y 30 docentes mas beneficiados con el fondo francisco jose de caldas de CECAR. | CS50: Proyectos para el fortalecimiento a docentes y directivos docentes en competencias básicas, específicas, ciudadanas y socioemocionales en el departamento de Sucre.
A51: MT048 | B51: 14 | C51: Transformación del Ser Humano | D51: Cobertura Neta en educación - Total, Cobertura bruta en educación - Total | E51: 92% - 105,42% | F51: Porcentaje (Multiplicado por 100) | G51: 2022 | H51: MEN - OAPF La cobertura se estimó con proyección censo DANE 2018 | I51: 92%, 105,5% | J51: 4. Educación de calidad | K51: Educación | L51: 9 | M51: Oportunidades Educativas en Educación Inicial, Preescolar, Básica y Media | N51: Educación | O51: 22 | P51: Calidad, cobertura y fortalecimiento de la educación inicial, prescolar, básica y media | Q51: 2201 | R51: Servicio de evaluación de la calidad de la educación inicial, preescolar, básica y media | S51: 2201073 | T51: Estudiantes evaluados con pruebas de calidad educativa | U51: 220107300 | V51: Incluye el diseño, desarrollo, sistematización, análisis, proyección de resultados y demás procesos que permitan la aplicación y análisis de las pruebas de medición de la calidad educativa. Así mismo, Incluye el diseño, aplicación, procesamiento y calificación de resultados de un examen de práctica o simulacro de evaluación de la educación en territorio, estas acciones no son financiables con recursos provenientes del Sistema General de Participaciones. | W51: Número de estudiantes | X51: No | Y51: Número | Z51: 500 | AA51: Acumulativo | AB51: Secretaría de Educación | AC51: 0 | AD51: 0 | AE51: 250 | AF51: 250 | AJ51: Proyecto preicfes | AL51: Proyecto preicfes (Bpin: ) | AT51: 0 | AU51: Minimo | AV51: 0 | AW51: 0 | AX51: Minimo | AY51: 100000000 | AZ51: 0 | BA51: 0 | BB51: 0 | BC51: 0 | BD51: 0 | BE51: 0 | BF51: 0 | BG51: 0 | BH51: 0 | BI51: 100000000 | BJ51: 105000000 | BK51: 0 | BL51: 0 | BM51: 0 | BN51: 0 | BO51: 0 | BP51: 0 | BQ51: 0 | BR51: 0 | BS51: 0 | BT51: 105000000 | BU51: 110250000 | BV51: 0 | BW51: 0 | BX51: 0 | BY51: 0 | BZ51: 0 | CA51: 0 | CB51: 0 | CC51: 0 | CD51: 0 | CE51: 110250000 | CF51: 115762500 | CG51: 0 | CH51: 0 | CI51: 0 | CJ51: 0 | CK51: 0 | CL51: 0 | CM51: 0 | CN51: 0 | CO51: 0 | CP51: 115762500 | CQ51: 431012500 | CS51: Incluye el diseño, desarrollo, sistematización, análisis, proyección de resultados y demás procesos que permitan la aplicación y análisis de las pruebas de medición de la calidad educativa. Así mismo, Incluye el diseño, aplicación, procesamiento y calific
A52: MT049 | B52: 15 | C52: Transformación del Ser Humano | D52: Cobertura Neta en educación - Total, Cobertura bruta en educación - Total | E52: 92% - 105,42% | F52: Porcentaje (Multiplicado por 100) | G52: 2022 | H52: MEN - OAPF La cobertura se estimó con proyección censo DANE 2018 | I52: 92%, 105,5% | J52: 4. Educación de calidad | K52: Educación | L52: 9 | M52: Oportunidades Educativas en Educación Inicial, Preescolar, Básica y Media | N52: Educación | O52: 22 | P52: Calidad, cobertura y fortalecimiento de la educación inicial, prescolar, básica y media | Q52: 2201 | R52: Servicio de accesibilidad a contenidos web para fines pedagógicos | S52: 2201050 | T52: Estudiantes con acceso a contenidos web en el establecimiento educativo. | U52: 220105000 | V52: Corresponde a la instalación del servicio de internet en los establecimientos educativos para fines pedagógicos | W52: Número de estudiantes | X52: No | Y52: Número | Z52: 117000 | AA52: Acumulativo | AB52: Secretaría de Educación | AC52: 55558 | AD52: 20481 | AE52: 20481 | AF52: 20480 | AG52: IMPLEMENTACIÓN DE LA ESTRATEGIA DE CONECTIVIDAD ESCOLAR – CONEXIÓN TOTAL – DEL MINISTERIO DE EDUCACIÓN NACIONAL VIGENCIA 2024 EN ESTABLECIMIENTOS Y/O SEDES EDUCATIVAS OFICIALES DE LOS MUNICIPIOS NO CERTIFICADOS DEL DEPARTAMENTO DE SUCRE (BPIN: 2024002700047) (Meta del Proyecto: 55558) (Ejecución 2024: 55558) | AH52: IMPLEMENTACIÓN DE LA ESTRATEGIA DE CONECTIVIDAD ESCOLARDURANTE LA VIGENCIA 2025 EN ESTABLECIMIENTOS Y/O SEDES EDUCATIVAS DEL DEPARTAMENTO DE SUCRE. (BPIN: 202500000027014) (Tipo de Banco: Banco Territorial) | AI52: Implementación de la estrategia de conectividad escolar durante la vigencia 2025 en establecimientos y/o sedes educativas del departamento de Sucre (Bpin: 202500000027014) (Tipo de Banco: Banco Territorial) (Meta total del indicador: 66087.0) (Meta total de la vigencia: 66087.0) (Ejecutado: 66087.0) | AJ52: IMPLEMENTACIÓN DE UNA ESTRATEGIA DE CONECTIVIDAD ESCOLAR DURANTE LA VIGENCIA 2026 EN ESTABLECIMIENTOS Y/O SEDES EDUCATIVAS OFICIALES DEL DEPARTAMENTO DE SUCRE. (BPIN: 202500000037457) (Meta del proyecto: 33758) (Tipo de Banco: Banco Territorial) (Estado en Portafolio: En estudios previos) Implementación de la estrategia de conectividad escolar del ministerio de educación nacional vigencia 2026 en establecimientos y/o sedes educativas de los municipios no certificados del departamento de Sucre (BPIN: 202600000007022) (Meta del proyecto: 54199) (Tipo de Banco: Banco Territorial) | AL52: IMPLEMENTACIÓN DE LA ESTRATEGIA DE CONECTIVIDAD ESCOLAR – CONEXIÓN TOTAL – DEL MINISTERIO DE EDUCACIÓN NACIONAL VIGENCIA 2027 EN ESTABLECIMIENTOS Y/O SEDES EDUCATIVAS OFICIALES DE LOS MUNICIPIOS NO CERTIFICADOS DEL DEPARTAMENTO DE SUCRE. (Bpin: ) | AM52: 55558 | AN52: 1 | AO52: Superior | AP52: 66087 | AQ52: 1 | AR52: Superior | AT52: 1 | AU52: Superior | AV52: 121645 | AW52: 1 | AX52: Superior | AY52: 0 | AZ52: 0 | BA52: 1797277135 | BB52: 0 | BC52: 0 | BD52: 0 | BE52: 0 | BF52: 0 | BG52: 0 | BH52: 0 | BI52: 1797277135 | BJ52: 0 | BK52: 0 | BL52: 1.887141e+09 | BM52: 0 | BN52: 0 | BO52: 0 | BP52: 0 | BQ52: 0 | BR52: 0 | BS52: 0 | BT52: 1.887141e+09 | BU52: 0 | BV52: 0 | BW52: 1.981498e+09 | BX52: 0 | BY52: 0 | BZ52: 0 | CA52: 0 | CB52: 0 | CC52: 0 | CD52: 0 | CE52: 1.981498e+09 | CF52: 0 | CG52: 0 | CH52: 2.0805729e+09 | CI52: 0 | CJ52: 0 | CK52: 0 | CL52: 0 | CM52: 0 | CN52: 0 | CO52: 0 | CP52: 2.0805729e+09 | CQ52: 7.7464891e+09 | CR52: 08-08-2024: El proyecto fue contratado el día 19 de julio de 2024 12/08/2024 PROYECTO CIB ACTA DE INICIO DEL 29/04/2024 | CS52: Corresponde a la instalación del servicio de internet en los establecimientos educativos para fines pedagógicos. Proyecto Implementación de La Estrategia de Conectividad Escolar – Conexión Total – del Ministerio de Educación Nacional Vigencia 2024 En Esta
A53: MT050 | B53: 16 | C53: Transformación del Ser Humano | D53: Cobertura Neta en educación - Total, Cobertura bruta en educación - Total | E53: 92% - 105,42% | F53: Porcentaje (Multiplicado por 100) | G53: 2022 | H53: MEN - OAPF La cobertura se estimó con proyección censo DANE 2018 | I53: 92%, 105,5% | J53: 4. Educación de calidad | K53: Educación | L53: 9 | M53: Oportunidades Educativas en Educación Inicial, Preescolar, Básica y Media | N53: Educación | O53: 22 | P53: Calidad, cobertura y fortalecimiento de la educación inicial, prescolar, básica y media | Q53: 2201 | R53: Servicio de acompañamiento para el desarrollo de modelos educativos interculturales | S53: 2201056 | T53: Modelos educativos acompañados | U53: 220105600 | V53: Incluye las acciones de acompañamiento en la construcción concertada y participativa de las fases de los modelos educativos: formulación, diseño y ajuste e implementación. | W53: Número de modelos | X53: No | Y53: Número | Z53: 1 | AA53: Acumulativo | AB53: Secretaría de Educación | AC53: 0 | AD53: 0 | AE53: 0 | AF53: 1 | AH53: Acompañamiento para la implementación de un modelo educativo intercultural (Tipo Banco: Banco de Gestiones) (Meta de la gestión: 1) | AI53: Acompañamiento para la implementación de un modelo educativo intercultural (Tipo de banco: Banco de Gestiones) (Meta de la gestión: 1) (Ejecutado: 5) | AJ53: Acompañamiento para la implementación de un modelo educativo intercultural | AL53: Acompañamiento para la implementación de un modelo educativo intercultural (Bpin: ) | AP53: 5 | AQ53: 1 | AR53: Superior | AV53: 5 | AW53: 1 | AX53: Superior | AY53: 50000000 | AZ53: 0 | BA53: 0 | BB53: 0 | BC53: 0 | BD53: 0 | BE53: 0 | BF53: 0 | BG53: 0 | BH53: 0 | BI53: 50000000 | BJ53: 52500000 | BK53: 0 | BL53: 0 | BM53: 0 | BN53: 0 | BO53: 0 | BP53: 0 | BQ53: 0 | BR53: 0 | BS53: 0 | BT53: 52500000 | BU53: 55125000 | BV53: 0 | BW53: 0 | BX53: 0 | BY53: 0 | BZ53: 0 | CA53: 0 | CB53: 0 | CC53: 0 | CD53: 0 | CE53: 55125000 | CF53: 57881250 | CG53: 0 | CH53: 0 | CI53: 0 | CJ53: 0 | CK53: 0 | CL53: 0 | CM53: 0 | CN53: 0 | CO53: 0 | CP53: 57881250 | CQ53: 215506250 | CS53: Establecer alianzas entre el MEN, secretarias de educación e instituciones educativas oficiales para resignificar los proyectos educativos institucionales PEI a proyectos educativos y/o etnoeducativos comunitarios PEC.
A54: MT051 | B54: 17 | C54: Transformación del Ser Humano | D54: Cobertura Neta en educación - Total, Cobertura bruta en educación - Total | E54: 92% - 105,42% | F54: Porcentaje (Multiplicado por 100) | G54: 2022 | H54: MEN - OAPF La cobertura se estimó con proyección censo DANE 2018 | I54: 92%, 105,5% | J54: 4. Educación de calidad | K54: Educación | L54: 9 | M54: Oportunidades Educativas en Educación Inicial, Preescolar, Básica y Media | N54: Educación | O54: 22 | P54: Calidad, cobertura y fortalecimiento de la educación inicial, prescolar, básica y media | Q54: 2201 | R54: Servicio educativo de promoción del bilingüismo para docentes | S54: 2201060 | T54: Docentes beneficiados con estrategias de promoción del bilingüismo. | U54: 220106000 | V54: Se refiere a los procesos y planes de formación docente que posibiliten el aprendizaje o mejoramiento del dominio del nivel de una lengua extranjera, el mejoramiento de las prácticas de aula, la renovación metodológica para la enseñanza de otras lenguas y el fomento a la implementación del currículo sugerido de otros idiomas. | W54: Número de docentes | X54: No | Y54: Número | Z54: 100 | AA54: Acumulativo | AB54: Secretaría de Educación | AC54: 0 | AD54: 30 | AE54: 30 | AF54: 40 | AG54: Asistencia de docentes al foro de bilingüismo 2024 (BPIN: Por Gestión) (Meta del Proyecto: 150) (Ejecución 2024: 150) Asistencia docentes al Tour linguistico y cultural 2024 (BPIN: Por Gestión) (Meta del Proyecto: 187) (Ejecución 2024: 187) CAPACITACION docentes - Webinar IA y aprendizaje de idiomas (BPIN: Por Gestión) (Meta del Proyecto: 24) (Ejecución 2024: 24) docentes formados con ALIANZA - ITALIA- COLOMBIA (BPIN: Por Gestión) (Meta del Proyecto: 2) (Ejecución 2024: 2) | AH54: Formación bilingüe para docentes (Tipo Banco: Banco de Gestiones) (Meta de la gestión: 102) | AI54: Formación bilingüe para docentes (Tipo de banco: Banco de Gestiones) (Meta de la gestión: 102) (Ejecutado: 102) | AJ54: Formación bilingüe para docentes | AL54: Formación bilingüe para docentes (Bpin: ) | AM54: 363 | AN54: 1 | AO54: Superior | AP54: 102 | AQ54: 1 | AR54: Superior | AT54: 1 | AU54: Superior | AV54: 465 | AW54: 1 | AX54: Superior | AY54: 30000000 | AZ54: 0 | BA54: 0 | BB54: 0 | BC54: 0 | BD54: 0 | BE54: 0 | BF54: 0 | BG54: 0 | BH54: 0 | BI54: 30000000 | BJ54: 0 | BK54: 0 | BL54: 0 | BM54: 0 | BN54: 0 | BO54: 0 | BP54: 0 | BQ54: 0 | BR54: 0 | BS54: 0 | BT54: 0 | BU54: 0 | BV54: 0 | BW54: 0 | BX54: 0 | BY54: 0 | BZ54: 0 | CA54: 0 | CB54: 0 | CC54: 0 | CD54: 0 | CE54: 0 | CF54: 0 | CG54: 0 | CH54: 0 | CI54: 0 | CJ54: 0 | CK54: 0 | CL54: 0 | CM54: 0 | CN54: 0 | CO54: 0 | CP54: 0 | CQ54: 30000000 | CS54: Realizar a través de alianzas público y privada los procesos de formación continua en una segunda lengua a los docentes de bilingüismo y dotar las instituciones educativas con aulas interactivas bilingües e interculturales.
A55: MT052 | B55: 18 | C55: Transformación del Ser Humano | D55: Cobertura Neta en educación - Total, Cobertura bruta en educación - Total | E55: 92% - 105,42% | F55: Porcentaje (Multiplicado por 100) | G55: 2022 | H55: MEN - OAPF La cobertura se estimó con proyección censo DANE 2018 | I55: 92%, 105,5% | J55: 4. Educación de calidad | K55: Educación | L55: 9 | M55: Oportunidades Educativas en Educación Inicial, Preescolar, Básica y Media | N55: Educación | O55: 22 | P55: Calidad, cobertura y fortalecimiento de la educación inicial, prescolar, básica y media | Q55: 2201 | R55: Servicio de apoyo a proyectos pedagógicos productivos | S55: 2201061 | T55: Establecimientos educativos beneficiados | U55: 220106100 | V55: Corresponden al apoyo financiero o en especie para la implementación de proyectos pedagógicos productivos. | W55: Número de establecimientos educativos | X55: No | Y55: Número | Z55: 20 | AA55: Acumulativo | AB55: Secretaría de Educación | AC55: 0 | AD55: 8 | AE55: 7 | AF55: 5 | AH55: Convenio Doble Titulación con SENA, programas productivos en las IETAS adscritas a la ETC Sucre. 2025 (Tipo Banco: Banco de Gestiones) (Meta de la gestión: 20) Gestionar los recursos económicos mediante el acceso a las convocatorias del orden internacional, nacional y regional para el fortalecimiento de los proyectos pedagógicos y productivos sostenibles en las IETAS del departamento. (Tipo Banco: Banco de Gestiones) (Meta de la gestión: 8) | AI55: Convenio Doble Titulación con SENA, programas productivos en las IETAS adscritas a la ETC Sucre. 2025 (Tipo de banco: Banco de Gestiones) (Meta de la gestión: 20) (Ejecutado: 20) | AJ55: Gestionar los recursos económicos mediante el acceso a las convocatorias del orden internacional, nacional y regional para el fortalecimiento de los proyectos pedagógicos y productivos sostenibles en las IETAS del departamento. Incluye el desarrollo de es | AL55: Gestionar los recursos económicos mediante el acceso a las convocatorias del orden internacional, nacional y regional para el fortalecimiento de los proyectos pedagógicos y productivos sostenibles en las IETAS del departamento. Incluye el desarrollo de es (Bpin: ) | AP55: 20 | AQ55: 1 | AR55: Superior | AT55: 1 | AU55: Superior | AV55: 20 | AW55: 1 | AX55: Superior | AY55: 0 | AZ55: 0 | BA55: 0 | BB55: 0 | BC55: 0 | BD55: 0 | BE55: 0 | BF55: 0 | BG55: 0 | BH55: 0 | BI55: 0 | BJ55: 0 | BK55: 0 | BL55: 0 | BM55: 0 | BN55: 0 | BO55: 0 | BP55: 0 | BQ55: 0 | BR55: 0 | BS55: 0 | BT55: 0 | BU55: 0 | BV55: 0 | BW55: 0 | BX55: 0 | BY55: 0 | BZ55: 0 | CA55: 0 | CB55: 0 | CC55: 0 | CD55: 0 | CE55: 0 | CF55: 0 | CG55: 0 | CH55: 0 | CI55: 0 | CJ55: 0 | CK55: 0 | CL55: 0 | CM55: 0 | CN55: 0 | CO55: 0 | CP55: 0 | CQ55: 0 | CS55: Gestionar los recursos económicos mediante el acceso a las convocatorias del orden internacional, nacional y regional para el fortalecimiento de los proyectos pedagógicos y productivos sostenibles en las IETAS del departamento. Incluye el desarrollo de es
A56: MT053 | B56: 19 | C56: Transformación del Ser Humano | D56: Cobertura Neta en educación - Total, Cobertura bruta en educación - Total | E56: 92% - 105,42% | F56: Porcentaje (Multiplicado por 100) | G56: 2022 | H56: MEN - OAPF La cobertura se estimó con proyección censo DANE 2018 | I56: 92%, 105,5% | J56: 4. Educación de calidad | K56: Educación | L56: 9 | M56: Oportunidades Educativas en Educación Inicial, Preescolar, Básica y Media | N56: Educación | O56: 22 | P56: Calidad, cobertura y fortalecimiento de la educación inicial, prescolar, básica y media | Q56: 2201 | R56: Estudios de preinversión | S56: 2201063 | T56: Estudios o diseños realizados | U56: 220106300 | V56: Incluye la realización de los estudios requeridos en las fases de pre factibilidad, factibilidad o definitivos. | W56: Número de estudios y diseños | X56: No | Y56: Número | Z56: 2 | AA56: Acumulativo | AB56: Secretaría de Educación | AC56: 0 | AD56: 0 | AE56: 1 | AF56: 1 | AJ56: La meta fue incluida para financiar la preinversión de proyectos de infraestructura que cumplan con las metas del plan de desarrollo. Actualmente no se tiene proyecto en formulación | AL56: La meta fue incluida para financiar la preinversión de proyectos de infraestructura que cumplan con las metas del plan de desarrollo. Actualmente no se tiene proyecto en formulación (Bpin: ) | AT56: 0 | AU56: Minimo | AV56: 0 | AW56: 0 | AX56: Minimo | AY56: 125000000 | AZ56: 0 | BA56: 0 | BB56: 0 | BC56: 0 | BD56: 0 | BE56: 0 | BF56: 0 | BG56: 0 | BH56: 0 | BI56: 125000000 | BJ56: 125000000 | BK56: 0 | BL56: 0 | BM56: 0 | BN56: 0 | BO56: 0 | BP56: 0 | BQ56: 0 | BR56: 0 | BS56: 0 | BT56: 125000000 | BU56: 125000000 | BV56: 0 | BW56: 0 | BX56: 0 | BY56: 0 | BZ56: 0 | CA56: 0 | CB56: 0 | CC56: 0 | CD56: 0 | CE56: 125000000 | CF56: 125000000 | CG56: 0 | CH56: 0 | CI56: 0 | CJ56: 0 | CK56: 0 | CL56: 0 | CM56: 0 | CN56: 0 | CO56: 0 | CP56: 125000000 | CQ56: 500000000 | CS56: Impulso de acciones encaminadas a la elaboración de estudios de preinversión y/o ampliar y mejorar la infraestructura educativa y su dotación. Ambientes de aprendizajes, laboratorios y comedores escolares.
A57: MT054 | B57: 20 | C57: Transformación del Ser Humano | D57: Cobertura Neta en educación - Total, Cobertura bruta en educación - Total | E57: 92% - 105,42% | F57: Porcentaje (Multiplicado por 100) | G57: 2022 | H57: MEN - OAPF La cobertura se estimó con proyección censo DANE 2018 | I57: 92%, 105,5% | J57: 4. Educación de calidad | K57: Educación | L57: 9 | M57: Oportunidades Educativas en Educación Inicial, Preescolar, Básica y Media | N57: Educación | O57: 22 | P57: Calidad, cobertura y fortalecimiento de la educación inicial, prescolar, básica y media | Q57: 2201 | R57: Servicio de evaluación para docentes | S57: 2201064 | T57: Docentes evaluados | U57: 220106400 | V57: Incluye la realización de evaluaciones que permitan valorar las competencias de los docentes. | W57: Número de docentes | X57: No | Y57: Número | Z57: 1900 | AA57: No acumulativo | AB57: Secretaría de Educación | AC57: 1900 | AD57: 1900 | AE57: 1900 | AF57: 1900 | AG57: Evaluación anual realizada a docentes y directivos docentes (BPIN: Por Gestión) (Meta del Proyecto: 1900) (Ejecución 2024: 1750) | AH57: Evaluación anual realizada a docentes y directivos docente (Tipo Banco: Banco de Gestiones) (Meta de la gestión: 1900) | AI57: Evaluación anual realizada a docentes y directivos docente (Tipo de banco: Banco de Gestiones) (Meta de la gestión: 1900) (Ejecutado: 1931) | AJ57: Gestión - Evaluación anual realizada a docentes y directivos docente | AL57: Gestión - Evaluación anual realizada a docentes y directivos docente (Bpin: ) | AM57: 1750 | AN57: 0.92105263 | AO57: Alto | AP57: 1931 | AQ57: 1 | AR57: Superior | AT57: 0 | AU57: Minimo | AV57: 3681 | AW57: 1 | AX57: Superior | AY57: 0 | AZ57: 0 | BA57: 0 | BB57: 0 | BC57: 0 | BD57: 0 | BE57: 0 | BF57: 0 | BG57: 0 | BH57: 0 | BI57: 0 | BJ57: 0 | BK57: 0 | BL57: 0 | BM57: 0 | BN57: 0 | BO57: 0 | BP57: 0 | BQ57: 0 | BR57: 0 | BS57: 0 | BT57: 0 | BU57: 0 | BV57: 0 | BW57: 0 | BX57: 0 | BY57: 0 | BZ57: 0 | CA57: 0 | CB57: 0 | CC57: 0 | CD57: 0 | CE57: 0 | CF57: 0 | CG57: 0 | CH57: 0 | CI57: 0 | CJ57: 0 | CK57: 0 | CL57: 0 | CM57: 0 | CN57: 0 | CO57: 0 | CP57: 0 | CQ57: 0 | CR57: Estas evaluaciones estan programadas para iniciar a finales de octubre y su culminación el 7 de diciembre, con lo que se cumpliria la meta. | CS57: Gestionar los mecanismos institucionales necesarios a través de los distintos actores del sistema educativo para implementar el Plan Decenal de Educación con criterios de Eficiencia, Eficacia, Innovación y Sostenibilidad.
